Workbook

Sheet 組合名簿
A1: No | B1: 氏名 | C1: メールアドレス | D1: ステータス | E1: 契約書送付日 | F1: 契約締結日 | G1: 役職 | H1: 会社 | I1: 入会者区分 | J1: LINE名 | K1: 電話番号 | L1: 住所 | M1: 紹介者 | N1: 備考 | O1: メモ | P1: documentID | Q1: クラウドサインURL | R1: リマインド回数 | S1: (旧契約書) ステータス | T1: (旧契約書) 契約書送付日 | U1: (旧契約書) 契約締結日 | V1: (旧契約書) documentID | W1: (旧契約書) クラウドサインURL | X1: (旧契約書) リマインド回数 | Y1: 訂正メール
A2: 1 | B2: 坂井 博俊 | C2: h.sakai@value-frontier.jp | D2: 契約書送付済 | E2: 46106.805 | G2: 代表取締役会長 | H2: VF | M2: バリューフロンティア | P2: 01mw7dm0xc0vc2kgjs71xjtmxra9z14r | R2: 1 | S2: 契約書送付済 | T2: 46038 | U2: 破棄処理 | Y2: 済み
A3: =IF(B3="","",COUNTA($B$2:B3)) -> 2 | B3: 大塚崇司 | C3: t.otsuka@value-frontier.jp | D3: 契約書送付済 | E3: 46106.805 | G3: 代表取締役社長 | H3: VF | P3: 01mw7dmcxwxj06hz4bexyyt7k6x2q095 | R3: 1 | S3: 組合員契約書締結 | T3: 46038 | U3: 46038 | Y3: 済み
A4: =IF(B4="","",COUNTA($B$2:B4)) -> 3 | B4: 菅原宗紀（すがわらむねのり） | C4: m.sugawara@value-frontier.jp | D4: 組合員契約書締結 | E4: 46106.805 | F4: 46106.843 | G4: 営業 | H4: VF | P4: 01mw7dmyvw7e06yk03t0wb1bdsxpbgrj | Q4: https://www.cloudsign.jp/document/01mw7dmyvw7e06yk03t0wb1bdsxpbgrj/summary | S4: 組合員契約書締結 | T4: 46039 | U4: 46040 | Y4: 済み
A5: =IF(B5="","",COUNTA($B$2:B5)) -> 4 | B5: 小山大貴（こやまだいき） | C5: d.koyama@value-frontier.jp | D5: 組合員契約書締結 | E5: 46106.805 | F5: 46114.697 | G5: 営業 | H5: VF | P5: 01mw7dnftgss41apy7akj1xk54vw8n42 | Q5: https://www.cloudsign.jp/document/01mw7dnftgss41apy7akj1xk54vw8n42/summary | R5: 1 | S5: 組合員契約書締結 | T5: 46039 | U5: 46042 | Y5: 済み
A6: =IF(B6="","",COUNTA($B$2:B6)) -> 5 | B6: 本岡 佳大（もとおかよしひろ） | C6: y.motooka@value-frontier.jp | D6: 契約書送付済 | E6: 46106.808 | G6: 営業 | H6: VF | P6: 01mw7dw7xjhsgsbtpndz8kgqvy79rg52 | R6: 1 | S6: 組合員契約書締結 | T6: 46039 | U6: 46042 | Y6: 済み
A7: =IF(B7="","",COUNTA($B$2:B7)) -> 6 | B7: 中村 友昭（なかむらともあき） | C7: t.nakamura@value-frontier.jp | D7: 組合員契約書締結 | E7: 46106.808 | F7: 46107.335 | G7: 営業 | H7: VF | P7: 01mw7dwedgt1ax422tby764vkvq4mjb1 | Q7: https://www.cloudsign.jp/document/01mw7dwedgt1ax422tby764vkvq4mjb1/summary | S7: 組合員契約書締結 | T7: 46039 | U7: 46040 | Y7: 済み
A8: =IF(B8="","",COUNTA($B$2:B8)) -> 7 | B8: 岡山 愛紗実（おかやまあさみ） | C8: a.okayama@value-frontier.jp | D8: 契約書送付済 | E8: 46106.808 | G8: 営業 | H8: VF | P8: 01mw7dwkxjq33avewrckfest31f4jb51 | R8: 1 | S8: 組合員契約書締結 | T8: 46039 | U8: 46042 | Y8: 済み
A9: =IF(B9="","",COUNTA($B$2:B9)) -> 8 | B9: 堀内 信宏（ほりうちのぶひろ） | C9: n.horiuchi@value-frontier.jp | D9: 組合員契約書締結 | E9: 46106.808 | F9: 46106.816 | G9: 営業 | H9: VF | P9: 01mw7dwsarv5jsd5pvccmcgrfe7yh1sk | Q9: https://www.cloudsign.jp/document/01mw7dwsarv5jsd5pvccmcgrfe7yh1sk/summary | S9: 組合員契約書締結 | T9: 46039 | U9: 46040 | Y9: 済み
A10: =IF(B10="","",COUNTA($B$2:B10)) -> 9 | B10: 久家 梨瑶（クヤ リヨウ） | C10: r.shinohara@value-frontier.jp | D10: 組合員契約書締結 | E10: 46106.808 | F10: 46106.854 | G10: 営業 | H10: VF | P10: 01mw7dx0qqwf99qgfqzdzc9p2vt351w8 | Q10: https://www.cloudsign.jp/document/01mw7dx0qqwf99qgfqzdzc9p2vt351w8/summary | S10: 組合員契約書締結 | T10: 46041 | U10: 46041 | Y10: 済み
A11: =IF(B11="","",COUNTA($B$2:B11)) -> 10 | B11: 野村 巡（ノムラ ジュン） | C11: j.nomura@value-frontier.jp | D11: 契約書送付済 | E11: 46106.808 | G11: 営業 | H11: VF | P11: 01mw7dx77efqj1vzdkbk7v2x8j78r4fr | R11: 1 | S11: 組合員契約書締結 | T11: 46041 | U11: 46041 | Y11: 済み
A12: =IF(B12="","",COUNTA($B$2:B12)) -> 11 | B12: 日髙 圭（ヒダカ ケイ） | C12: k.hidaka@value-frontier.jp | D12: 組合員契約書締結 | E12: 46106.808 | F12: 46114.73 | G12: 営業 | H12: VF | P12: 01mw7dxcrbd9cgwyd1gkc3wtx2g6qfks | Q12: https://www.cloudsign.jp/document/01mw7dxcrbd9cgwyd1gkc3wtx2g6qfks/summary | R12: 1 | S12: 組合員契約書締結 | T12: 46041 | U12: 46042 | Y12: 済み
A13: =IF(B13="","",COUNTA($B$2:B13)) -> 12 | B13: 田中創作 | C13: sousaku0113@gmail.com | D13: 契約書送付済 | E13: 46106.808 | G13: 理事 | H13: Nuクリニック | P13: 01mw7dxhbzxt424n588n0sr92weqfrr9 | R13: 1 | S13: 組合員契約書締結 | T13: 46039 | U13: 46040 | Y13: 済み
A14: =IF(B14="","",COUNTA($B$2:B14)) -> 13 | B14: 新沼直哉 | C14: niinumanaoya@sedent.co.jp | D14: 組合員契約書締結 | E14: 46106.808 | F14: 46114.769 | G14: 代表取締役社長 | H14: 株式会社セキムラ | P14: 01mw7dxqadpx492s6e3d9zy5kmcmhqxd | Q14: https://www.cloudsign.jp/document/01mw7dxqadpx492s6e3d9zy5kmcmhqxd/summary | R14: 1 | S14: 組合員契約書締結 | T14: 46039 | U14: 46040 | Y14: 済み
A15: =IF(B15="","",COUNTA($B$2:B15)) -> 14 | B15: 木村久美子 | C15: kimura@sedent.co.jp | D15: 不要データ | H15: 新沼さんと同じ会社 | S15: 契約破棄 | T15: 46039
A16: =IF(B16="","",COUNTA($B$2:B16)) -> 15 | B16: 川添恭伯 | C16: y.kawazoe@coaris.co.jp | D16: 組合員契約書締結 | E16: 46106.808 | F16: 46108.419 | G16: 代表取締役社長 | P16: 01mw7dxx2vb5bvsbfej54vcemahdhv71 | Q16: https://www.cloudsign.jp/document/01mw7dxx2vb5bvsbfej54vcemahdhv71/summary | S16: 組合員契約書締結 | T16: 46040 | U16: 46040 | Y16: 済み
A17: =IF(B17="","",COUNTA($B$2:B17)) -> 16 | B17: 渡邉勝紀 | C17: k.watanabe@kotonohamarketing.com | D17: 組合員契約書締結 | E17: 46106.808 | F17: 46107.406 | H17: スタイルエッジ | P17: 01mw7dy3ga388jq27yp89vbe45n4g40a | Q17: https://www.cloudsign.jp/document/01mw7dy3ga388jq27yp89vbe45n4g40a/summary | S17: 組合員契約書締結 | T17: 46041 | U17: 46044 | Y17: 済み
A18: =IF(B18="","",COUNTA($B$2:B18)) -> 17 | B18: 鈴木孝一郎 | C18: swimno1.516@gmail.com | D18: 契約書送付済 | E18: 46106.808 | G18: 弊社 | H18: Stella | P18: 01mw7dy81kcjq8dted7pfkpqz4reybh9 | R18: 1 | S18: 組合員契約書締結 | T18: 46042 | U18: 46042 | Y18: 済み
A19: =IF(B19="","",COUNTA($B$2:B19)) -> 18 | B19: 高畑智弘 | C19: takahata@ensolu.jp | D19: 契約書送付済 | E19: 46106.808 | G19: 代表取締役/セールスコンサルタント ブランディング戦略プロデューサー | H19: 株式会社エンジン&ソリューションズ | P19: 01mw7dyfz5cfnqdt2maxm8g6abbx2tsq | R19: 1 | S19: 組合員契約書締結 | T19: 46042 | U19: 46042 | Y19: 済み
A20: =IF(B20="","",COUNTA($B$2:B20)) -> 19 | B20: 井久保 大介 | C20: d.ikubo@pricom.jp | D20: 契約書送付済 | E20: 46106.808 | G20: 代表者 | H20: 株式会社プリコム | M20: バリューフロンティア | O20: 2/18再送 | P20: 01mw7dyvtst5f529skmmq8zcaggaye7w | R20: 1 | S20: 組合員契約書締結 | T20: 46042 | U20: 46071 | Y20: 済み
A21: =IF(B21="","",COUNTA($B$2:B21)) -> 20 | B21: 大津山裕介 | C21: yusuke-otsuyama@new-create.jp | D21: 契約書送付済 | E21: 46106.812 | G21: 代表者 | H21: 株式会社NEWCREATE | M21: バリューフロンティア | P21: 01mw7eapx2ff3ta6hx8ft29qnsve4r06 | R21: 1 | S21: 契約破棄 | T21: 46042 | U21: 破棄処理 | V21: 01mpy6wnt70mvc4v6f3zjtvrcd50rxv2 | X21: 4 | Y21: 済み
A22: =IF(B22="","",COUNTA($B$2:B22)) -> 21 | B22: 草野純広 | C22: utopia5571@gmail.com | D22: 契約書送付済 | E22: 46106.808 | G22: 代表者 | H22: 株式会社ＴＲＩＰ | M22: バリューフロンティア | O22: 2/18再送 | P22: 01mw7dz479h608n4h6t8xh10j55s8drq | R22: 1 | S22: 組合員契約書締結 | T22: 46042 | U22: 46071 | Y22: 済み
A23: =IF(B23="","",COUNTA($B$2:B23)) -> 22 | B23: 花田誉宜 | C23: aspo@office.email.ne.jp | D23: 組合員契約書締結 | E23: 46106.808 | F23: 46112.424 | G23: 代表者 | H23: aspo株式会社 | M23: バリューフロンティア | P23: 01mw7dz9segxe9415y4npz9rjpjm9ad4 | Q23: https://www.cloudsign.jp/document/01mw7dz9segxe9415y4npz9rjpjm9ad4/summary | S23: 組合員契約書締結 | T23: 46042 | U23: 46042 | Y23: 済み
A24: =IF(B24="","",COUNTA($B$2:B24)) -> 23 | B24: 菊池 幸宏 | C24: miyatozipapa@me.com | D24: 契約書送付済 | E24: 46106.808 | P24: 01mw7dzfm6vy1aycd25actcj76797740 | R24: 1 | S24: 組合員契約書締結 | T24: 46043 | U24: 46045 | Y24: 済み
A25: =IF(B25="","",COUNTA($B$2:B25)) -> 24 | B25: 石田敏之 | C25: ishida1410@gmail.com | D25: 契約書送付済 | E25: 46106.808 | P25: 01mw7dznmvn5q92k5t1yxf20qs7w86wz | R25: 1 | S25: 組合員契約書締結 | T25: 46043 | U25: 46044 | Y25: 済み
A26: =IF(B26="","",COUNTA($B$2:B26)) -> 25 | B26: 吉川 泰一 | C26: y.yoshikawa@aragan-group.com | D26: 契約書送付済 | E26: 46106.809 | P26: 01mw7dzvsk7853ram1gx9x61ngy8zcrd | R26: 1 | S26: 組合員契約書締結 | T26: 46043 | U26: 46050 | Y26: 済み
A27: =IF(B27="","",COUNTA($B$2:B27)) -> 26 | B27: 有馬恵樹 | C27: mcstbm@gmail.com | D27: 組合員契約書締結 | E27: 46106.809 | F27: 46106.83 | P27: 01mw7e038cfwwcpjn9z7pqqg50rzxtfa | Q27: https://www.cloudsign.jp/document/01mw7e038cfwwcpjn9z7pqqg50rzxtfa/summary | S27: 組合員契約書締結 | T27: 46043 | U27: 46045 | Y27: 済み
A28: =IF(B28="","",COUNTA($B$2:B28)) -> 27 | B28: 森光朝陽 | C28: llihc.ital51@gmail.com | D28: 契約書送付済 | E28: 46106.809 | G28: AS | P28: 01mw7e08qnj7kw2m5j91d2xxhccrc6k3 | R28: 1 | S28: 組合員契約書締結 | T28: 46042 | U28: 46043 | Y28: 済み
A29: =IF(B29="","",COUNTA($B$2:B29)) -> 28 | B29: 川満惇平 | C29: jkkjjunpei@gmail.com | D29: 契約書送付済 | E29: 46106.809 | G29: AS | P29: 01mw7e0e52h8ttps2v2e4qgfzmed6eba | R29: 1 | S29: 組合員契約書締結 | T29: 46042 | U29: 46043 | Y29: 済み
A30: =IF(B30="","",COUNTA($B$2:B30)) -> 29 | B30: 天野来海 | C30: amnkrm01@gmail.com | D30: 組合員契約書締結 | E30: 46106.809 | F30: 46111.608 | G30: AS | P30: 01mw7e0mtfynr5gh512nen1jgfpwe6w7 | Q30: https://www.cloudsign.jp/document/01mw7e0mtfynr5gh512nen1jgfpwe6w7/summary | S30: 組合員契約書締結 | T30: 46042 | U30: 46043 | Y30: 済み
A31: =IF(B31="","",COUNTA($B$2:B31)) -> 30 | B31: 尾崎由紀 | C31: xocuvw5735@yahoo.co.jp | D31: 組合員契約書締結 | E31: 46106.809 | F31: 46106.812 | G31: 理事 | P31: 01mw7e0w0jw9nrvd98a69tk5t12j0t7n | Q31: https://www.cloudsign.jp/document/01mw7e0w0jw9nrvd98a69tk5t12j0t7n/summary | S31: 組合員契約書締結 | T31: 46041 | U31: 46042 | Y31: 済み
A32: =IF(B32="","",COUNTA($B$2:B32)) -> 31 | B32: 芝田陽祐 | C32: clover.lcozz@gmail.com | D32: 契約書送付済 | E32: 46106.809 | O32: 再送※2026/1/25 | P32: 01mw7e12ytfc3v1p75cstbg3f8wk3z0w | R32: 1 | S32: 組合員契約書締結 | T32: 46044 | U32: 46049 | Y32: 済み
A33: =IF(B33="","",COUNTA($B$2:B33)) -> 32 | B33: 村主健太 | C33: kenta1721@gmail.com | D33: 契約書送付済 | E33: 46106.809 | O33: 再送※2026/1/26 | P33: 01mw7e182dckv8gdr0tz6178k2dbzfzv | R33: 1 | S33: 組合員契約書締結 | T33: 46044 | U33: 46048 | Y33: 済み
A34: 33 | B34: 木原卓男 | C34: kihara@mirai-support-center.org | D34: 契約書未送付 | E34: 46106.812 | P34: 01mw7eaw2cnmvye3r0n5t7sa06jt09ht | R34: 1 | S34: 契約破棄 | T34: 46044 | U34: 破棄処理 | V34: 01mq3grmv4gpmh1xck0244jnfb4qmx4c | X34: 4 | Y34: 済み
A35: =IF(B35="","",COUNTA($B$2:B35)) -> 34 | B35: 田岡春幸 | C35: taoka0415@gmail.com | D35: 契約書送付済 | E35: 46106.813 | G35: 顧問・代表者 | H35: ヒューマンリスクマネジメント株式会社 | P35: 01mw7eb11jz5h7cjavrbv1vbjpasggtt | R35: 1 | S35: 組合員契約書締結 | T35: 46044 | U35: 46044 | Y35: 済み
A36: =IF(B36="","",COUNTA($B$2:B36)) -> 35 | B36: 斎藤充 | C36: saito@gs-payment.co.jp | D36: 契約書送付済 | E36: 46106.809 | P36: 01mw7e1jn3ervjsnkxe7s91hsgn5xf01 | R36: 1 | S36: 組合員契約書締結 | T36: 46047 | U36: 46055 | Y36: 済み
A37: =IF(B37="","",COUNTA($B$2:B37)) -> 36 | B37: 島倉優奈 | C37: tinyisland117@gmail.com | D37: 組合員契約書締結 | E37: 46106.81 | F37: 46113.437 | H37: Stella | P37: 01mw7e1r4c65ms2ymzsc05q1tmn2yyge | Q37: https://www.cloudsign.jp/document/01mw7e1r4c65ms2ymzsc05q1tmn2yyge/summary | S37: 組合員契約書締結 | T37: 46048 | U37: 46048 | Y37: 済み
A38: =IF(B38="","",COUNTA($B$2:B38)) -> 37 | B38: 塩澤和真 | C38: kazuma.shiozawa0816@gmail.com | D38: 組合員契約書締結 | E38: 46106.81 | F38: 46106.973 | P38: 01mw7e1ypwca6bazf1k3843gjax329q9 | Q38: https://www.cloudsign.jp/document/01mw7e1ypwca6bazf1k3843gjax329q9/summary | S38: 組合員契約書締結 | T38: 46048 | U38: 46049 | Y38: 済み
A39: =IF(B39="","",COUNTA($B$2:B39)) -> 38 | B39: 町田太朗 | C39: taro.machida@airx.co.jp | D39: 契約書送付済 | E39: 46106.81 | G39: コーポレート部門Director | H39: 株式会社AirX | P39: 01mw7e23d5nkz8gy5992prdsnjjkhf19 | R39: 1 | S39: 契約破棄 | T39: 46049 | U39: 破棄処理 | V39: 01mqgvakjnrpynqzdvagwjp6d0d5pexj | X39: 4 | Y39: 済み
A40: =IF(B40="","",COUNTA($B$2:B40)) -> 39 | B40: 福栄祐吾 | C40: yugo@airx.co.jp | D40: 契約書送付済 | E40: 46106.81 | G40: コーポレート部門人事部長 | H40: 株式会社AirX | P40: 01mw7e29y5h2kf44en62c7c97j9hk2ex | R40: 1 | S40: 契約破棄 | T40: 46049 | U40: 破棄処理 | V40: 01mqgvhcsc2b4swe1x84knqkk4wtc69s | X40: 4 | Y40: 済み
A41: =IF(B41="","",COUNTA($B$2:B41)) -> 40 | B41: 久保崎由佳 | C41: yuka.kubosaki@gmail.com | D41: 契約書送付済 | E41: 46106.81 | P41: 01mw7e2fngwkh0jftq4jhtd1kabyvz6f | R41: 1 | S41: 組合員契約書締結 | T41: 46049 | U41: 46050 | Y41: 済み
A42: =IF(B42="","",COUNTA($B$2:B42)) -> 41 | B42: 峰山勝成 | C42: mineyama@sunshine-cc.jp | D42: 契約書送付済 | E42: 46106.81 | G42: 担当者 | H42: 株式会社 宮崎サンシャイン | M42: バリューフロンティア | P42: 01mw7e2na8k24mk2gjyqbz2b2t5ej8ss | R42: 1 | S42: 組合員契約書締結 | T42: 46049 | U42: 46072 | Y42: 済み
A43: =IF(B43="","",COUNTA($B$2:B43)) -> 42 | B43: 松山祐樹 | C43: matsuyama@princematsuyama.co.jp | D43: 組合員契約書締結 | E43: 46106.81 | F43: 46114.507 | G43: 担当者 | H43: 有限会社プリンス松山美容室 | M43: バリューフロンティア | O43: 2/18再送 | P43: 01mw7e2vvr79asxdjxdvs3qqvsdr9pg7 | Q43: https://www.cloudsign.jp/document/01mw7e2vvr79asxdjxdvs3qqvsdr9pg7/summary | R43: 1 | S43: 組合員契約書締結 | T43: 46051 | U43: 46071 | Y43: 済み
A44: =IF(B44="","",COUNTA($B$2:B44)) -> 43 | B44: 郡ゆかり | C44: yukari.Koori@gmail.com | D44: 契約書送付済 | E44: 46106.81 | G44: 担当者 | H44: 有限会社郡組 | M44: バリューフロンティア | P44: 01mw7e31bhz4cgp52rzx4rx7jgmtjpff | R44: 1 | S44: 組合員契約書締結 | T44: 46050 | U44: 46053 | Y44: 済み
A45: =IF(B45="","",COUNTA($B$2:B45)) -> 44 | B45: 谷川裕一朗 | C45: thc-one@peace.ocn.ne.jp | D45: 契約書送付済 | E45: 46106.81 | G45: 代表 | H45: 株式会社熊本電算 | M45: バリューフロンティア | P45: 01mw7e35fr6xbyjgqma01fynqf51n0n6 | R45: 1 | S45: 組合員契約書締結 | T45: 46051 | U45: 46051 | Y45: 済み
A46: =IF(B46="","",COUNTA($B$2:B46)) -> 45 | B46: 齋藤吟史 | C46: sginji3110@gmail.com | D46: 契約書送付済 | E46: 46106.81 | H46: Stella | P46: 01mw7e3b9s9yqzjnmjsbfpeaj5mq74d5 | R46: 1 | S46: 組合員契約書締結 | T46: 46052 | U46: 46097.436 | V46: 01mqr9w8ye3ahxy8v2fqsaphfmcx63he | W46: https://www.cloudsign.jp/document/01mqr9w8ye3ahxy8v2fqsaphfmcx63he/summary | X46: 4 | Y46: 済み
A47: =IF(B47="","",COUNTA($B$2:B47)) -> 46 | B47: 堂坂京平 | C47: kd2486r@gmail.com | D47: 契約書送付済 | E47: 46106.81 | H47: Stella | P47: 01mw7e3gp2gqt2r1bnwehws4tfd45n70 | R47: 1 | S47: 契約破棄 | T47: 46052 | U47: 破棄処理 | V47: 01mqra6pa1kve5dffe28q0s5t38493m2 | X47: 4 | Y47: 済み
A48: =IF(B48="","",COUNTA($B$2:B48)) -> 47 | B48: 鈴木孝一郎 | C48: swimno1.516@gmail.com | D48: 不要データ | H48: Stella | S48: 契約書送付済 | T48: 46052
A49: =IF(B49="","",COUNTA($B$2:B49)) -> 48 | B49: 堀口駿輔 | C49: hori.shun17@gmail.com | D49: 組合員契約書締結 | E49: 46106.81 | F49: 46107.512 | H49: Stella | P49: 01mw7e3nqrf8atcc7yhssvykdg93kzz7 | Q49: https://www.cloudsign.jp/document/01mw7e3nqrf8atcc7yhssvykdg93kzz7/summary | S49: 組合員契約書締結 | T49: 46052 | U49: 46052 | Y49: 済み
A50: =IF(B50="","",COUNTA($B$2:B50)) -> 49 | B50: 宮原大輔 | C50: m.bigs.0613@gmail.com | D50: 組合員契約書締結 | E50: 46106.81 | F50: 46111.868 | H50: Stella | P50: 01mw7e3tzq8016zgrfs33j4sfjq8300q | Q50: https://www.cloudsign.jp/document/01mw7e3tzq8016zgrfs33j4sfjq8300q/summary | S50: 組合員契約書締結 | T50: 46052 | U50: 46052 | Y50: 済み
A51: =IF(B51="","",COUNTA($B$2:B51)) -> 50 | B51: 飯塚隆之介 | C51: wara.ika46@gmail.com | D51: 契約書送付済 | E51: 46106.81 | H51: Stella | P51: 01mw7e402n7evakpw19a43x79s7an0fd | R51: 1 | S51: 組合員契約書締結 | T51: 46052 | U51: 46052 | Y51: 済み
A52: =IF(B52="","",COUNTA($B$2:B52)) -> 51 | B52: 内藤充希 | C52: 6n2m2n6@gmail.com | D52: 組合員契約書締結 | E52: 46106.81 | F52: 46107.442 | H52: Stella | P52: 01mw7e46hhwhms9nmrhwzz61kgmr7rft | Q52: https://www.cloudsign.jp/document/01mw7e46hhwhms9nmrhwzz61kgmr7rft/summary | S52: 契約破棄 | T52: 46052 | U52: 破棄処理 | V52: 01mqrbpcmyv62cg38sp6kd2d3p4yggyf | Y52: 済み
A53: =IF(B53="","",COUNTA($B$2:B53)) -> 52 | B53: 手塚直也 | C53: naoyatezuka1203@gmail.com | D53: 契約書送付済 | E53: 46106.81 | H53: Stella | P53: 01mw7e4bw4pja3bevx3djy1n3q6rgczx | R53: 1 | S53: 契約破棄 | T53: 46052 | U53: 破棄処理 | V53: 01mqrbtkdzz49a673vepm9kzabr4h15k | Y53: 済み
A54: =IF(B54="","",COUNTA($B$2:B54)) -> 53 | B54: 大村悠仁 | C54: gkmulaji0815@gmail.com | D54: 契約書送付済 | E54: 46106.81 | H54: Stella | P54: 01mw7e4n1xcmtbarebkgy8azkjqf22pz | R54: 1 | S54: 組合員契約書締結 | T54: 46052 | U54: 46052 | Y54: 済み
A55: =IF(B55="","",COUNTA($B$2:B55)) -> 54 | B55: 岩崎鈴未 | C55: suu.00015@gmail.com | D55: 契約書送付済 | E55: 46106.81 | H55: Stella | P55: 01mw7e4vg104fjayacnsvfpq599ae670 | R55: 1 | S55: 組合員契約書締結 | T55: 46052 | U55: 46052 | Y55: 済み
A56: =IF(B56="","",COUNTA($B$2:B56)) -> 55 | B56: 今川将文 | C56: kotomikense2@gmail.com | D56: 組合員契約書締結 | E56: 46106.81 | F56: 46114.558 | G56: 代表 | H56: KOTOMI GROUP | P56: 01mw7e50s35hf594bxhwdyj1qs80d0cy | Q56: https://www.cloudsign.jp/document/01mw7e50s35hf594bxhwdyj1qs80d0cy/summary | R56: 1 | S56: 組合員契約書締結 | T56: 46052 | U56: 46055 | Y56: 済み
A57: =IF(B57="","",COUNTA($B$2:B57)) -> 56 | B57: 花蜜幸伸 | C57: hana@sekaiheiwa.jp | D57: 契約書送付済 | E57: 46106.81 | P57: 01mw7e565fcb30nwgysnb7rz24ak0amh | R57: 1 | S57: 組合員契約書締結 | T57: 46052 | U57: 46055 | Y57: 済み
A58: =IF(B58="","",COUNTA($B$2:B58)) -> 57 | B58: 大江広満 | C58: hiromitsu@megumi-jimusho.jp | D58: 契約書送付済 | E58: 46106.81 | H58: 株式会社セキムラの顧問社労士 | P58: 01mw7e5ca9pyfvjappaz8qr2aq899bm3 | R58: 1 | S58: 組合員契約書締結 | T58: 46055 | U58: 46059 | Y58: 済み
A59: =IF(B59="","",COUNTA($B$2:B59)) -> 58 | B59: 加藤敦士 | C59: kato@ryg.co.jp | D59: 契約書送付済 | E59: 46106.811 | H59: 株式会社 MILLIMANIA | P59: 01mw7e5hb7j7rmxmngrqmkyymdee4znn | R59: 1 | S59: 組合員契約書締結 | T59: 46056 | U59: 46056 | Y59: 済み
A60: =IF(B60="","",COUNTA($B$2:B60)) -> 59 | B60: 上野剛 | C60: ueno@ryg.co.jp | D60: 契約書送付済 | E60: 46106.811 | H60: 株式会社 MILLIMANIA | P60: 01mw7e5qzm9a3gazrxske8b06511gmsz | R60: 1 | S60: 組合員契約書締結 | T60: 46056 | U60: 46056 | Y60: 済み
A61: =IF(B61="","",COUNTA($B$2:B61)) -> 60 | B61: 杉本誠 | C61: cerezoline@outlook.jp | D61: 契約書送付済 | E61: 46106.811 | H61: CEREZOLINE株式会社 | M61: バリューフロンティア | P61: 01mw7e5w2yb01z1apdm8da44y4r0fc4v | R61: 1 | S61: 契約破棄 | T61: 46057 | U61: 破棄処理 | V61: 01mr599vka65qpr8cf14b669vyc76p7n | Y61: 済み
A62: =IF(B62="","",COUNTA($B$2:B62)) -> 61 | B62: 谷健太郎 | C62: taniken@at-office.co.jp | D62: 契約書送付済 | E62: 46106.811 | H62: アットオフィス | P62: 01mw7e62gmf5v6zw69c13pwg0ye8346s | R62: 1 | S62: 組合員契約書締結 | T62: 46058 | U62: 46058 | Y62: 済み
A63: =IF(B63="","",COUNTA($B$2:B63)) -> 62 | B63: 田村航 | C63: tamura@ai-shigyo.or.jp | D63: 組合員契約書締結 | E63: 46106.811 | F63: 46106.836 | P63: 01mw7e67f0j2msvppcf9e6x08t56sm7y | Q63: https://www.cloudsign.jp/document/01mw7e67f0j2msvppcf9e6x08t56sm7y/summary | S63: 組合員契約書締結 | T63: 46058 | U63: 46058 | Y63: 済み
A64: =IF(B64="","",COUNTA($B$2:B64)) -> 63 | B64: 田畑裕也 | C64: kichi.ku.tabata@gmail.com | D64: 契約書送付済 | E64: 46106.811 | P64: 01mw7e6cahznqsjqrjjdfedxc8xwrb55 | R64: 1 | S64: 組合員契約書締結 | T64: 46058 | U64: 46072 | Y64: 済み
A65: =IF(B65="","",COUNTA($B$2:B65)) -> 64 | B65: 青柳朋樺 | C65: kichi.ku.aoyagi@gmail.com | D65: 契約書送付済 | E65: 46106.811 | P65: 01mw7e6kkaxb58gw8ans3ne6krpr50pe | R65: 1 | S65: 契約破棄 | T65: 46058 | U65: 破棄処理 | V65: 01mr7z646kqq9sa3gkne2pny5kkhk3gw | Y65: 済み
A66: =IF(B66="","",COUNTA($B$2:B66)) -> 65 | B66: 石﨑真 | C66: ishizaki@c-partners.co.jp | D66: 組合員契約書締結 | E66: 46106.811 | F66: 46107.01 | P66: 01mw7e6ry19qctw26838xp5yb4c7mvfb | Q66: https://www.cloudsign.jp/document/01mw7e6ry19qctw26838xp5yb4c7mvfb/summary | S66: 組合員契約書締結 | T66: 46058 | U66: 46064 | Y66: 済み
A67: =IF(B67="","",COUNTA($B$2:B67)) -> 66 | B67: 山口達朗 | C67: t.yamaguchi@g-w-j.co.jp | D67: 契約書送付済 | E67: 46106.811 | G67: 取締役 | H67: 株式会社Good Work Japan | P67: 01mw7e6y0hhxpjbhp7fj26zejzpmhfsm | R67: 1 | S67: 組合員契約書締結 | T67: 46059 | U67: 46059 | Y67: 済み
A68: =IF(B68="","",COUNTA($B$2:B68)) -> 67 | B68: 吉田惇一 | C68: j.y@g-w-j.co.jp | D68: 組合員契約書締結 | E68: 46106.813 | F68: 46114.451 | P68: 01mw7eb7gd2ft4n7j4w673vwe0vastgp | Q68: https://www.cloudsign.jp/document/01mw7eb7gd2ft4n7j4w673vwe0vastgp/summary | R68: 1 | S68: 組合員契約書締結 | T68: 46059 | U68: 46059 | Y68: 済み
A69: =IF(B69="","",COUNTA($B$2:B69)) -> 68 | B69: 内田恭平 | C69: ukyou666666@gmail.com | D69: 組合員契約書締結 | E69: 46106.813 | F69: 46114.63 | P69: 01mw7ebdjjw202f2y5wtcerghv36yv8y | Q69: https://www.cloudsign.jp/document/01mw7ebdjjw202f2y5wtcerghv36yv8y/summary | R69: 1 | S69: 組合員契約書締結 | T69: 46059 | U69: 46059 | Y69: 済み
A70: =IF(B70="","",COUNTA($B$2:B70)) -> 69 | B70: 根本光一 | C70: nemoto.k33@gmail.com | D70: 契約書送付済 | E70: 46106.813 | P70: 01mw7ebmt3jh78zpbfyt68mca280tzh1 | R70: 1 | S70: 組合員契約書締結 | T70: 46059 | U70: 46059 | Y70: 済み
A71: =IF(B71="","",COUNTA($B$2:B71)) -> 70 | B71: 植倉弘智 | C71: hirotomouekura1915111@gmail.com | D71: 契約書送付済 | E71: 46106.813 | P71: 01mw7ebsyrzk5xm3y7gm9hmnyw3r7q6w | R71: 1 | S71: 組合員契約書締結 | T71: 46059 | U71: 46059 | Y71: 済み
A72: =IF(B72="","",COUNTA($B$2:B72)) -> 71 | B72: 望月和義 | C72: 3s3.cube@gmail.com | D72: 契約書送付済 | E72: 46106.813 | P72: 01mw7ebzsew8932pgyacmt9x644nxhm8 | R72: 1 | S72: 組合員契約書締結 | T72: 46062 | U72: 46062 | Y72: 済み
A73: =IF(B73="","",COUNTA($B$2:B73)) -> 72 | B73: 上沖和己 | C73: kamioki19@olive.plala.or.jp | D73: 契約書送付済 | E73: 46106.813 | G73: 代表 | H73: 株式会社上沖産業 | M73: バリューフロンティア | P73: 01mw7ec5w0c3dthszme4rc8hknq0jg2r | R73: 1 | S73: 組合員契約書締結 | T73: 46062 | U73: 46069 | Y73: 済み
A74: =IF(B74="","",COUNTA($B$2:B74)) -> 73 | B74: 藤尾謙太 | C74: kenta.fujio.0811@gmail.com | D74: 契約書送付済 | E74: 46106.813 | H74: リアンクリニック | P74: 01mw7ecbzx0hprk7pft4djxcf75t0hbb | R74: 1 | S74: 組合員契約書締結 | T74: 46064 | U74: 46064 | Y74: 済み
A75: =IF(B75="","",COUNTA($B$2:B75)) -> 74 | B75: 姫宮光一 | C75: himemiya@kasoku.co.jp | D75: 契約書送付済 | E75: 46106.813 | H75: カソク株式会社 | P75: 01mw7ech7fh2ejgnfypkq66c65a6anx4 | R75: 1 | S75: 組合員契約書締結 | T75: 46066 | U75: 46066 | Y75: 済み
A76: =IF(B76="","",COUNTA($B$2:B76)) -> 75 | B76: 周郷海 | C76: kai.sugo.1@gmail.com | D76: 契約書送付済 | E76: 46106.813 | H76: 株式会社keytable | M76: バリューフロンティア | P76: 01mw7ecqk07s9jxw2v08w8y87nh03pcc | R76: 1 | S76: 契約破棄 | T76: 46066 | U76: 破棄処理 | V76: 01mrx2n9er8ak6td6k72m1pxj1dggwr6 | Y76: 済み
A77: =IF(B77="","",COUNTA($B$2:B77)) -> 76 | B77: 今井直紀 | C77: imai@imf.gr.jp | D77: 組合員契約書締結 | E77: 46106.814 | F77: 46107.483 | G77: 代表 | H77: IMF株式会社 | M77: バリューフロンティア | P77: 01mw7ecwa7et6b2nstjs18bhekh6myz8 | Q77: https://www.cloudsign.jp/document/01mw7ecwa7et6b2nstjs18bhekh6myz8/summary | S77: 組合員契約書締結 | T77: 46069 | U77: 46090 | Y77: 済み
A78: =IF(B78="","",COUNTA($B$2:B78)) -> 77 | B78: 田實誠幸 | C78: sudaku.88@gmail.com | D78: 契約書送付済 | E78: 46106.814 | G78: 代表 | H78: 株式会社S.Bホールディングス | M78: バリューフロンティア | P78: 01mw7ed2ted2c4msskcszt9y0c5gycty | R78: 1 | S78: 組合員契約書締結 | T78: 46069 | U78: 46069 | Y78: 済み
A79: =IF(B79="","",COUNTA($B$2:B79)) -> 78 | B79: 増田えりか | C79: erika1126@e-top-clinic.net | D79: 契約書送付済 | E79: 46106.814 | H79: イートップクリニック | P79: 01mw7ed8ez3are1nwm0vamrdcqvytkh2 | R79: 1 | S79: 組合員契約書締結 | T79: 46069 | U79: 46069 | Y79: 済み
A80: =IF(B80="","",COUNTA($B$2:B80)) -> 79 | B80: 石上文之 | C80: contact@otokojuku.biz | D80: 組合員契約書締結 | E80: 46106.814 | F80: 46106.936 | H80: 株式会社やってみる | P80: 01mw7edeq5c3w5nf3t1pxc5f3xffvh18 | Q80: https://www.cloudsign.jp/document/01mw7edeq5c3w5nf3t1pxc5f3xffvh18/summary | S80: 組合員契約書締結 | T80: 46070 | U80: 46072 | Y80: 済み
A81: =IF(B81="","",COUNTA($B$2:B81)) -> 80 | B81: 遠藤雄太 | C81: y.endo@drtraining.jp | D81: 契約書送付済 | E81: 46106.814 | G81: 人事担当 | H81: ドクタートレーニング | P81: 01mw7edm2x1t129ckwznrky42tr9f4t7 | R81: 1 | S81: 組合員契約書締結 | T81: 46070 | U81: 46070 | Y81: 済み
A82: =IF(B82="","",COUNTA($B$2:B82)) -> 81 | B82: 杉本清和 | C82: k-sugimoto@sugimoto-shika.com | D82: 契約書送付済 | E82: 46106.814 | H82: 医療法人社団ハピネス | P82: 01mw7edtpkdjfffdjq5s0m60wsgxap1t | R82: 1 | S82: 契約破棄 | T82: 46070 | U82: 破棄処理 | V82: 01ms7qaqd17407eyqznx9n3vmx2mf7b1 | Y82: 済み
A83: =IF(B83="","",COUNTA($B$2:B83)) -> 82 | B83: 姫野憲一 | C83: himeno@ac-create.jp | D83: 組合員契約書締結 | E83: 46106.814 | F83: 46106.882 | H83: 株式会社エーシークリエイト | P83: 01mw7ee0t61dfwttz7jejejdhbphsncn | Q83: https://www.cloudsign.jp/document/01mw7ee0t61dfwttz7jejejdhbphsncn/summary | S83: 契約破棄 | T83: 46070 | U83: 破棄処理 | V83: 01ms7qs5b1e2etdmqgfk5eyfg77jmtcs | Y83: 済み
A84: =IF(B84="","",COUNTA($B$2:B84)) -> 83 | B84: 山越健司 | C84: k-yamakoshi@value-advisers.co.jp | D84: 契約書送付済 | E84: 46106.814 | H84: 株式会社会社バリューアドバイザーズ | P84: 01mw7ee59ar9pj7bqtv5pbyep8kb7fqc | R84: 1 | S84: 組合員契約書締結 | T84: 46070 | U84: 46072 | Y84: 済み
A85: =IF(B85="","",COUNTA($B$2:B85)) -> 84 | B85: 三好恭統 | C85: jship.central@gmail.com | D85: 組合員契約書締結 | E85: 46106.814 | F85: 46106.816 | P85: 01mw7eecjn7kx4r3twa062wp5yrcmhhj | Q85: https://www.cloudsign.jp/document/01mw7eecjn7kx4r3twa062wp5yrcmhhj/summary | S85: 組合員契約書締結 | T85: 46070 | U85: 46070 | Y85: 済み
A86: =IF(B86="","",COUNTA($B$2:B86)) -> 85 | B86: 浜崎幸男 | C86: yasue@hamakou.jp | D86: 組合員契約書締結 | E86: 46106.814 | F86: 46107.564 | H86: 株式会社ハマダ工商 | M86: バリューフロンティア | P86: 01mw7eehp99xjvk7xq9mj4tmyt4zayyg | Q86: https://www.cloudsign.jp/document/01mw7eehp99xjvk7xq9mj4tmyt4zayyg/summary | S86: 組合員契約書締結 | T86: 46070 | U86: 46086 | V86: 01ms7rq296956rt0q3nycntf1kt729jt | Y86: 済み
A87: =IF(B87="","",COUNTA($B$2:B87)) -> 86 | B87: 村上達哉 | C87: t-murakami@lifemeister.com | D87: 組合員契約書締結 | E87: 46106.815 | F87: 46106.953 | H87: ライフマスター株式会社 | P87: 01mw7ees6ra48ymm0ys7vp79ssk2t0m2 | Q87: https://www.cloudsign.jp/document/01mw7ees6ra48ymm0ys7vp79ssk2t0m2/summary | S87: 組合員契約書締結 | T87: 46070 | U87: 46072 | Y87: 済み
A88: =IF(B88="","",COUNTA($B$2:B88)) -> 87 | B88: 浦崇典 | C88: uratakagt@monzen-noto.com | D88: 組合員契約書締結 | E88: 46106.815 | F88: 46114.606 | H88: 株式会社能登つ猛進 | M88: バリューフロンティア | P88: 01mw7ef0gey3a0gs2hghr5aq8zzwc2ft | Q88: https://www.cloudsign.jp/document/01mw7ef0gey3a0gs2hghr5aq8zzwc2ft/summary | R88: 1 | S88: 組合員契約書締結 | T88: 46071 | U88: 46085 | Y88: 済み
A89: =IF(B89="","",COUNTA($B$2:B89)) -> 88 | B89: 渕上雄一 | C89: jubileefuchigami@gmail.com | D89: 契約書送付済 | E89: 46106.815 | P89: 01mw7ef5x1713pcry6ey1khbz3yd4r79 | R89: 1 | S89: 組合員契約書締結 | T89: 46071 | U89: 46071 | Y89: 済み
A90: =IF(B90="","",COUNTA($B$2:B90)) -> 89 | B90: 岡野光壮 | C90: okano@urudensun.jp | D90: 組合員契約書締結 | E90: 46106.815 | F90: 46108.537 | H90: 株式会社Sun.Assist | M90: バリューフロンティア | P90: 01mw7efbdbh6whm28a94x580g1pq0wba | Q90: https://www.cloudsign.jp/document/01mw7efbdbh6whm28a94x580g1pq0wba/summary | S90: 組合員契約書締結 | T90: 46071 | U90: 46073 | Y90: 済み
A91: =IF(B91="","",COUNTA($B$2:B91)) -> 90 | B91: 飯田真子 | C91: mirai.seed168@gmail.com | D91: 契約書送付済 | E91: 46106.815 | H91: 未来seed合同会社 | P91: 01mw7efh1jhr8mkrdkwyqnnxhscyjvsh | R91: 1 | S91: 組合員契約書締結 | T91: 46071 | U91: 46079 | Y91: 済み
A92: =IF(B92="","",COUNTA($B$2:B92)) -> 91 | B92: 西脇賢匡 | C92: nishiwaki@newwest.jp | D92: 契約書未送付 | E92: 46106.815 | H92: 株式会社NewWest | P92: 01mw7efqv6r7cgz63rj31sda7cccmt1h | R92: 1 | S92: 組合員契約書締結 | T92: 46071 | U92: 46072 | Y92: 済み
A93: =IF(B93="","",COUNTA($B$2:B93)) -> 92 | B93: 三浦孝之 | C93: t.miura@earth-p.jp | D93: 契約書送付済 | E93: 46106.815 | H93: 株式会社アースプランニング | M93: バリューフロンティア | O93: 2026/02/20メールアドレス変更のため再送 | P93: 01mw7efy6vfks5ee7wxk1nvatwxaqdpy | R93: 1 | S93: 契約破棄 | T93: 46071 | U93: 破棄処理 | V93: 01msfg049kgw8hsar1hf84jgmet25t9z | Y93: 済み
A94: =IF(B94="","",COUNTA($B$2:B94)) -> 93 | B94: 浅井克敏 | C94: t.ishida@shoko-office.co.jp | D94: 契約書送付済 | E94: 46106.815 | H94: 株式会社商工オフィス | M94: バリューフロンティア | P94: 01mw7eg4vm9pwkgxdncxm492d9txz8my | R94: 1 | S94: 組合員契約書締結 | T94: 46071 | U94: 46072 | Y94: 済み
A95: =IF(B95="","",COUNTA($B$2:B95)) -> 94 | B95: 安樂陸 | C95: anraku4545@gmail.com | D95: 契約書送付済 | E95: 46106.815 | P95: 01mw7eg9ftmgz41q02b6zxbr36nj0sgz | R95: 1 | S95: 組合員契約書締結 | T95: 46071 | U95: 46071 | Y95: 済み
A96: =IF(B96="","",COUNTA($B$2:B96)) -> 95 | B96: 大林幸 | C96: k.obayashi@talent-grp.co.jp | D96: 契約書送付済 | E96: 46106.815 | H96: 株式会社タラント | M96: バリューフロンティア | P96: 01mw7eggwde970hfjdhbwhbadrzn6s4z | R96: 1 | S96: 組合員契約書締結 | T96: 46072 | U96: 46072 | Y96: 済み
A97: =IF(B97="","",COUNTA($B$2:B97)) -> 96 | B97: 竹内広大 | C97: ko.takeuchi@eggm.co.jp | D97: 契約書送付済 | E97: 46106.815 | P97: 01mw7egnyzfgf99f9b57mqh731skqe6k | R97: 1 | S97: 契約破棄 | T97: 46072 | U97: 破棄処理 | V97: 01mscze87mzwta0gbyed1mr017j4g6xg | Y97: 済み
A98: =IF(B98="","",COUNTA($B$2:B98)) -> 97 | B98: 沼倉隆平 | C98: ooxmichaelxoo@gmail.com | D98: 契約書送付済 | E98: 46106.815 | G98: 代表取締役 | H98: 株式会社イケメン | P98: 01mw7egv2spmmx0mazh4vfhfxtnmxtz2 | R98: 1 | S98: 契約破棄 | T98: 46072 | U98: 破棄処理 | V98: 01msczybw26csemdng7e9qgvj8hyn3e7 | Y98: 済み
A99: =IF(B99="","",COUNTA($B$2:B99)) -> 98 | B99: 藤山泰成 | C99: ta@fujiyama.work | D99: 契約書送付済 | E99: 46106.815 | G99: 代表取締役 | H99: 大吉会計株式会社 | P99: 01mw7eh25f6n73ph90491mcg5rn3qewd | R99: 1 | S99: 組合員契約書締結 | T99: 46072 | U99: 46074 | Y99: 済み
A100: =IF(B100="","",COUNTA($B$2:B100)) -> 99 | B100: 川島僚介 | C100: ure.2023@gmail.com | D100: 契約書送付済 | E100: 46106.828 | G100: 代表取締役 | H100: 株式会社Universe Solutions | O100: 2026/2/20再送 | P100: 01mw7fm3nmrkm0wvp797hgemvx5hex5m | R100: 1 | S100: 組合員契約書締結 | T100: 46072 | U100: 46073 | Y100: 済み
...

Sheet 面談実施リスト
A1: № | B1: 氏名 | C1: 企業名 | D1: 日付 | E1: 担当者 | F1: 紹介者 | G1: 代理店％ | H1: ステータス
B2: 木原 | D2: 46035 | E2: 尾崎 | G2: 1％ | H2: 面談実施
B3: 高畑 | D3: 46042 | E3: 尾崎 | G3: 1％ | H3: 面談実施
B4: 手塚 | C4: 株式会社AirX | D4: 46049 | E4: 尾崎 | F4: 創作さん | H4: お見送り
B5: 新沼 | C5: 株式会社セキムラ | D5: 46049 | E5: 尾崎 | F5: 創作さん | H5: 概算お渡し済み
B6: 川添 | C6: COARIS | D6: 46051 | E6: 尾崎 | G6: 1％ | H6: 面談実施
B7: 渡邊 | C7: kotonoha | D7: 46051 | E7: 尾崎 | G7: 1％ | H7: 面談実施
B8: 今川 | D8: 46052 | E8: 尾崎 | G8: 1％ | H8: 面談実施
B9: 花蜜 | D9: 46052 | E9: 尾崎 | G9: 1％ | H9: 面談実施

Sheet シート11
B2: 平均給与 | C2: 300000 | G2: 目標 | H2: 300000000
B3: 人数 | C3: 100 | G3: 1人当たり | H3: 150000
B4: １人あたりの導入金額 | C4: 100000
B6: 初期費用 | C6: =C3*C4 -> 10000000
B7: 既存の社会保険料/月 | C7: 30000
B8: 削減金額/月 | C8: 18000
B9: 削減額合計 | C9: =C8*C3 -> 1800000
B11: 月額利用料/人 | C11: 1000
B12: 月額利用料総額 | C12: =C11*C3 -> 100000
B16: 回収まで | C16: =C6/C9 -> 5.5555556 | D16: ヶ月

Sheet 契約書一覧
A1: 契約書名 | B1: ドライブURL | C1: ステータス
A2: 組合員契約書 | B2: ★一般社団法人_公的制度教育推進協会組合員契約書_修正_0321YS.docx - Google ドキュメント | C2: リーガルチェック済
A3: 組合規定書 | B3: ★一般社団法人_公的制度教育推進協会組合規定書_修正_0321YS.docx - Google ドキュメント | C3: リーガルチェック済
A4: 受託開発契約書 開発企業×企業 | B4: ★受託開発契約書＿開発会社×企業_0324YS.docx - Google ドキュメント | C4: 修正中
A5: 給与評価制度適正化支援契約書 一般社団法人×企業 | B5: ★給与評価制度適正化支援契約書＿一般社団法人×企業_0324YS.docx - Google ドキュメント | C5: リーガルチェック済
A6: 代理店契約書 開発会社×代理店 | B6: ★代理店契約書＿開発会社×代理店_0324YS.docx - Google ドキュメント | C6: 修正中
A7: 組合契約書 法人用 | B7: ★一般社団法人_公的制度教育推進協会組合契約書_修正_法人用 - Google ドキュメント | C7: リーガルチェック済
A8: 組合規定書 法人用 | B8: ★一般社団法人_公的制度教育推進協会組合規定書_修正_法人用.docx - Google ドキュメント | C8: リーガルチェック済 | I8: 企業研修
A9: システム販売契約書 | B9: システム販売・導入契約書 - Google ドキュメント | C9: 作成中
A10: システム仕様書 | B10: 職能評価システム 仕様書（テンプレ） - Google ドキュメント | C10: 作成中
A11: 今後の代理店契約書

Sheet 自動化
A2: 回答用_メインフォーム | B2: https://forms.gle/zftF5VZPxHCRYtrCA
A3: 編集用_メインフォーム | B3: https://docs.google.com/forms/d/1aGe_IjCSVTHPEwQ5okrSzLf0ddRNFOKZG8qZ0zNkUGU/edit
A4: VF専用_回答用_メインフォーム | B4: https://forms.gle/yHVUY6hzuTyuUWde6
A5: VF専用_編集用_メインフォーム | B5: https://docs.google.com/forms/d/1brpnY6VBoPnuO735oC0RhDV8gI_uTWB0_HCI6Q_lQKY/edit
A6: VF中間シート | B6: https://docs.google.com/spreadsheets/d/1C6NymtxuBqP1vLMswJTxDnX0SxvtIdsO8BoHSH5eOrs/edit?usp=sharing
A7: VF側シート | B7: https://docs.google.com/spreadsheets/d/1qjNACHsS6r82qBPFERNrDExtIhi9m3iv/edit?gid=380300159#gid=380300159

Sheet 案件管理シート
A2: 案件番号 | B2: 案件起票日 | C2: 年金事務所への電話 | D2: AS担当者 | E2: 顧客区分 | F2: 都道府県 | G2: 管轄の年金事務所 | H2: 年金事務所担当者名 | I2: 企業名 | J2: 算定基礎届・源泉徴収簿 | K2: 代表者名 | L2: 紹介者 | M2: 業種 | N2: ステータス | O2: 概算見積リンク | P2: 希望者名簿 | Q2: 最大申請人数 | R2: 想定申請人数 | S2: 想定最大還付額 | T2: 想定還付金額 | U2: 確定還付金額 | V2: 弊社想定売上(※開発費) | W2: 確定想定売上(※開発費) | X2: 想定代理店報酬 | Y2: 確定代理店売上 | Z2: 次のアクション | AA2: 次に連絡する日 | AB2: 初回商談日 | AC2: 想定申請日 | AD2: 確定申請日 | AE2: 想定充当通知日 | AF2: 確定充当通知日 | AG2: 想定還付日 | AH2: 確定還付日 | AI2: 想定伊藤先生報酬額 | AJ2: 想定伊藤先生支払日 | AK2: 確定伊藤先生報酬額 | AL2: 確定伊藤先生支払日 | AM2: 想定弊社報酬額 | AN2: 想定弊社支払日 | AO2: 確定弊社報酬額 | AP2: 確定弊社支払日
A3: 0 | D3: 尾崎 | F3: 東京 | G3: 港年金事務所 | H3: 岩下さん | I3: Stella株式会社
A4: 1 | B4: 46069 | D4: 鈴木 | E4: クライアント | F4: 大阪 | G4: 八尾年金事務所 | I4: 株式会社 アポロホールディングス | J4: https://drive.google.com/drive/folders/1KPrf6Fev_4qbIKuUJrqsfUrmJd_7cC26?usp=sharing | M4: 美容業 | N4: 概算提案フェーズ | Q4: 107 | R4: =Q4*80% -> 85.6 | T4: =S4*0.5 -> 0 | V4: =T4*0.2*0.8 -> 0 | X4: =T4*0.1 -> 0 | AC4: =AB4+30 -> 30 | AE4: =AC4+60 -> 90 | AG4: =AE4+60 -> 150 | AI4: =T4*5% -> 0 | AJ4: =AG4+45 -> 195 | AM4: =T4*10% -> 0 | AN4: =AG4+30 -> 180
A5: 2 | B5: 46069 | D5: 鈴木 | E5: クライアント | F5: 東京 | G5: 大手前年金事務所 | I5: 株式会社 アポロプランニング | J5: https://drive.google.com/drive/folders/1KPrf6Fev_4qbIKuUJrqsfUrmJd_7cC26?usp=sharing | M5: 観光業 | N5: 概算提案フェーズ | Q5: 354 | R5: =Q5*80% -> 283.2 | T5: =S5*0.5 -> 0 | V5: =T5*0.2*0.8 -> 0 | X5: =T5*0.1 -> 0 | AC5: =AB5+30 -> 30 | AE5: =AC5+60 -> 90 | AG5: =AE5+60 -> 150 | AI5: =T5*5% -> 0 | AJ5: =AG5+45 -> 195 | AM5: =T5*10% -> 0 | AN5: =AG5+30 -> 180
A6: 3 | B6: 46069 | C6: 待ち | D6: 尾崎 | E6: クライアント | F6: 神奈川 | G6: 小田原年金事務所 | I6: 株式会社 琴美建設 | J6: https://drive.google.com/drive/folders/1OyTAtQzaBoJZMhqieuT8p-uww35EvR_s?usp=sharing | K6: 今川将文 | L6: 望月さん | M6: 建設業 | N6: 概算提案フェーズ | O6: 株式会社美琴建設 | Q6: 17 | R6: =Q6*80% -> 13.6 | S6: 15573557 | T6: =S6*0.5 -> 7786778.5 | V6: =T6*0.2*0.8 -> 1245884.6 | X6: =T6*0.1 -> 778677.85 | AC6: =AB6+30 -> 30 | AE6: =AC6+60 -> 90 | AG6: =AE6+60 -> 150 | AI6: =T6*5% -> 389338.92 | AJ6: =AG6+45 -> 195 | AM6: =T6*10% -> 778677.85 | AN6: =AG6+30 -> 180
A7: 4 | B7: 46069 | D7: 飯塚 | E7: クライアント | F7: 東京 | G7: 足立年金事務所 | I7: 株式会社RISE様 | J7: https://drive.google.com/drive/folders/1dwakvflY9pOgv_Mp840by1MsEE3Bql6Q?usp=sharing | K7: 小室立 | L7: 直 | M7: 美容業 | N7: 概算提案フェーズ | O7: output_株式会社RISE | Q7: 23 | R7: =Q7*80% -> 18.4 | S7: 28530256 | T7: =S7*0.5 -> 14265128 | V7: =T7*0.2*0.8 -> 2282420.5 | X7: =T7*0.1 -> 1426512.8 | AC7: =AB7+30 -> 30 | AE7: =AC7+60 -> 90 | AG7: =AE7+60 -> 150 | AI7: =T7*5% -> 713256.4 | AJ7: =AG7+45 -> 195 | AM7: =T7*10% -> 1426512.8 | AN7: =AG7+30 -> 180
A8: 5 | B8: 46069 | D8: 鈴木 | E8: クライアント | F8: 東京 | G8: 新宿年金事務所 | I8: 株式会社ＭａｉｎＣ様 | J8: https://drive.google.com/drive/folders/1V3kxanVQkv1LMgU2Y1ynsv8QwceoN9ud?usp=sharing | K8: 辻亮 | L8: 直 | M8: 飲食業 | N8: 概算提案フェーズ | O8: output_株式会社MainC | Q8: 15 | R8: =Q8*80% -> 12 | S8: 10826393 | T8: =S8*0.5 -> 5413196.5 | V8: =T8*0.2*0.8 -> 866111.44 | X8: =T8*0.1 -> 541319.65 | AC8: =AB8+30 -> 30 | AE8: =AC8+60 -> 90 | AG8: =AE8+60 -> 150 | AI8: =T8*5% -> 270659.83 | AJ8: =AG8+45 -> 195 | AM8: =T8*10% -> 541319.65 | AN8: =AG8+30 -> 180
A9: 6 | B9: 46069 | C9: 済み | D9: 尾崎 | E9: クライアント | F9: 大阪 | G9: 淀川年金事務所 | I9: 株式会社バリューフロンティア | J9: https://drive.google.com/drive/folders/1RXvJ0YVUGTVlXtPxy0UZ7raPoaBBH7e9?usp=sharing | K9: 大塚崇司 | L9: 望月さん | M9: 営業 | N9: 申請フェーズ | Q9: 52 | R9: =Q9*80% -> 41.6 | T9: =S9*0.5 -> 0 | V9: =T9*0.2*0.8 -> 0 | X9: =T9*0.1 -> 0 | AC9: =AB9+30 -> 30 | AE9: =AC9+60 -> 90 | AG9: =AE9+60 -> 150 | AI9: =T9*5% -> 0 | AJ9: =AG9+45 -> 195 | AM9: =T9*10% -> 0 | AN9: =AG9+30 -> 180
A10: 7 | B10: 46069 | C10: 待ち | D10: 尾崎 | E10: クライアント | F10: 東京 | G10: 佐原年金事務所 | I10: 株式会社Good Work Japan | J10: https://drive.google.com/drive/folders/15YhdKX2gbnH2pfEgAsIysrjnsHQGT6zz?usp=sharing | K10: 吉田さん | L10: 創作 | M10: 人材業 | N10: 概算提案フェーズ | O10: ファイルサイズが大きい為別途送付可能 | Q10: 1945 | R10: =Q10*80% -> 1556 | S10: 672409696 | T10: =S10*0.5 -> 336204848 | AC10: =AB10+30 -> 30 | AE10: =AC10+60 -> 90 | AG10: =AE10+60 -> 150 | AI10: =T10*5% -> 16810242 | AJ10: =AG10+45 -> 195 | AM10: =T10*10% -> 33620485 | AN10: =AG10+30 -> 180
A11: 8 | B11: 46083 | D11: 尾崎 | E11: クライアント | F11: 東京 | G11: 渋谷年金事務所 | I11: リアンクリニック（一般社団法人LIEN） | J11: https://drive.google.com/drive/folders/1s-xQ5KPC2BhuPd28epESClY0K-KYu2yQ?usp=sharing | K11: 藤尾謙太 | L11: 創作 | M11: 美容クリニック | N11: 申請フェーズ | O11: output_一般社団法人LIEN | Q11: 29 | R11: =Q11*80% -> 23.2 | S11: 60346992 | T11: =S11*0.5 -> 30173496 | AC11: =AB11+30 -> 30 | AE11: =AC11+60 -> 90 | AG11: =AE11+60 -> 150 | AI11: =T11*5% -> 1508674.8 | AJ11: =AG11+45 -> 195 | AM11: =T11*10% -> 3017349.6 | AN11: =AG11+30 -> 180
A12: 9 | B12: 46083 | D12: 尾崎 | E12: クライアント/代理店 | F12: 愛知 | G12: 鶴舞年金事務所 | I12: ジェイシップセントラル | J12: https://drive.google.com/drive/folders/1Ry1wQBQ7QC52-TJOOZvp6S-q6rshBXtH?usp=sharing | K12: 三好恭統 | L12: 創作 | M12: 人材採用 | N12: 申請フェーズ | O12: ジェイシップセントラル㈱ | Q12: 27 | R12: =Q12*80% -> 21.6 | S12: 31621501 | T12: =S12*0.5 -> 15810750 | AC12: =AB12+30 -> 30 | AE12: =AC12+60 -> 90 | AG12: =AE12+60 -> 150 | AI12: =T12*5% -> 790537.53 | AJ12: =AG12+45 -> 195 | AM12: =T12*10% -> 1581075.1 | AN12: =AG12+30 -> 180
A13: 10 | B13: 46083 | C13: 待ち | D13: 尾崎 | E13: クライアント | F13: 東京 | G13: 宮崎年金事務所 | I13: aspo株式会社 | J13: https://drive.google.com/drive/folders/1zDPa_Z9wF6SkvOoi0WWV0R0nvTCzNhZG?usp=sharing | K13: 花田 誉宜 | L13: VF | M13: 健康経営支援 | N13: 概算提案フェーズ | O13: output_株式会社aspo.xlsx | Q13: 74 | R13: =Q13*80% -> 59.2 | S13: 38219349 | T13: =S13*0.5 -> 19109674 | AC13: =AB13+30 -> 30 | AE13: =AC13+60 -> 90 | AG13: =AE13+60 -> 150 | AI13: =T13*5% -> 955483.72 | AJ13: =AG13+45 -> 195 | AM13: =T13*10% -> 1910967.4 | AN13: =AG13+30 -> 180
A14: 11 | B14: 46083 | C14: 待ち | D14: 尾崎 | E14: クライアント | F14: 東京 | G14: 港年金事務所 | I14: 株式会社NEXT（旧: 株式会社ADOLOGI） | J14: https://drive.google.com/drive/folders/1g-8xtcXR4_Tt2ASFOMCsirDkrM7joNgF | K14: 栗原政史 | L14: 三好さん | M14: IT | N14: 概算提案フェーズ | O14: output_株式会社NEXT (1) | P14: 希望者名簿＿output_株式会社NEXT（修正版）.xlsx - Google スプレッドシート | Q14: 17 | R14: =Q14*80% -> 13.6 | S14: 112610895 | T14: =S14*0.5 -> 56305448 | AC14: =AB14+30 -> 30 | AE14: =AC14+60 -> 90 | AG14: =AE14+60 -> 150 | AI14: =T14*5% -> 2815272.4 | AJ14: =AG14+45 -> 195 | AM14: =T14*10% -> 5630544.8 | AN14: =AG14+30 -> 180
A15: 12 | B15: 46104 | D15: 尾崎 | E15: クライアント | F15: 東京 | G15: 板橋年金事務所 | I15: 株式会社セキムラ | J15: https://drive.google.com/drive/folders/1z25XIjyDhllINrsKEYVlWiFHFjuKTjdx?usp=sharing | K15: 新沼 直哉 | L15: 創作さん | M15: 医療機器メーカー | N15: 概算提案フェーズ | O15: 株式会社セキムラ | Q15: 71 | R15: =Q15*80% -> 56.8 | S15: 130448744 | T15: =S15*0.5 -> 65224372
A16: 13 | B16: 46093 | D16: 尾崎 | E16: クライアント | F16: 東京 | G16: 足立年金事務所 | I16: 株式会社HRfreaks | J16: https://drive.google.com/drive/folders/1FILKYriYaYciipHV1X14tll5bVwtijI0?usp=sharing | K16: 山根 弘行 | L16: 田中 | M16: 採用コンサルティング | N16: 書類取得フェーズ | R16: =Q16*80% -> 0 | T16: =S16*0.5 -> 0
A17: 14 | B17: 46096 | D17: 尾崎 | E17: クライアント | F17: 神奈川 | G17: 鶴見年金事務所 | I17: ハワイアンフォレスト株式会社 | J17: https://drive.google.com/drive/folders/1moDm_27z9F5Df0bKLgvQ-FyInvXg3kQW?usp=sharing | K17: 宮崎優 | L17: 花蜜 | M17: マッサージサロン | N17: 概算提案フェーズ | O17: output_ハワイアンフォレストSpa株式会社 | Q17: 59 | R17: =Q17*80% -> 47.2 | S17: 20312308 | T17: =S17*0.5 -> 10156154
A18: 15 | B18: 46096 | D18: 尾崎 | E18: クライアント | F18: 神奈川 | G18: 鶴見年金事務所 | I18: リラク＆ビューティー株式会社 | J18: https://drive.google.com/drive/folders/1moDm_27z9F5Df0bKLgvQ-FyInvXg3kQW?usp=sharing | K18: 宮崎優 | L18: 花蜜 | M18: 美容業 | N18: 概算提案フェーズ | O18: output_リラク＆ビューティー株式会社 | Q18: 109 | R18: =Q18*80% -> 87.2 | S18: 19410542 | T18: =S18*0.5 -> 9705271
A19: 17 | B19: 46100 | D19: 尾崎 | E19: クライアント | F19: 東京 | G19: 池袋年金事務所 | I19: エプコットソフトウェア | J19: https://drive.google.com/drive/folders/1_BYKwCfLzaW61QFGv4AVMJc_qvrWbG4q?usp=drive_link | K19: 山崎由介 | L19: 松本 | M19: システム開発 | N19: 概算提案フェーズ | O19: 株式会社エプコットソフトウェア | Q19: 169 | R19: =Q19*80% -> 135.2 | S19: 256372905 | T19: =S19*0.5 -> 1.2818645e+08
A20: 18 | B20: 46111 | D20: 尾崎 | E20: クライアント | F20: 岡山 | G20: 岡山西年金事務所 | I20: 株式会社スイッチ | J20: https://drive.google.com/drive/folders/1yFeFBOmzW7cbEi38oeYwKPM37bzStCNL | K20: 恒次明宏 | L20: VF | M20: web制作 | N20: 概算提案フェーズ | O20: 株式会社スイッチ | Q20: 49 | R20: =Q20*80% -> 39.2 | S20: 79758591 | T20: =S20*0.5 -> 39879296
A21: 19 | B21: 46111 | D21: 尾崎 | E21: クライアント | F21: 奈良 | G21: 奈良年金事務所 | I21: 株式会社ENAKAMA | J21: https://drive.google.com/drive/folders/17Ak1ZGq5iBWwGVZRatkc0wYuIddfBXsh | K21: 奥野 茂樹 | L21: VF | M21: 児童発達支援 | N21: 概算提案フェーズ | O21: 株式会社ENAKAM | Q21: 8 | R21: =Q21*80% -> 6.4 | S21: 9269769 | T21: =S21*0.5 -> 4634884.5
A22: 20 | B22: 46111 | D22: 尾崎 | E22: クライアント | F22: 東京 | G22: 奈良年金事務所 | I22: 株式会社K-FielD | J22: https://drive.google.com/drive/folders/1ZINJ3Ntsz76KgZfYTxRROuVQqPDiDgKE | K22: 兼利太樹 | L22: VF | M22: 不動産 | N22: 概算提案フェーズ | O22: 株式会社K-FielD | Q22: 71 | R22: =Q22*80% -> 56.8 | S22: 45145957 | T22: =S22*0.5 -> 22572978
A23: 21 | B23: 46111 | D23: 尾崎 | E23: クライアント | F23: 石川 | G23: 小松年金事務所 | I23: BOSS Group株式会社 | J23: https://drive.google.com/drive/folders/1Tu5OX6Nr0jwgUh1CS2X2ay0iCAcWtjLO | K23: 白江 誠一郎 | L23: VF | M23: 飲食 | N23: 概算提案フェーズ | O23: BOSS Group株式会社 | Q23: 9 | R23: =Q23*80% -> 7.2 | S23: 9325057 | T23: =S23*0.5 -> 4662528.5
A24: 22 | B24: 46113 | D24: 尾崎 | E24: クライアント | F24: 奈良 | G24: 大和高田年金事務所 | I24: 11.株式会社ベース | J24: https://drive.google.com/drive/folders/1xgSQpBfLYppF_z3elh05ibp5lPRCxdaN?usp=drive_link | K24: 京谷陽介 | L24: VF | M24: 不動産 | N24: 書類取得フェーズ | R24: =Q24*80% -> 0 | T24: =S24*0.5 -> 0
A25: 23 | B25: 46113 | D25: 尾崎 | E25: クライアント | F25: 広島 | G25: 広島東年金事務所 | I25: 4.株式会社クォリティプラス | J25: https://drive.google.com/drive/folders/1hWGWdqkHnUXHAzTh5dGcq7SH8YvybVAy?usp=drive_link | K25: 内平 雅也 | L25: VF | M25: 太陽光など | N25: 書類取得フェーズ | R25: =Q25*80% -> 0 | T25: =S25*0.5 -> 0
A26: 24 | B26: 46113 | D26: 尾崎 | E26: クライアント | F26: 大阪 | G26: 東大阪年金事務所 | I26: 15.株式会社豊見山組 | J26: https://drive.google.com/drive/folders/1cXR78HzITlsbCk4NUDemNWree9LErynY?usp=drive_link | K26: 豊見山亮 | L26: VF | M26: 左官工事 | N26: 書類取得フェーズ | R26: =Q26*80% -> 0 | T26: =S26*0.5 -> 0
A27: 25 | B27: 46113 | D27: 尾崎 | E27: クライアント | F27: 奈良 | G27: 奈良年金事務所 | I27: 14.株式会社エイチツーオー | J27: https://drive.google.com/drive/folders/1bk7reKFZYjMxSKlhvlzkCDb7ou5_oiiL?usp=drive_link | L27: VF | M27: 建設工事 | N27: 書類取得フェーズ | R27: =Q27*80% -> 0 | T27: =S27*0.5 -> 0
A28: 26 | B28: 46113 | D28: 尾崎 | E28: クライアント | F28: 大阪 | G28: 東大阪年金事務所 | I28: 13.豊栄水産株式会社 | J28: https://drive.google.com/drive/folders/1RxnBuGzvivC2ZTnZfG6c-kJTmem7zZFY?usp=drive_link | K28: 長町喜光 | L28: VF | M28: 水産業 | N28: 書類取得フェーズ | R28: =Q28*80% -> 0 | T28: =S28*0.5 -> 0
A29: 27 | B29: 46113 | D29: 尾崎 | E29: クライアント | F29: 京都 | G29: 中京年金事務所 | I29: 5.立生株式会社 | J29: https://drive.google.com/drive/folders/1MRd7KSTj-nsIhhljgU8xLMREQ4uL9JHk?usp=drive_link | K29: 佐藤靖之 | L29: VF | M29: HP制作 | N29: 書類取得フェーズ | R29: =Q29*80% -> 0 | T29: =S29*0.5 -> 0
A30: 28 | B30: 46113 | D30: 尾崎 | E30: クライアント | F30: 東京 | G30: 八王子年金事務所 | I30: 12.株式会社ソキュアス | J30: https://drive.google.com/drive/folders/1Hfm4-9Q4AEkcDGGJQoJ2SnOiwMxzrY_n?usp=drive_link | K30: 川近充 | L30: VF | M30: 帽子通販 | N30: 書類取得フェーズ | R30: =Q30*80% -> 0 | T30: =S30*0.5 -> 0
A31: 29 | B31: 46113 | D31: 尾崎 | E31: クライアント | F31: 京都 | G31: 京都南年金事務所 | I31: 10.株式会社YKS | J31: https://drive.google.com/drive/folders/1Af3KOefEMgCGg-hU2Cu7GmT6kXa5dDBD?usp=drive_link | K31: 小嶋康彦 | L31: VF | M31: 防水・止水工事など | N31: 書類取得フェーズ | R31: =Q31*80% -> 0 | T31: =S31*0.5 -> 0
A32: 30 | B32: 46113 | D32: 尾崎 | E32: クライアント | F32: 大阪 | G32: 平野年金事務所 | I32: 2.ケーツーエンジニアリング株式会社 | J32: https://drive.google.com/drive/folders/1ASlDv9YUUPXl7NTzt22lLJrP5K5MH3SS?usp=drive_link | K32: 秀平健二 | L32: VF | M32: オフィス機器導入 | N32: 書類取得フェーズ | R32: =Q32*80% -> 0 | T32: =S32*0.5 -> 0
A33: 31 | B33: 46113 | D33: 尾崎 | E33: クライアント | F33: 広島 | G33: 広島東年金事務所 | I33: 9.株式会社Sun.Assist | J33: https://drive.google.com/drive/folders/10RpyeMHTZFskyfzgWY3rER-7xQyNPw6L?usp=drive_link | K33: 岡野光壮 | L33: VF | M33: 太陽光など | N33: 書類取得フェーズ | R33: =Q33*80% -> 0 | T33: =S33*0.5 -> 0
A34: 32 | D34: 尾崎 | E34: クライアント | F34: 愛知 | G34: 鶴舞年金事務所 | I34: 株式会社Fit Founder | J34: 回収中 | K34: 八賀 晋太朗 | L34: 角田 | M34: 太陽光など | N34: 書類取得フェーズ | R34: =Q34*80% -> 0 | T34: =S34*0.5 -> 0
A35: 33 | R35: =Q35*80% -> 0 | T35: =S35*0.5 -> 0
A36: 34 | R36: =Q36*80% -> 0 | T36: =S36*0.5 -> 0
A37: 35 | R37: =Q37*80% -> 0 | T37: =S37*0.5 -> 0
A38: 36 | R38: =Q38*80% -> 0 | T38: =S38*0.5 -> 0
A39: 37 | R39: =Q39*80% -> 0
A40: 38 | R40: =Q40*80% -> 0
A41: 39 | R41: =Q41*80% -> 0
A42: 40 | R42: =Q42*80% -> 0
A43: 41 | R43: =Q43*80% -> 0
A44: 42 | R44: =Q44*80% -> 0
A45: 43 | R45: =Q45*80% -> 0
A46: 44 | R46: =Q46*80% -> 0
A47: 45 | R47: =Q47*80% -> 0
A48: 46 | R48: =Q48*80% -> 0
A49: 47 | R49: =Q49*80% -> 0
A50: 48 | R50: =Q50*80% -> 0
... A103: 101 | R103: =Q103*80% -> 0
A104: 102
A105: 103
A106: 104
A107: 105
A108: 106
A109: 107
A110: 108
A111: 109
A112: 110
A113: 111
A114: 112
A115: 113
... A118: 116

Sheet 進行中リスト
A1: 案件番号 | B1: 案件起票日 | C1: 名前 | D1: AS担当者 | E1: 顧客区分 | F1: 企業名 | G1: 紹介者 | H1: 業種 | I1: ステータス | J1: 最大申請人数 | K1: 想定申請人数 | L1: 想定還付金額 | M1: 確定還付金額 | N1: 弊社想定売上(※開発費) | O1: 確定想定売上(※開発費) | P1: 想定代理店売上 | Q1: 確定代理店売上 | R1: 次のアクション | S1: 次に連絡する日 | T1: 初回商談日 | U1: 想定申請日 | V1: 確定申請日 | W1: 想定充当通知日 | X1: 確定充当通知日 | Y1: 想定還付日 | Z1: 確定還付日 | AA1: 想定伊藤先生報酬額 | AB1: 想定伊藤先生支払日 | AC1: 確定伊藤先生報酬額 | AD1: 確定伊藤先生支払日 | AE1: 想定弊社報酬額 | AF1: 想定弊社支払日 | AG1: 確定弊社報酬額 | AH1: 確定弊社支払日
A2: 1 | B2: 46064 | C2: サンプル | D2: 宮原 | E2: クライアント | F2: サンプル株式会社 | H2: 建設業 | I2: 書類取得フェーズ | J2: 申請可能人数(申請人数) | R2: 申請フェーズ | S2: 46064 | T2: 46064 | U2: =T2+30 -> 46094 | W2: =U2+60 -> 46154 | Y2: =W2+60 -> 46214 | AA2: =L2*10% -> 0 | AB2: =Y2+45 -> 46259 | AE2: =L2*10% -> 0 | AF2: =Y2+30 -> 46244
A3: 2 | B3: 46069 | D3: 鈴木 | E3: クライアント | F3: 株式会社 アポロホールディングス | H3: 美容業 | I3: 概算提案フェーズ | J3: 107 | K3: =J3*50% -> 53.5 | L3: 110541008 | N3: =L3*0.2*0.8 -> 17686561 | P3: =L3*0.1 -> 11054101 | U3: =T3+30 -> 30 | W3: =U3+60 -> 90 | Y3: =W3+60 -> 150 | AA3: =L3*10% -> 11054101 | AB3: =Y3+45 -> 195 | AE3: =L3*10% -> 11054101 | AF3: =Y3+30 -> 180
A4: 3 | B4: 46069 | D4: 鈴木 | E4: クライアント | F4: 株式会社 アポロプランニング | H4: 観光業 | I4: 概算提案フェーズ | J4: 354 | K4: =J4*80% -> 283.2 | L4: 353957644 | N4: =L4*0.2*0.8 -> 56633223 | P4: =L4*0.1 -> 35395764 | U4: =T4+30 -> 30 | W4: =U4+60 -> 90 | Y4: =W4+60 -> 150 | AA4: =L4*10% -> 35395764 | AB4: =Y4+45 -> 195 | AE4: =L4*10% -> 35395764 | AF4: =Y4+30 -> 180
A5: 4 | B5: 46069 | D5: 尾崎 | E5: クライアント | F5: 株式会社 琴美建設 | H5: 建設業 | I5: 概算提案フェーズ | J5: 17 | K5: =J5*80% -> 13.6 | L5: 6655839 | N5: =L5*0.2*0.8 -> 1064934.2 | P5: =L5*0.1 -> 665583.9 | U5: =T5+30 -> 30 | W5: =U5+60 -> 90 | Y5: =W5+60 -> 150 | AA5: =L5*10% -> 665583.9 | AB5: =Y5+45 -> 195 | AE5: =L5*10% -> 665583.9 | AF5: =Y5+30 -> 180
A6: 5 | B6: 46069 | D6: 飯塚 | E6: クライアント | F6: 株式会社RISE様 | H6: 美容業 | I6: 申請フェーズ | J6: 23 | K6: =J6*80% -> 18.4 | L6: 30251059 | N6: =L6*0.2*0.8 -> 4840169.4 | P6: =L6*0.1 -> 3025105.9 | U6: =T6+30 -> 30 | W6: =U6+60 -> 90 | Y6: =W6+60 -> 150 | AA6: =L6*10% -> 3025105.9 | AB6: =Y6+45 -> 195 | AE6: =L6*10% -> 3025105.9 | AF6: =Y6+30 -> 180
A7: 6 | B7: 46069 | D7: 鈴木 | E7: クライアント | F7: 株式会社ＭａｉｎＣ様 | H7: 飲食業 | I7: 概算提案フェーズ | J7: 15 | K7: =J7*80% -> 12 | L7: 10826393 | N7: =L7*0.2*0.8 -> 1732222.9 | P7: =L7*0.1 -> 1082639.3 | U7: =T7+30 -> 30 | W7: =U7+60 -> 90 | Y7: =W7+60 -> 150 | AA7: =L7*10% -> 1082639.3 | AB7: =Y7+45 -> 195 | AE7: =L7*10% -> 1082639.3 | AF7: =Y7+30 -> 180
A8: 7 | B8: 46069 | D8: 尾崎 | E8: クライアント | F8: 株式会社バリューフロンティア | H8: 営業 | I8: 申請フェーズ | J8: 52 | K8: =J8*80% -> 41.6 | L8: 35304064 | N8: =L8*0.2*0.8 -> 5648650.2 | P8: =L8*0.1 -> 3530406.4 | U8: =T8+30 -> 30 | W8: =U8+60 -> 90 | Y8: =W8+60 -> 150 | AA8: =L8*10% -> 3530406.4 | AB8: =Y8+45 -> 195 | AE8: =L8*10% -> 3530406.4 | AF8: =Y8+30 -> 180
A9: 8 | B9: 46069 | D9: 尾崎 | E9: クライアント | F9: 株式会社Good Work Japan | H9: 人材業 | I9: 申請フェーズ | J9: 1945 | K9: =J9*20% -> 389 | U9: =T9+30 -> 30 | W9: =U9+60 -> 90 | Y9: =W9+60 -> 150 | AA9: =L9*10% -> 0 | AB9: =Y9+45 -> 195 | AE9: =L9*10% -> 0 | AF9: =Y9+30 -> 180
A10: 9 | B10: 46080 | D10: 尾崎 | E10: クライアント | F10: 株式会社ＮＥＸＴ | G10: 三好様 | H10: 物販 | I10: 書類取得フェーズ | K10: =J10*80% -> 0 | U10: =T10+30 -> 30 | W10: =U10+60 -> 90 | Y10: =W10+60 -> 150 | AA10: =L10*10% -> 0 | AB10: =Y10+45 -> 195 | AE10: =L10*10% -> 0 | AF10: =Y10+30 -> 180
A11: 10 | B11: 46078 | D11: 尾崎 | E11: クライアント | F11: ジェイシップセントラル株式会社 | H11: 人材業 | I11: 書類取得フェーズ | K11: =J11*80% -> 0 | U11: =T11+30 -> 30 | W11: =U11+60 -> 90 | Y11: =W11+60 -> 150 | AA11: =L11*10% -> 0 | AB11: =Y11+45 -> 195 | AE11: =L11*10% -> 0 | AF11: =Y11+30 -> 180
A12: 11 | B12: 46070 | D12: 尾崎 | E12: クライアント | F12: 一般社団法人LIEN | G12: 植倉様 | H12: 美容業 | I12: 概算提案フェーズ | K12: =J12*80% -> 0 | U12: =T12+30 -> 30 | W12: =U12+60 -> 90 | Y12: =W12+60 -> 150 | AA12: =L12*10% -> 0 | AB12: =Y12+45 -> 195 | AE12: =L12*10% -> 0 | AF12: =Y12+30 -> 180
A13: 12 | B13: 46079 | D13: 尾崎 | E13: クライアント | F13: aspo株式会社 | G13: VF | I13: 書類取得フェーズ | K13: =J13*80% -> 0 | U13: =T13+30 -> 30 | W13: =U13+60 -> 90 | Y13: =W13+60 -> 150 | AA13: =L13*10% -> 0 | AB13: =Y13+45 -> 195 | AE13: =L13*10% -> 0 | AF13: =Y13+30 -> 180
A14: 13 | K14: =J14*80% -> 0 | U14: =T14+30 -> 30 | W14: =U14+60 -> 90 | Y14: =W14+60 -> 150 | AA14: =L14*10% -> 0 | AB14: =Y14+45 -> 195 | AE14: =L14*10% -> 0 | AF14: =Y14+30 -> 180
A15: 14 | K15: =J15*80% -> 0 | U15: =T15+30 -> 30 | W15: =U15+60 -> 90 | Y15: =W15+60 -> 150 | AA15: =L15*10% -> 0 | AB15: =Y15+45 -> 195 | AE15: =L15*10% -> 0 | AF15: =Y15+30 -> 180
A16: 15 | K16: =J16*80% -> 0 | U16: =T16+30 -> 30 | W16: =U16+60 -> 90 | Y16: =W16+60 -> 150 | AA16: =L16*10% -> 0 | AB16: =Y16+45 -> 195 | AE16: =L16*10% -> 0 | AF16: =Y16+30 -> 180
A17: 16 | K17: =J17*80% -> 0 | U17: =T17+30 -> 30 | W17: =U17+60 -> 90 | Y17: =W17+60 -> 150 | AA17: =L17*10% -> 0 | AB17: =Y17+45 -> 195 | AE17: =L17*10% -> 0 | AF17: =Y17+30 -> 180
A18: 17 | K18: =J18*80% -> 0 | U18: =T18+30 -> 30 | W18: =U18+60 -> 90 | Y18: =W18+60 -> 150 | AA18: =L18*10% -> 0 | AB18: =Y18+45 -> 195 | AE18: =L18*10% -> 0 | AF18: =Y18+30 -> 180
A19: 18 | K19: =J19*80% -> 0 | U19: =T19+30 -> 30 | W19: =U19+60 -> 90 | Y19: =W19+60 -> 150 | AA19: =L19*10% -> 0 | AB19: =Y19+45 -> 195 | AE19: =L19*10% -> 0 | AF19: =Y19+30 -> 180
A20: 19 | K20: =J20*80% -> 0 | U20: =T20+30 -> 30 | W20: =U20+60 -> 90 | Y20: =W20+60 -> 150 | AA20: =L20*10% -> 0 | AB20: =Y20+45 -> 195 | AE20: =L20*10% -> 0 | AF20: =Y20+30 -> 180
A21: 20 | K21: =J21*80% -> 0 | U21: =T21+30 -> 30 | W21: =U21+60 -> 90 | Y21: =W21+60 -> 150 | AA21: =L21*10% -> 0 | AB21: =Y21+45 -> 195 | AE21: =L21*10% -> 0 | AF21: =Y21+30 -> 180
A22: 21 | K22: =J22*80% -> 0 | U22: =T22+30 -> 30 | W22: =U22+60 -> 90 | Y22: =W22+60 -> 150 | AA22: =L22*10% -> 0 | AB22: =Y22+45 -> 195 | AE22: =L22*10% -> 0 | AF22: =Y22+30 -> 180
A23: 22 | K23: =J23*80% -> 0 | U23: =T23+30 -> 30 | W23: =U23+60 -> 90 | Y23: =W23+60 -> 150 | AA23: =L23*10% -> 0 | AB23: =Y23+45 -> 195 | AE23: =L23*10% -> 0 | AF23: =Y23+30 -> 180
A24: 23 | K24: =J24*80% -> 0 | U24: =T24+30 -> 30 | W24: =U24+60 -> 90 | Y24: =W24+60 -> 150 | AA24: =L24*10% -> 0 | AB24: =Y24+45 -> 195 | AE24: =L24*10% -> 0 | AF24: =Y24+30 -> 180
A25: 24 | K25: =J25*80% -> 0 | U25: =T25+30 -> 30 | W25: =U25+60 -> 90 | Y25: =W25+60 -> 150 | AA25: =L25*10% -> 0 | AB25: =Y25+45 -> 195 | AE25: =L25*10% -> 0 | AF25: =Y25+30 -> 180
... A101: 100 | K101: =J101*80% -> 0 | U101: =T101+30 -> 30 | W101: =U101+60 -> 90 | Y101: =W101+60 -> 150 | AA101: =L101*10% -> 0 | AB101: =Y101+45 -> 195 | AE101: =L101*10% -> 0 | AF101: =Y101+30 -> 180

Sheet 伊藤先生質問予定
A1: 記載日 | B1: 質問日 | C1: 質問 | D1: 回答
A2: 46037 | B2: 46043 | C2: 外国人労働者も対象なのか | D2: 可能 源泉所得税を20%→10%に下げられる
C3: 雇用契約と業務委託の契約を明確にしていくロジックだが役員や社長分が還付されるのはどんな内容か
C4: テレグラムに移行して良いか
C5: 従業員の同意書 | D5: /同意書/意識表明書
C6: 企業と伊藤先生が結ぶ契約書 どゆこと？ | D6: 業務委託報酬/職能別の資料作成費用
C7: 報酬を20%もらうと思うのですが、人事制度見直しを例えばバリューがstellaに依頼する場合の契約書が必要だと思うのですがどうですか
C8: 源泉所得税と支払っている金額は、本来取りすぎているので、社員が確定申告後、還付もしくは追加徴税は発生しますか？ →これを聞かれた際の対応を明確にする
C9: ・すでに年金もらってる方達が給料見直しするとどうなるのか？ →現在もらっている年金に影響があるのか？
C10: 概算を出した後の業務の明確化
C11: 今後、給与+報酬の従業員の確定申告の必要性とその場合の対応方法は
C12: 合意書を最適化させるにあたってのポイント
C13: 未来の業務委託費用の支払いは同一企業で問題ないのか。
A14: 46052 | C14: ご質問の件ですが、在留資格「技術・人文知識・国際業務（いわゆる技人国）」につきましては、原則として業務委託契約での就業は認められておりません。 技人国は「雇用契約」を前提とした在留資格であり、指揮命令下での業務・安定的な給与支払いが要件となるため、業務委託（成果報酬・裁量労働）との併用、いわゆる**「一部社員・一部業務委託」という形態も、実務上は認められない扱い**となります。 なお、業務委託が可能なのは永住者、日本人の配偶者等、定住者などの身分系在留資格に限られます。 そのため、技人国の方を起用する場合は、雇用契約（社員・契約社員等）に一本化する形が安全となります。
A15: 46055 | C15: 基本給を減額することにより標準報酬月額が下がるので産休手当も必然的に下がると思いますが、その場合昨年度の基本給だけ下げない方法も可能でしょうか。

Sheet 登記前の経費シート
A1: 日付 | B1: 名目 | C1: 金額 | D1: 備考
A2: 46037 | B2: 03plus契約料 | C2: 25446 | D2: 尾崎さんの楽天銀行で振り込み ※法人登記後変更する
A3: 46037 | B3: クラウドサイン | C3: 11000 | D3: 初期費用：0円 月額費用：10,000円（税込 11,000円） 年額費用：120,000円（税込 132,000円） 書類送信費用：1件あたり200円（税込 220円） ※毎月、月額費用と当該月の送信件数に応じた書類送信費用をお支払いいただきます
A4: 46045 | B4: 一般社団法人設立サポート費用 | C4: 120000 | D4: 【明細】 ■ 報酬額 ・一般社団法人設立登記費用（司法書士） 数量：1 単価：90,000円 金額：90,000円 ・値引き（顧問契約分） 数量：1 単価：-90,000円 金額：-90,000円 ・定款作成費用 数量：1 単価：0円 金額：0円 ■ 登録免許税又は印紙等費用 ・一般社団法人設立登録免許税 数量：1 単価：60,000円 金額：60,000円 ・定款印紙代 数量：1 単価：40,000円 金額：40,000円 ・電子定款による値引き 数量：1 単価：-40,000円 金額：-40,000円 ・定款認証費用（公証役場） 数量：1 単価：52,000円 金額：52,000円 ・登記事項証明書（1通） 数量：1 単価：500円 金額：500円 ・印鑑証明書（1通） 数量：1 単価：500円 金額：500円 ■ その他費用 ・郵送費 数量：1 単価：2,150円 金額：2,150円 ・法人印鑑作成費用（代表印・銀行印・角印・ケース） 数量：1 単価：5,860円 金額：5,860円
A5: 46053 | B5: クラウドサイン送信費用 | C5: 12980 | D5: 送信合計 59 ×220円
A6: 46077 | B6: 03plus1月分費用 | C6: 3942
A7: 46053 | B7: 従業員動画作成費用(外注費用) | C7: 60,000円 | D7: 大村に正確な数字を確認する

Sheet スターターキット
A1: 📦 スターターキット完全一覧
A3: 事業スタートに必要な全ての書類・ツール・資料を完全網羅
A4: 現状14項目 → 提案82項目（合計）
A6: カテゴリ | B6: No | C6: 項目名 | D6: 形式 | E6: 重要度 | F6: ステータス | G6: 備考 | H6: 備考
A8: 【現状の項目】14項目
A10: Webサイト
B11: 1 | C11: 会社HP | D11: Web | E11: ★★★ | F11: □
A12: 契約・法務書類（7項目）
B13: 2 | C13: 組合員契約書 | D13: Word/PDF | E13: ★★★ | F13: □ | G13: 弁護士チェック必須 | H13: https://docs.google.com/document/d/10-VrAL2LJeN1zCDoCIbBPoYFEctPAaMmkyVrnG474dk/edit?tab=t.0 | I13: https://docs.google.com/document/d/1iPK2y4dy5PZvpkpI3fK8S4_A0RbQg3WYXCTIzGvqRJc/edit?usp=sharing
B14: 3 | C14: 組合規定 | D14: Word/PDF | E14: ★★★ | F14: □ | H14: https://docs.google.com/document/d/1ktuLrfRa47YU0trBCXB_K1QkfWXXlmhGN0Co245UtGE/edit?tab=t.0
B15: 4 | C15: 代理店契約書 | D15: Word/PDF | E15: ★★★ | F15: □ | G15: バリュー社3%条件含む | H15: https://docs.google.com/document/d/1FgSSlzyvZcQ2Zw8jPO869CIqX9X4KhHyJU2luncwQqo/edit?usp=sharing
B16: 5 | C16: 機密情報および個人情報の取扱いに関する同意書 | D16: Word/PDF | E16: ★★★ | F16: □ | H16: https://docs.google.com/document/d/1PmYDTBTh2e0Qb7kZtHiWXCQZluRcKGcn3B_cuJY5qms/edit?usp=sharing
B17: 6 | C17: 反社会的勢力の排除に関する誓約書 | D17: Word/PDF | E17: ★★★ | F17: □ | H17: https://docs.google.com/document/d/1SJdWNy1dzF9gIQoPVrMiZ2o6FjfPcZItKQpubZCWVuQ/edit?usp=sharing
B18: 7 | C18: 業務委託契約書 | D18: Word/PDF | E18: ★★★ | F18: □ | G18: 従業員用 | H18: https://docs.google.com/document/d/17HRwAb2JJMneLaPYGED_-ZfcxzHG5ddRTvHVYje4D9Q/edit?tab=t.0
B19: 8 | C19: 従業員同意書 | D19: Word/PDF | E19: ★★★ | F19: □ | G19: 人事労務評価制度への同意 | H19: https://docs.google.com/document/d/1Ml6mlJ0yM4VNEMLQ66PGF_EO_5ruKDx41LtUK6s3jkI/edit?tab=t.0
A20: 教育・説明資料（4項目）
B21: 9 | C21: 従業員説明動画(LLS) | D21: MP4 | E21: ★★★ | F21: □ | G21: LMSで自動生成
B22: 10 | C22: 営業資料(組合入会前) | D22: PPT/PDF | E22: ★★★ | F22: □ | H22: https://www.canva.com/design/DAG-esrNdQo/pa4F3wjPArqqaN8-T72ZTA/view?utm_content=DAG-esrNdQo&utm_campaign=designshare&utm_medium=link2&utm_source=uniquelinks&utlId=h115d8fd5a7
B23: 11 | C23: トークスクリプト | D23: Word/PDF | E23: ★★★ | F23: □
B24: 12 | C24: 概要説明資料 | D24: PPT/PDF | E24: ★★★ | F24: □ | H24: https://www.canva.com/design/DAG-D0UMy1s/Gt3ICNEMs3JH1-oaBb4v2A/view?utm_content=DAG-D0UMy1s&utm_campaign=designshare&utm_medium=link2&utm_source=uniquelinks&utlId=hec288880b9
A25: 業務書類（2項目）
B26: 13 | C26: 還付金請求書 | D26: Excel/PDF | E26: ★★★ | F26: □
B27: 14 | C27: 必要書類提出フォーム | D27: Excel/Web | E27: ★★★ | F27: □ | G27: Googleフォーム等 | H27: https://yjpv5pf0p3pj.jp.larksuite.com/share/base/form/shrjp1ksluRzpVbtKSG0VwOaTYe
A30: 【追加提案項目】68項目
A32: 1. 年金事務所申請関連書類（6項目）
B33: 15 | C33: 過誤申立書フォーマット | D33: Word/Excel | E33: ★★★ | F33: □ | G33: 年金事務所提出用
B34: 16 | C34: 人事評価制度変更届出書 | D34: Word/PDF | E34: ★★★ | F34: □
B35: 17 | C35: 弁護士意見書ひな形 | D35: Word/PDF | E35: ★★★ | F35: □ | G35: 伊藤先生
B36: 18 | C36: 新旧制度比較表フォーマット | D36: Excel/Word | E36: ★★★ | F36: □ | G36: 伊藤先生
B37: 19 | C37: 業務実態を示す資料フォーマット | D37: Word/PDF | E37: ★★★ | F37: □ | G37: 伊藤先生
B38: 20 | C38: 年金事務所提出書類チェックリスト | D38: Excel | E38: ★★★ | F38: □ | G38: 伊藤先生
A39: 2. シミュレーション・試算ツール（5項目）
B40: 21 | C40: 簡易シミュレーター（Excel） | D40: Excel | E40: ★★★ | F40: □ | G40: 営業用 | H40: https://st022187.static.jp/d/social-insurance-simulator/
B41: 22 | C41: 詳細シミュレーター（Excel） | D41: Excel | E41: ★★★ | F41: □ | G41: 精密試算用 | H41: https://docs.google.com/spreadsheets/d/1mE2582OK3Sy8POqKTShjK9eSLI3cc2gB4zhqkf-syFI/edit?usp=sharing
B42: 23 | C42: 個別従業員シミュレーション資料 | D42: Excel | E42: ★★★ | F42: □ | G42: 従業員説明会用
B43: 24 | C43: 還付金グラフ自動生成ツール | D43: Excel | E43: ★★ | F43: □ | G43: グラフ自動作成
B44: 25 | C44: 見積書自動生成ツール | D44: Excel | E44: ★★★ | F44: □ | G44: 今週中必須
A45: 3. 営業支援ツール（9項目）
B46: 26 | C46: LINE公式アカウント設定ガイド | D46: PDF | E46: ★★★ | F46: □
B47: 27 | C47: プロライン導線設定マニュアル | D47: PDF | E47: ★★★ | F47: □
B48: 28 | C48: 初回面談用プレゼン資料（PPT） | D48: PPT | E48: ★★★ | F48: □
B49: 29 | C49: 営業用パンフレット（PDF） | D49: PDF | E49: ★★★ | F49: □ | G49: Figmaで作成
B50: 30 | C50: サービス紹介動画（3分） | D50: MP4 | E50: ★★ | F50: □ | G50: YouTube掲載
B51: 31 | C51: 導入事例集 | D51: PDF | E51: ★★★ | F51: □ | G51: 建設業・介護福祉業
B52: 32 | C52: FAQ資料（100問） | D52: PDF/Word | E52: ★★ | F52: □
B53: 33 | C53: 料金表 | D53: PDF | E53: ★★★ | F53: □ | G53: シンプル版
B54: 34 | C54: 競合比較資料 | D54: Excel/PDF | E54: ★★ | F54: □ | G54: 差別化ポイント明記
A55: 4. 顧客管理・業務フロー（6項目）
B56: 35 | C56: CRM顧客管理テンプレート | D56: Excel | E56: ★★★ | F56: □ | G56: Salesforce等
B57: 36 | C57: 案件管理シート（Excel） | D57: Excel | E57: ★★★ | F57: □
B58: 37 | C58: 9ステップ進捗管理シート | D58: Excel | E58: ★★★ | F58: □
B59: 38 | C59: 業務フローチャート | D59: Visio/PDF | E59: ★★ | F59: □
B60: 39 | C60: タスク管理チェックリスト | D60: Excel | E60: ★★ | F60: □
B61: 40 | C61: 顧客対応履歴テンプレート | D61: Excel | E61: ★★ | F61: □
A62: 5. 従業員説明会関連（6項目）
B63: 41 | C63: 従業員説明会用プレゼン資料（PPT） | D63: PPT | E63: ★★★ | F63: □
B64: 42 | C64: 従業員向けQ&A資料 | D64: PDF | E64: ★★★ | F64: □
B65: 43 | C65: 従業員向け制度説明動画（10分） | D65: MP4 | E65: ★★ | F65: □
B66: 44 | C66: DC（確定拠出年金）説明資料 | D66: PDF | E66: ★★ | F66: □ | G66: 4,000万円→9,274万円
B67: 45 | C67: 年金シミュレーション比較資料 | D67: Excel | E67: ★★ | F67: □ | G67: 国民年金 vs DC
B68: 46 | C68: 同意書回収チェックリスト | D68: Excel | E68: ★★★ | F68: □
A69: 6. 内部管理・マニュアル（6項目）
B70: 47 | C70: 業務マニュアル（全体版） | D70: PDF | E70: ★★★ | F70: □ | G70: 100ページ超
B71: 48 | C71: CS対応マニュアル | D71: PDF | E71: ★★★ | F71: □ | G71: 飯塚作成
B72: 49 | C72: 年金事務所対応マニュアル（一課vs三課） | D72: PDF | E72: ★★★ | F72: □ | G72: 必読
B73: 50 | C73: 税務調査対応マニュアル | D73: PDF | E73: ★★★ | F73: □ | G73: 売上否認されない論理
B74: 51 | C74: トラブルシューティングガイド | D74: PDF | E74: ★★ | F74: □
B75: 52 | C75: 緊急時対応フローチャート | D75: PDF | E75: ★★ | F75: □
A76: 7. クロスセル関連資料（5項目）
B77: 53 | C77: DC（確定拠出年金）提案資料 | D77: PDF | E77: ★★★ | F77: □ | G77: 2倍の運用成果
B78: 54 | C78: 生命保険提案資料 | D78: PDF | E78: ★★★ | F78: □ | G78: 90%紹介料
B79: 55 | C79: 節税商材一覧 | D79: Excel/PDF | E79: ★★ | F79: □ | G79: 還付金の使途
B80: 56 | C80: 採用ブースト事業説明資料 | D80: PDF | E80: ★★ | F80: □ | G80: 7-8分の1単価
B81: 57 | C81: 助成金・研修サービス案内 | D81: PDF | E81: ★ | F81: □
A82: 8. コンプライアンス・リスク管理（5項目）
B83: 58 | C83: コンプライアンスチェックリスト | D83: Excel | E83: ★★★ | F83: □
B84: 59 | C84: 情報セキュリティ管理規程 | D84: Word/PDF | E84: ★★★ | F84: □ | G84: Google Drive禁止
B85: 60 | C85: 個人情報管理台帳 | D85: Excel | E85: ★★★ | F85: □
B86: 61 | C86: リスク管理チェックリスト | D86: Excel | E86: ★★ | F86: □
B87: 62 | C87: 法改正モニタリングシート | D87: Excel | E87: ★★★ | F87: □ | G87: 2年以内が勝負
A88: 9. 報告・精算関連書類（6項目）
B89: 63 | C89: 月次報告書フォーマット | D89: Excel/Word | E89: ★★ | F89: □
B90: 64 | C90: 還付金受領報告書 | D90: Word/PDF | E90: ★★★ | F90: □
B91: 65 | C91: 成果報酬請求書 | D91: Excel/PDF | E91: ★★★ | F91: □ | G91: 20%
B92: 66 | C92: 領収書フォーマット | D92: Excel/PDF | E92: ★★★ | F92: □
B93: 67 | C93: 精算明細書 | D93: Excel | E93: ★★ | F93: □
B94: 68 | C94: 従業員配分計算シート | D94: Excel | E94: ★★ | F94: □
A95: 10. 代理店支援ツール（5項目）
B96: 69 | C96: 代理店向け説明資料 | D96: PDF | E96: ★★★ | F96: □
B97: 70 | C97: 代理店契約条件一覧（機密） | D97: Excel | E97: ★★★ | F97: □ | G97: バリュー社3%等
B98: 71 | C98: 代理店教育プログラム | D98: PDF | E98: ★★ | F98: □
B99: 72 | C99: 代理店向けロールプレイング台本 | D99: Word/PDF | E99: ★★ | F99: □
B100: 73 | C100: 代理店向け月次報告フォーマット | D100: Excel | E100: ★★ | F100: □
A101: 11. システム・データ管理（4項目）
B102: 74 | C102: 書類管理台帳（Excel） | D102: Excel | E102: ★★★ | F102: □
B103: 75 | C103: データバックアップ手順書 | D103: PDF | E103: ★★ | F103: □
B104: 76 | C104: パスワード管理ルール | D104: PDF | E104: ★★★ | F104: □
B105: 77 | C105: クラウドストレージ運用ガイド | D105: PDF | E105: ★★ | F105: □ | G105: Google Drive以外
A106: 12. ブランディング・デザイン（5項目）
B107: 78 | C107: ロゴデータ（AI/PNG/SVG） | D107: AI/PNG/SVG | E107: ★★★ | F107: □
...

Sheet BizDev
A1: ✅ 社会保険料適正化サービス BizDev チェックリスト
A2: このチェックリストは、社会保険料適正化サービスの事業健全性を189項目で評価します。
A4: カテゴリ | B4: サブカテゴリ | C4: チェック項目 | D4: 説明・基準 | E4: 優先度 | F4: 確認頻度 | G4: 担当/責任 | I4: 完了
A5: ガバナンス・組織 | B5: コンプラ | C5: 反社チェックフローがあるか | D5: 顧客・パートナーの反社チェックを実施 | E5: S | F5: 月次 | G5: 管理部
A6: ガバナンス・組織 | B6: コンプラ | C6: 社会保険労務士との顧問契約があるか | D6: 適正化サービスの法的妥当性を常時確認 | E6: S | F6: 契約中 | G6: 経営層
A7: ガバナンス・組織 | B7: コンプラ | C7: 税理士との顧問契約があるか | D7: 税務面での適法性を常時確認 | E7: S | F7: 契約中 | G7: 経営層
A8: ガバナンス・組織 | B8: 内部統制 | C8: 稟議・承認が電子化されているか | D8: 契約承認フローの透明性確保 | E8: A | F8: 月次 | G8: 管理部
A9: ガバナンス・組織 | B9: 内部統制 | C9: 内部通報/ホットラインの仕組みがあるか | D9: 不正防止の仕組み | E9: A | F9: 四半期 | G9: 管理部
A10: ガバナンス・組織 | B10: 情報共有 | C10: 経営数値が幹部に共有されているか | D10: 売上・契約数・還付額などKGI/KPI | E10: S | F10: 週次 | G10: 経営層
A11: ガバナンス・組織 | B11: 情報共有 | C11: 議事録・決定事項がアーカイブされているか | D11: 経営会議・営業会議の記録保存 | E11: A | F11: 月次 | G11: 管理部
A12: ガバナンス・組織 | B12: 意思決定 | C12: 経営会議の開催頻度と議題が固定されているか | D12: 週次または月次で定例化 | E12: S | F12: 週次 | G12: 経営層
A13: ガバナンス・組織 | B13: 意思決定 | C13: 重要決裁の権限規程があるか | D13: 契約金額・割引率などの決裁ライン | E13: S | F13: 四半期 | G13: 経営層
A14: ガバナンス・組織 | B14: 組織設計 | C14: RACIで責任所在が明確か | D14: 営業・CS・伊藤先生側・税理士の役割明確化 | E14: A | F14: 四半期 | G14: 経営層
A15: ガバナンス・組織 | B15: 組織設計 | C15: 組織図と役割が最新化されているか | D15: 営業5名→20名への拡大計画と連動 | E15: A | F15: 月次 | G15: 人事
A16: ガバナンス・組織 | B16: KPI設計 | C16: KPIを週次/月次でモニタリングする場があるか | D16: 商談数・成約数・還付実行数など | E16: S | F16: 週次 | G16: 営業部長
A17: ガバナンス・組織 | B17: KPI設計 | C17: 事業KGI→事業KPI→現場KPIがピラミッドでつながっているか | D17: 売上3億→契約30社→商談150社 | E17: S | F17: 月次 | G17: 経営層
A18: ガバナンス・組織 | B18: ミッション/ビジョン | C18: 存在意義（Why）が一文で定義されているか | D18: 例: 企業と従業員の両方を豊かにする | E18: S | F18: 年次 | G18: 経営層 | H18: 中小企業が“知らないことで損をし続ける構造”を、仕組みで改善する | I18: 完了
A19: ガバナンス・組織 | B19: ミッション/ビジョン | C19: 3年ビジョンを数値とストーリーで示しているか | D19: 3年後: 売上10億円、契約100社など | E19: S | F19: 年次 | G19: 経営層 | H19: 1年後：売上25.2億、粗利12,6億、契約420社 | I19: 完了
A20: ガバナンス・組織 | B20: ミッション/ビジョン | C20: MVVが組織に共有・浸透しているか | D20: 採用・評価・研修に連動しているか | E20: A | F20: 半期 | G20: 人事
A21: ガバナンス・組織 | B21: 市場・ポジショニング | C21: 主要市場の定義が明確か（業界・エリア・顧客規模） | D21: 従業員10-50名、年間給与総額5000万円以上 | E21: S | F21: 四半期 | G21: 営業部長 | H21: 日本全体の社会保険料収入80.1兆
A22: ガバナンス・組織 | B22: 市場・ポジショニング | C22: 競合マップを四象限で描けるか | D22: 遡及期間×成果報酬率で競合分析 | E22: S | F22: 四半期 | G22: 営業部長
A23: ガバナンス・組織 | B23: 市場・ポジショニング | C23: 自社の差別化ポイント（USP）が3つ以内で話せるか | D23: ①5年遡及 ②初期費用0円 ③実態構築支援 | E23: S | F23: 月次 | G23: 営業部長
A24: 営業・マーケティング | B24: リード獲得 | C24: 無料診断の提供体制があるか | D24: 算定基礎届から還付見込額を無料試算 | E24: S | F24: 毎日 | G24: 営業
A25: 営業・マーケティング | B25: リード獲得 | C25: 紹介営業の仕組みがあるか | D25: 税理士・伊藤先生側・既存顧客からの紹介 | E25: S | F25: 月次 | G25: 営業部長
A26: 営業・マーケティング | B26: リード獲得 | C26: セミナー・説明会を定期開催しているか | D26: 経営者向け社会保険料削減セミナー | E26: A | F26: 月次 | G26: 営業
A27: 営業・マーケティング | B27: リード獲得 | C27: Web広告（Google/Facebook）を運用しているか | D27: 「社会保険料 削減」などのキーワード | E27: B | F27: 月次 | G27: マーケ
A28: 営業・マーケティング | B28: 営業プロセス | C28: 営業トークスクリプトが整備されているか | D28: 5シーン別の台本を全員が暗記 | E28: S | F28: 四半期 | G28: 営業部長
A29: 営業・マーケティング | B29: 営業プロセス | C29: 還付金シミュレーターを商談で使っているか | D29: Excel使用、リアルタイム計算 | E29: S | F29: 毎日 | G29: 営業
A30: 営業・マーケティング | B30: 営業プロセス | C30: 提案書テンプレートがあるか | D30: 還付見込額・配分・スケジュールを記載 | E30: A | F30: 月次更新 | G30: 営業部長
A31: 営業・マーケティング | B31: 営業プロセス | C31: 成約後の手続きフローが明文化されているか | D31: 契約→資料収集→伊藤先生側連携→実行 | E31: S | F31: 四半期 | G31: CS
A32: 営業・マーケティング | B32: 営業プロセス | C32: クロージング時の価格交渉ルールがあるか | D32: 成果報酬15-20%の裁量範囲を明確化 | E32: A | F32: 四半期 | G32: 営業部長
A33: 営業・マーケティング | B33: 案件管理 | C33: CRMで案件進捗を管理しているか | D33: リード→商談→成約→実行の各段階 | E33: S | F33: 毎日 | G33: 営業部長
... A37: 法務・コンプライアンス | B37: 契約書 | C37: 業務委託契約書のひな型があるか | D37: 実態構築用の委託契約テンプレート | E37: S | F37: 年次見直し | G37: 法務
A38: 法務・コンプライアンス | B38: 契約書 | C38: 組合規約が整備されているか | D38: 組合員の権利義務を明文化 | E38: S | F38: 年次見直し | G38: 法務 | I38: 完了
A39: 法務・コンプライアンス | B39: 契約書 | C39: 秘密保持契約（NDA）があるか | D39: 算定基礎届など機密情報の取扱い | E39: S | F39: 個別締結 | G39: 法務 | I39: 完了
A40: 法務・コンプライアンス | B40: 実態構築 | C40: 業務委託の実態基準が文書化されているか | D40: 月○回の業務実施、報告書作成など | E40: S | F40: 四半期 | G40: 伊藤先生側
A41: 法務・コンプライアンス | B41: 実態構築 | C41: 業務日報・報告書のテンプレートがあるか | D41: 実態の証跡として保管 | E41: S | F41: 毎月 | G41: CS
A42: 法務・コンプライアンス | B42: 実態構築 | C42: 業務実施の写真・動画を記録しているか | D42: 調査時の証拠として活用 | E42: A | F42: 毎月 | G42: CS
A43: 法務・コンプライアンス | B43: 実態構築 | C43: 実態構築チェックリストがあるか | D43: 10項目以上の確認項目 | E43: S | F43: 案件ごと | G43: 伊藤先生側
A44: 法務・コンプライアンス | B44: 調査対応 | C44: 年金事務所調査への対応マニュアルがあるか | D44: 調査時の説明・資料提出フロー | E44: S | F44: 年次見直し | G44: 伊藤先生側
A45: 法務・コンプライアンス | B45: 調査対応 | C45: 税務調査への対応マニュアルがあるか | D45: 給与所得vs事業所得の説明準備 | E45: S | F45: 年次見直し | G45: 税理士
A46: 法務・コンプライアンス | B46: 調査対応 | C46: 調査時の立会い体制があるか | D46: 伊藤先生側・税理士が必ず同席 | E46: S | F46: 随時 | G46: 伊藤先生側・税理士
A47: 法務・コンプライアンス | B47: 調査対応 | C47: 過去の調査事例をデータベース化しているか | D47: 指摘事項と対応策を蓄積 | E47: A | F47: 随時更新 | G47: 伊藤先生側
A48: オペレーション | B48: 資料収集 | C48: 顧客から収集する資料リストがあるか | D48: 算定基礎届・給与台帳・就業規則など | E48: S | F48: 案件ごと | G48: CS
A49: オペレーション | B49: 資料収集 | C49: 資料の電子化・保管ルールがあるか | D49: PDF化、顧客別フォルダ管理 | E49: A | F49: 案件ごと | G49: CS
A50: オペレーション | B50: 資料収集 | C50: 資料収集の平均所要日数を把握しているか | D50: 目標: 依頼から7日以内に完了 | E50: A | F50: 月次 | G50: CS
A51: オペレーション | B51: 還付申請 | C51: 申請書類のひな型があるか | D51: 訂正届・遡及変更の申請様式 | E51: S | F51: 年次更新 | G51: 伊藤先生側
... A193: イノベーション | B193: 新技術 | C193: 最新の社会保険制度動向を追跡しているか | D193: マイナンバー連携・デジタル化など | E193: A | F193: 四半期 | G193: 伊藤先生側

Sheet 営業管理売上見込
A1: 月 | B1: 月間獲得件数 | C1: 累計獲得件数 | D1: 日間獲得数
A2: 1月 | B2: 6 | C2: 6 | D2: =B2/30 -> 0.2
A3: 2月 | B3: 9 | C3: 15 | D3: =B3/30 -> 0.3
A4: 3月 | B4: 12 | C4: 27 | D4: =B4/30 -> 0.4
A5: 4月 | B5: 15 | C5: 42 | D5: =B5/30 -> 0.5
A6: 5月 | B6: 18 | C6: 60 | D6: =B6/30 -> 0.6
A7: 6月 | B7: 23 | C7: 83 | D7: =B7/30 -> 0.76666667
A8: 7月 | B8: 29 | C8: 112 | D8: =B8/30 -> 0.96666667
A9: 8月 | B9: 36 | C9: 148 | D9: =B9/30 -> 1.2
A10: 9月 | B10: 46 | C10: 194 | D10: =B10/30 -> 1.5333333
A11: 10月 | B11: 56 | C11: 250 | D11: =B11/30 -> 1.8666667
A12: 11月 | B12: 64 | C12: 314 | D12: =B12/30 -> 2.1333333
A13: 12月 | B13: 106 | C13: 420 | D13: =B13/30 -> 3.5333333

Sheet 開発要件定義
A1: あなたは、公的資金（補助金・助成金・行政連携案件）における
A2: システム開発要件定義書の作成を専門とするITコンサルタント兼PMです。
A3: 以下の【簡易要件定義】をもとに、
A4: 「公的資金開発に耐えうる正式な要件定義書」を作成してください。
A5: ■ 要求水準
A6: - 開発会社にそのまま見積・設計依頼ができるレベル
A7: - 補助金・公的資金の審査で指摘されない論理性・網羅性
A8: - 業務要件／機能要件／非機能要件を明確に分離
A9: - 曖昧な表現は避け、誰が読んでも同じ解釈になること
A10: - 「やること／やらないこと（スコープ）」を明確にすること
A11: ■ アウトプット形式
A12: 以下の章立てで、**日本語・テキスト形式**で作成してください。
... A93: - 公的資金案件として説明責任が果たせる文章にすること

Sheet 00_マスター目次
A1: 📋 社会保険料適正化サービス 完全統合版 v23
A2: 〜 実務で即使える完全マニュアル 〜
A3: 【v23の特徴】
A4: ✓ 全ナレッジを完全統合（情報欠落ゼロ）
A5: ✓ 実務フロー重視の構成
A6: ✓ 役割別最適化
A7: ✓ 視認性を最大化
A8: ✓ 9シートで完結
A11: No | B11: シート名 | C11: 内容 | D11: 対象者
A12: 00 | B12: マスター目次 | C12: ナビゲーション・クイックスタート | D12: 全員
A13: 01 | B13: 事業コンセプト完全理解 | C13: 成立理由・1顧客7収入・2年計画・市場 | D13: 経営者・営業
A14: 02 | B14: 法的基盤と防御戦略 | C14: 使用従属性・4層防御・伊藤先生・リスク | D14: 経営者・営業
A15: 03 | B15: 営業完全マニュアル | C15: 9ステップ・トーク・反論処理50 | D15: 営業・代理店
A16: 04 | B16: シミュレーター＆ツール | C16: 簡易版・詳細版・グラフ・計算式 | D16: 営業・CS
A17: 05 | B17: CS実務ガイド | C17: オンボーディング・案件管理・品質 | D17: CS
A18: 06 | B18: 書類・契約テンプレート | C18: 契約書・申請書・同意書・説明資料 | D18: CS・バックオフィス
A19: 07 | B19: 組織運営・拡大戦略 | C19: 代理店・KPI・協会運営・研修 | D19: 経営者・管理者
A20: 08 | B20: リファレンス | C20: 用語・法律・FAQ・連絡先・履歴 | D20: 全員
A22: 【5秒でスタート】
A23: 🎯 経営者の方 | B23: → 01 → 02 → 07 | C23: 事業理解・法的基盤・組織戦略
A24: 💼 営業担当の方 | B24: → 01 → 03 → 04 | C24: コンセプト・営業術・ツール使用
A25: 🎧 CS担当の方 | B25: → 05 → 04 → 06 | C25: 実務手順・ツール・書類管理
A26: 📊 バックオフィスの方 | B26: → 06 → 07 | C26: 書類・KPI管理
A27: 🤝 代理店の方 | B27: → 01 → 02 → 03 | C27: コンセプト・法的理解・営業術
A29: 【今週やること】
A31: □ | B31: 01を読んで事業コンセプトを理解（15分）
A32: □ | B32: 02で法的基盤を確認（20分）
A33: □ | B33: 03で営業9ステップを習得（30分）
A34: □ | B34: 04でシミュレーターを試用（10分）
A35: □ | B35: 自分の役割のシートを精読（30分）

Sheet 01_事業コンセプト完全理解
A1: 💡 事業コンセプト完全理解
A2: なぜ成立するか・1顧客7収入・2年計画・市場機会
A3: なぜ成立するか・1顧客7収入モデル・2年計画を完全理解
A4: ━━━━━━━━━━━━━━━━━━━━━━━━━━━━━━━━━━━━━━━━━━━━━━━━━━
A5: 第1章: なぜこのビジネスが成立するのか
A6: ━━━━━━━━━━━━━━━━━━━━━━━━━━━━━━━━━━━━━━━━━━━━━━━━━━
A7: ■ 3つの理由
A8: 理由1 | B8: 40年前の曖昧な基準 | C8: 使用従属性の判断基準が昭和60年制定で現代に不適合 | D8: ★★★★★
A9: 理由2 | B9: 弁護士による法的防御 | C9: 労働法専門弁護士が監査済み契約書を作成 | D9: ★★★★★
A10: 理由3 | B10: Win-Win構造 | C10: 企業も従業員も両方メリット→社会問題化しにくい | D10: ★★★★★
A11: ■ 市場機会
A12: 潜在市場 | B12: 日本全国の中小企業 | C12: 約380万社
A13: ターゲット | B13: 従業員10名以上 | C13: 約100万社
A14: 現実的ターゲット | B14: 従業員10-100名 | C14: 約30万社
A15: → 2年で1,000社獲得は市場の0.3%のみ（十分達成可能）
A16: ━━━━━━━━━━━━━━━━━━━━━━━━━━━━━━━━━━━━━━━━━━━━━━━━━━
A17: 第2章: 1顧客7収入モデルの全貌
A18: ━━━━━━━━━━━━━━━━━━━━━━━━━━━━━━━━━━━━━━━━━━━━━━━━━━
A19: ■ 7つの収入源（詳細）
A20: 収入 | B20: 内容 | C20: 金額 | D20: タイミング | E20: 継続性 | F20: 難易度
A21: ①初期コンサル | B21: 無料診断・提案 | C21: 0-30万円 | D21: 初回 | E21: 1回のみ | F21: 低
A22: ②成功報酬 | B22: 精算金の20-30% | C22: 500-2,000万円 | D22: 精算時 | E22: 1回のみ | F22: 中
A23: ③月額顧問料 | B23: 継続サポート | C23: 3-10万円/月 | D23: 毎月 | E23: 継続 | F23: 低
A24: ④追加サービス | B24: 研修・セミナー | C24: 10-50万円 | D24: 随時 | E24: 随時 | F24: 中
A25: ⑤紹介料 | B25: 他社紹介 | C25: 成功報酬の10% | D25: 紹介時 | E25: 随時 | F25: 低
A26: ⑥代理店フィー | B26: 代理店からの収入 | C26: 成功報酬の50% | D26: 契約時 | E26: 随時 | F26: 中
A27: ⑦アップセル | B27: 他サービス | C27: 個別見積 | D27: 随時 | E27: 随時 | F27: 高
A28: ■ 収益シミュレーション
A29: ケース | B29: 初回 | C29: 継続（年間） | D29: 合計（初年度）
A30: 小規模（10名） | B30: 500万円 | C30: 36万円 | D30: 536万円
A31: 中規模（30名） | B31: 1,200万円 | C31: 72万円 | D31: 1,272万円
A32: 大規模（100名） | B32: 3,000万円 | C32: 120万円 | D32: 3,120万円
A33: → 100社で初年度10億円超の収益可能
A34: ━━━━━━━━━━━━━━━━━━━━━━━━━━━━━━━━━━━━━━━━━━━━━━━━━━
A35: 第3章: 2年計画（なぜ2年以内なのか）
A36: ━━━━━━━━━━━━━━━━━━━━━━━━━━━━━━━━━━━━━━━━━━━━━━━━━━
A37: ■ タイムライン
A38: 時期 | B38: 状況 | C38: 対応 | D38: 目標
A39: 現在 | B39: 法律40年前、基準曖昧 | C39: バリュー社で実証 | D39: 1社成功
A40: 1-3ヶ月 | B40: 実証結果確認 | C40: 代理店10社選定 | D40: 実証完了
A41: 4-6ヶ月 | B41: 初期展開加速 | C41: 各社10社獲得 | D41: 100社達成
A42: 7-12ヶ月 | B42: 本格展開 | C42: 全国展開 | D42: 1,000社達成
A43: 1-2年後 | B43: 法改正の兆候 | C43: 既存契約保全 | D43: 継続収入確保
A44: 2-3年後 | B44: 新法施行の可能性 | C44: 新サービス移行 | D44: 事業転換
A45: ■ Phase別詳細計画
A46: Phase 1（1-3ヶ月）: 実証
A47: 目標: バリュー社で成功実証
A48: タスク: 実証実施・データ収集・ノウハウ文書化
A49: 成果: 1社契約・プロセス確立
A50: Phase 2（4-6ヶ月）: 初期展開
A51: 目標: 100社獲得
A52: タスク: 代理店10社選定・研修・営業開始
A53: 成果: 月間1億円ストック収入
A54: Phase 3（7-12ヶ月）: 本格展開
A55: 目標: 1,000社獲得
A56: タスク: 全国代理店展開・マーケティング強化
... A62: ■ 3ステップで即開始
A63: STEP1（2分） | B63: この第1部を読む | C63: 全体像を把握
A64: STEP2（1分） | B64: 自分の役割を確認 | C64: 読むべきシートを把握
A65: STEP3（2分） | B65: 今週やることリストを確認 | C65: 具体的なタスクを開始
A66: ■ 役割別の読み方
A67: 役割 | B67: 読むべきシート | C67: 読み方 | D67: 重要度
A68: 🎯 経営者 | B68: 01 → 02 → 03 → 09 | C68: START HERE → ビジネス理解 → 法的基盤 → 組織運営 | D68: ★★★★★
A69: 💼 営業担当 | B69: 01 → 05 → 07 | C69: START HERE → 営業マニュアル → シミュレーター | D69: ★★★★★
A70: 🎧 CS担当 | B70: 01 → 06 → 07 → 08 | C70: START HERE → CS業務 → ツール → 書類管理 | D70: ★★★★★
A71: 📊 バックオフィス | B71: 01 → 08 → 09 | C71: START HERE → 書類管理 → KPI・財務 | D71: ★★★★☆
A72: 🤝 代理店 | B72: 01 → 04 → 05 | C72: START HERE → 市場戦略 → 営業マニュアル | D72: ★★★★★
A73: ━━━━━━━━━━━━━━━━━━━━━━━━━━━━━━━━━━━━━━━━━━━━━━━━━━
A74: 第2部: 事業の全体像（1枚絵）
A75: ━━━━━━━━━━━━━━━━━━━━━━━━━━━━━━━━━━━━━━━━━━━━━━━━━━
A76: ■ ビジネスモデル概要
A77: サービス名 | B77: 社会保険料適正化サービス
A78: 正式名称 | B78: 給与制度改革による社会保険料の適正化支援
A79: 運営 | B79: 一般社団法人公的資金教育推進協会
A80: ■ 事業の流れ（3フェーズ）
A81: Phase | B81: 期間 | C81: 目標 | D81: 内容 | E81: 成果
A82: Phase 1 | B82: 1-3ヶ月 | C82: 実証 | D82: バリュー社で実証・ノウハウ確立 | E82: 1社契約成功
A83: Phase 2 | B83: 4-6ヶ月 | C83: 100社 | D83: 厳選10社の代理店×10社 | E83: 月間1億円ストック
A84: Phase 3 | B84: 7-12ヶ月 | C84: 1,000社 | D84: 全国展開 | E84: 月間3億円ストック
A85: ■ 収益構造: 1顧客7収入モデル
A86: 収入源 | B86: 内容 | C86: 金額イメージ | D86: 備考
A87: ①初期コンサル | B87: 無料診断・契約 | C87: 0円〜30万円 | D87: 初回限定
A88: ②精算金の成功報酬 | B88: 精算金の20-30% | C88: 500万〜2,000万 | D88: 1回限り
A89: ③月額顧問料 | B89: 継続サポート | C89: 3万〜10万/月 | D89: 継続収入
A90: ④追加サービス | B90: 研修・セミナー | C90: 10万〜50万 | D90: 随時
A91: ⑤紹介料 | B91: 他社紹介 | C91: 成功報酬の10% | D91: 紹介ベース
A92: ⑥代理店フィー | B92: 代理店からの収入 | C92: 契約金の10-20% | D92: 代理店経由
A93: ⑦アップセル | B93: 他サービス販売 | C93: 個別見積 | D93: 顧客拡大
A94: → 1社あたり合計: 600万〜3,000万円（初年度）
A95: → 継続収入: 36万〜120万円/年（2年目以降）
A96: ━━━━━━━━━━━━━━━━━━━━━━━━━━━━━━━━━━━━━━━━━━━━━━━━━━
A97: 第3部: 今週やることリスト
A98: ━━━━━━━━━━━━━━━━━━━━━━━━━━━━━━━━━━━━━━━━━━━━━━━━━━
A99: 役割 | B99: 優先度 | C99: タスク | D99: 期限 | E99: ステータス
A100: 経営者 | B100: 最優先 | C100: 法的基盤の完全理解 | D100: 今週 | E100: □
A101: 経営者 | B101: 最優先 | C101: 2年計画の策定 | D101: 今週 | E101: □
A102: 経営者 | B102: 高 | C102: バリュー社実証の準備 | D102: 今週 | E102: □
A103: 営業 | B103: 最優先 | C103: 営業9ステップの習得 | D103: 今週 | E103: □
A104: 営業 | B104: 最優先 | C104: シミュレーターの使い方 | D104: 今週 | E104: □
A105: 営業 | B105: 高 | C105: 反論処理50の暗記 | D105: 今週 | E105: □
...

Sheet 02_法的基盤と防御戦略
A1: ⚖️ 法的基盤と防御戦略
A2: 使用従属性・4層防御・伊藤先生の叡智・リスク管理
A3: 使用従属性・弁護士戦略・4層防御・リスク管理を完全網羅
A4: 本サービスの法的基盤を支える伊藤先生の核心的ナレッジ
A5: ■ 1. 雇用契約と業務委託契約の判断基準「使用従属性」
A6: 項目 | B6: 内容 | C6: 本サービスへの影響
A7: 使用従属性とは | B7: 厚生労働省が定める雇用契約の判断基準 「使用者の指揮命令の下で労働すること」 約40年前（昭和60年）に制定された基準 | C7: 現代の働き方（リモートワーク、フレックス、 成果主義等）に対応できていない 判断が曖昧になる
A8: 判断要素の曖昧性 | B8: 使用従属性の判断要素: ①指揮監督下の労働 ②報酬の労務対償性 ③その他の要素（専属性、事業者性等） しかし「総合的に判断」という曖昧な表現 | C8: 明確な線引きが困難 個別事案ごとに判断が必要 グレーゾーンが存在する
A9: 現代の働き方との乖離 | B9: 現代の働き方: ・リモートワーク（指揮監督が見えにくい） ・フレックスタイム（時間管理が緩い） ・成果主義（労務対償性が不明確） ・副業・兼業の普及 | C9: 40年前の基準では判断が困難 業務委託契約として整理する 余地が生まれている
A10: 労働契約法の定義 | B10: 労働契約法第6条 「労働契約は、労働者が使用者に使用されて 労働し、使用者がこれに対して賃金を支払う ことについて、労働者及び使用者が合意する ことによって成立する」 | C10: 「使用されて」=使用従属性の有無 この解釈が曖昧 使用従属性の程度により 雇用契約と業務委託契約の境界が変わる
A11: ■ 2. 弁護士活用による法的防御（最重要）
A12: 戦略 | B12: 内容 | C12: 効果
A13: 弁護士による 契約書作成 | B13: 「弁護士による法的監査によって契約書を作成します」 という文言を契約書に明記 使用従属性の判断において「業務委託契約」が 適切であるという弁護士の法的見解を示す | C13: 税務署や年金事務所が異議を唱える場合、 弁護士（国家資格者）の法的判断に 異議を唱えることになる → 事実上の防御壁として機能
A14: 逃げ道の確保 | B14: 「弁護士が使用従属性を検討した結果、 業務委託契約として整理することが 法的に適切であると判断した」 という事実を契約書に残す | C14: 「弁護士の判断に基づいている」 という防御ラインを構築 企業側に悪意がないことの証明 善意の第三者として保護
A15: 国との対峙回避 | B15: 弁護士が作成した契約書に文句をつける = 国家資格者の専門的判断に異議を唱える = 国（法曹界）との対峙になる | C15: 実務上、税務署・年金事務所は 弁護士の判断を尊重せざるを得ない 介入のハードルが高くなる
A16: ■ 3. 雇用契約書の法的位置づけ
A17: 法的根拠 | B17: 詳細 | C17: 実務対応
A18: 雇用契約書は 義務ではない | B18: 労働基準法第15条: 「労働条件の明示」は義務 → 労働条件通知書の交付で足りる 雇用契約書の作成・締結は 法律で義務付けられていない | C18: あえて雇用契約書を作成しない という選択肢がある 労働条件通知書のみで 法的要件を満たす
A19: 労働条件通知書 との違い | B19: 労働条件通知書: 使用者→労働者への一方的通知 雇用契約書: 労使双方の合意を示す契約書 法的には通知書のみで問題ない | C19: 契約書という形式を避けることで 「使用従属性」の判断要素を 弱めることができる 双方合意の証拠を残さない戦略
A20: 業務委託契約書は必須 | B20: 業務委託契約では契約書が商習慣上必須 弁護士監査を経たことを明記 使用従属性が低いことを契約書で明確化: ・時間管理の自由 ・場所の自由 ・指揮命令の緩さ ・成果報酬性 | C20: こちらが主契約となる 法的整合性を確保 使用従属性の低さを 契約書で具体的に証明
A21: ■ 4. 同一労働同一賃金ガイドラインの活用
A22: 制度 | B22: 内容 | C22: 本サービスでの活用
A23: 正式名称 | B23: 「短時間・有期雇用労働者及び派遣労働者に対する 不合理な待遇の禁止等に関する指針」 （平成30年厚生労働省告示第430号） | C23: 国の政策として位置づけ 厚労省の方針に沿っている という正当性の根拠
A24: 趣旨 | B24: 雇用形態の違いによる不合理な待遇差を禁止 正規・非正規の区別なく「同一労働には同一賃金」 働き方改革関連法の一環として制定 | C24: 雇用契約と業務委託契約の 待遇差をなくす取り組み 業務内容が同じなら 契約形態を問わず公平に評価
A25: 厚労省の方針 | B25: 厚生労働省が待遇差をなくす取り組みを推進 判断要素: 「職務内容」 「職務内容・配置の変更範囲」 「その他の事情」 | C25: 本サービスはこの方針に 「乗っかっている」と主張 第三者評価により 公平な待遇を実現
A26: 営業トーク例 | B26: 「国の政策である同一労働同一賃金に基づき、 雇用形態ではなく『職務内容』で公平に評価する 制度を導入します」 | C26: 国の政策との整合性を強調 正当性をアピール 使用従属性の有無ではなく 職務内容で評価する正当性
A27: ■ 5. 使用従属性の5大判断要素と本サービスの設計
A28: 判断要素 | B28: 雇用契約（使用従属性:高） | C28: 業務委託契約（使用従属性:低） ← 本サービスの設計方針
A29: ①指揮監督性 | B29: 使用者の具体的な指揮命令の下で労働 時間・場所・方法を詳細に指定される 業務の進め方に裁量がない | C29: 自律的に業務遂行 時間・場所・方法の裁量が大きい → 成果報酬部分はこの設計 → 「成果」のみを評価
A30: ②報酬の 労務対償性 | B30: 時間給・日給・月給 労働時間に対する対価 働いた時間で報酬が決まる | C30: 成果報酬・出来高払い 成果に対する対価 → 業務委託報酬部分 → 生産性・付加価値で報酬決定
A31: ③業務の 代替性 | B31: 本人が自ら業務を行う必要あり 代替不可（労務提供義務） 欠勤時は控除 | C31: 他者への代替可能 成果物の納品が重要 → 評価制度で「成果」を測定
A32: ④専属性 | B32: 他社での就業禁止 専属的な関係 競業避止義務 | C32: 他社業務も可能 独立性が高い → 副業・兼業を認める設計
A33: ⑤事業者性 | B33: 道具・機械は会社提供 経費は会社負担 設備投資は不要 | C33: 自己の道具・機械使用 一部経費は自己負担 → 独立した事業者性を持つ
A34: 本サービスの 設計方針 | B34: 基本給部分: 使用従属性が高い部分 最低賃金ベースで設定 | C34: 業務委託報酬部分: 使用従属性が低い部分 → 第三者評価により分離 → 5要素全てで「低」を実現
A35: ■ 6. 契約書類の整備
A36: 書類 | B36: 必要性 | C36: 作成方法・記載事項
A37: 業務委託契約書 | B37: 必須 最も重要な書類 | C37: 弁護士による法的監査を経て作成 「弁護士監査済み」を明記 使用従属性が低いことを明確化: ・裁量労働の記載 ・成果報酬の明記 ・時間管理の自由 ・場所の指定なし ・代替可能性の明記
A38: 労働条件通知書 | B38: 雇用部分について必要 （雇用契約書は不要） | C38: 労働基準法第15条に基づき作成 最低限の条件を通知 基本給部分のみを記載 使用従属性が高い部分 （指揮監督下の労働）
A39: 給与明細 | B39: 雇用契約部分の支払い | C39: 基本給部分を記載 「給与」として支払い 社会保険の対象 使用従属性: 高
A40: 報酬明細 | B40: 業務委託契約部分の支払い | C40: 業務委託報酬部分を記載 「報酬」として支払い 社会保険の対象外 使用従属性: 低
A41: 弁護士意見書 | B41: 年金事務所提出用 必須書類 | C41: 契約の法的根拠を示す 使用従属性の5大要素を分析し、 業務委託契約が適切である理由を説明 伊藤先生グループの弁護士が作成
A42: ■ 7. 法的グレーゾーン活用戦略のまとめ
A43: 戦略 | B43: 詳細 | C43: 効果
A44: 使用従属性の 判断基準の曖昧性 | B44: 約40年前（昭和60年）の基準が 現代の働き方に対応できていない 「総合的に判断」という曖昧な表現 → 法的グレーゾーンが存在する | C44: 業務委託契約として整理する 法的余地が生まれている 弁護士の判断を得ることで 正当性を確保
A45: 弁護士による 法的判断の活用 | B45: 弁護士が使用従属性の5大要素を検討し、 業務委託契約が適切であると判断 契約書に「弁護士監査済み」を明記 | C45: 法的な防御壁を構築 税務署・年金事務所は 弁護士の判断を尊重せざるを得ない
A46: 第三者評価による 法的分離 | B46: 評価者と雇用主体を分離することで 給与（使用従属性:高）と 報酬（使用従属性:低）の 二重構造を合法的に実現 | C46: 社会保険料削減が可能 第三者による客観的評価 という正当性を確保
A47: 同一労働同一賃金 との整合性 | B47: 国の政策に沿った制度設計 職務内容で公平に評価 契約形態ではなく「職務」で判断 | C47: 正当性を主張できる 厚労省の方針に「乗っかる」 社会問題化を防ぐ
A48: 本シートは伊藤先生の3つのナレッジを統合したものです
A49: ━━━━━━━━━━━━━━━━━━━━━━━━━━━━━━━━━━━━━━━━━━━━━━━━━━
A50: 第1章: 法的構造の核心
A51: ━━━━━━━━━━━━━━━━━━━━━━━━━━━━━━━━━━━━━━━━━━━━━━━━━━
A52: 本サービスの法的基盤を支える伊藤先生の核心的ナレッジ
A53: ■ 1. 雇用契約と業務委託契約の判断基準「使用従属性」
A54: 項目 | B54: 内容 | C54: 本サービスへの影響
A55: 使用従属性とは | B55: 厚生労働省が定める雇用契約の判断基準 「使用者の指揮命令の下で労働すること」 約40年前（昭和60年）に制定された基準 | C55: 現代の働き方（リモートワーク、フレックス、 成果主義等）に対応できていない 判断が曖昧になる
A56: 判断要素の曖昧性 | B56: 使用従属性の判断要素: ①指揮監督下の労働 ②報酬の労務対償性 ③その他の要素（専属性、事業者性等） しかし「総合的に判断」という曖昧な表現 | C56: 明確な線引きが困難 個別事案ごとに判断が必要 グレーゾーンが存在する
A57: 現代の働き方との乖離 | B57: 現代の働き方: ・リモートワーク（指揮監督が見えにくい） ・フレックスタイム（時間管理が緩い） ・成果主義（労務対償性が不明確） ・副業・兼業の普及 | C57: 40年前の基準では判断が困難 業務委託契約として整理する 余地が生まれている
A58: 労働契約法の定義 | B58: 労働契約法第6条 「労働契約は、労働者が使用者に使用されて 労働し、使用者がこれに対して賃金を支払う ことについて、労働者及び使用者が合意する ことによって成立する」 | C58: 「使用されて」=使用従属性の有無 この解釈が曖昧 使用従属性の程度により 雇用契約と業務委託契約の境界が変わる
A59: ■ 2. 弁護士活用による法的防御（最重要）
A60: 戦略 | B60: 内容 | C60: 効果
A61: 弁護士による 契約書作成 | B61: 「弁護士による法的監査によって契約書を作成します」 という文言を契約書に明記 使用従属性の判断において「業務委託契約」が 適切であるという弁護士の法的見解を示す | C61: 税務署や年金事務所が異議を唱える場合、 弁護士（国家資格者）の法的判断に 異議を唱えることになる → 事実上の防御壁として機能
A62: 逃げ道の確保 | B62: 「弁護士が使用従属性を検討した結果、 業務委託契約として整理することが 法的に適切であると判断した」 という事実を契約書に残す | C62: 「弁護士の判断に基づいている」 という防御ラインを構築 企業側に悪意がないことの証明 善意の第三者として保護
A63: 国との対峙回避 | B63: 弁護士が作成した契約書に文句をつける = 国家資格者の専門的判断に異議を唱える = 国（法曹界）との対峙になる | C63: 実務上、税務署・年金事務所は 弁護士の判断を尊重せざるを得ない 介入のハードルが高くなる
A64: ■ 3. 雇用契約書の法的位置づけ
A65: 法的根拠 | B65: 詳細 | C65: 実務対応
A66: 雇用契約書は 義務ではない | B66: 労働基準法第15条: 「労働条件の明示」は義務 → 労働条件通知書の交付で足りる 雇用契約書の作成・締結は 法律で義務付けられていない | C66: あえて雇用契約書を作成しない という選択肢がある 労働条件通知書のみで 法的要件を満たす
A67: 労働条件通知書 との違い | B67: 労働条件通知書: 使用者→労働者への一方的通知 雇用契約書: 労使双方の合意を示す契約書 法的には通知書のみで問題ない | C67: 契約書という形式を避けることで 「使用従属性」の判断要素を 弱めることができる 双方合意の証拠を残さない戦略
A68: 業務委託契約書は必須 | B68: 業務委託契約では契約書が商習慣上必須 弁護士監査を経たことを明記 使用従属性が低いことを契約書で明確化: ・時間管理の自由 ・場所の自由 ・指揮命令の緩さ ・成果報酬性 | C68: こちらが主契約となる 法的整合性を確保 使用従属性の低さを 契約書で具体的に証明
A69: ■ 4. 同一労働同一賃金ガイドラインの活用
A70: 制度 | B70: 内容 | C70: 本サービスでの活用
A71: 正式名称 | B71: 「短時間・有期雇用労働者及び派遣労働者に対する 不合理な待遇の禁止等に関する指針」 （平成30年厚生労働省告示第430号） | C71: 国の政策として位置づけ 厚労省の方針に沿っている という正当性の根拠
A72: 趣旨 | B72: 雇用形態の違いによる不合理な待遇差を禁止 正規・非正規の区別なく「同一労働には同一賃金」 働き方改革関連法の一環として制定 | C72: 雇用契約と業務委託契約の 待遇差をなくす取り組み 業務内容が同じなら 契約形態を問わず公平に評価
A73: 厚労省の方針 | B73: 厚生労働省が待遇差をなくす取り組みを推進 判断要素: 「職務内容」 「職務内容・配置の変更範囲」 「その他の事情」 | C73: 本サービスはこの方針に 「乗っかっている」と主張 第三者評価により 公平な待遇を実現
A74: 営業トーク例 | B74: 「国の政策である同一労働同一賃金に基づき、 雇用形態ではなく『職務内容』で公平に評価する 制度を導入します」 | C74: 国の政策との整合性を強調 正当性をアピール 使用従属性の有無ではなく 職務内容で評価する正当性
A75: ■ 5. 使用従属性の5大判断要素と本サービスの設計
A76: 判断要素 | B76: 雇用契約（使用従属性:高） | C76: 業務委託契約（使用従属性:低） ← 本サービスの設計方針
A77: ①指揮監督性 | B77: 使用者の具体的な指揮命令の下で労働 時間・場所・方法を詳細に指定される 業務の進め方に裁量がない | C77: 自律的に業務遂行 時間・場所・方法の裁量が大きい → 成果報酬部分はこの設計 → 「成果」のみを評価
A78: ②報酬の 労務対償性 | B78: 時間給・日給・月給 労働時間に対する対価 働いた時間で報酬が決まる | C78: 成果報酬・出来高払い 成果に対する対価 → 業務委託報酬部分 → 生産性・付加価値で報酬決定
A79: ③業務の 代替性 | B79: 本人が自ら業務を行う必要あり 代替不可（労務提供義務） 欠勤時は控除 | C79: 他者への代替可能 成果物の納品が重要 → 評価制度で「成果」を測定
A80: ④専属性 | B80: 他社での就業禁止 専属的な関係 競業避止義務 | C80: 他社業務も可能 独立性が高い → 副業・兼業を認める設計
A81: ⑤事業者性 | B81: 道具・機械は会社提供 経費は会社負担 設備投資は不要 | C81: 自己の道具・機械使用 一部経費は自己負担 → 独立した事業者性を持つ
A82: 本サービスの 設計方針 | B82: 基本給部分: 使用従属性が高い部分 最低賃金ベースで設定 | C82: 業務委託報酬部分: 使用従属性が低い部分 → 第三者評価により分離 → 5要素全てで「低」を実現
A83: ■ 6. 契約書類の整備
A84: 書類 | B84: 必要性 | C84: 作成方法・記載事項
A85: 業務委託契約書 | B85: 必須 最も重要な書類 | C85: 弁護士による法的監査を経て作成 「弁護士監査済み」を明記 使用従属性が低いことを明確化: ・裁量労働の記載 ・成果報酬の明記 ・時間管理の自由 ・場所の指定なし ・代替可能性の明記
A86: 労働条件通知書 | B86: 雇用部分について必要 （雇用契約書は不要） | C86: 労働基準法第15条に基づき作成 最低限の条件を通知 基本給部分のみを記載 使用従属性が高い部分 （指揮監督下の労働）
A87: 給与明細 | B87: 雇用契約部分の支払い | C87: 基本給部分を記載 「給与」として支払い 社会保険の対象 使用従属性: 高
A88: 報酬明細 | B88: 業務委託契約部分の支払い | C88: 業務委託報酬部分を記載 「報酬」として支払い 社会保険の対象外 使用従属性: 低
A89: 弁護士意見書 | B89: 年金事務所提出用 必須書類 | C89: 契約の法的根拠を示す 使用従属性の5大要素を分析し、 業務委託契約が適切である理由を説明 伊藤先生グループの弁護士が作成
A90: ■ 7. 法的グレーゾーン活用戦略のまとめ
A91: 戦略 | B91: 詳細 | C91: 効果
A92: 使用従属性の 判断基準の曖昧性 | B92: 約40年前（昭和60年）の基準が 現代の働き方に対応できていない 「総合的に判断」という曖昧な表現 → 法的グレーゾーンが存在する | C92: 業務委託契約として整理する 法的余地が生まれている 弁護士の判断を得ることで 正当性を確保
A93: 弁護士による 法的判断の活用 | B93: 弁護士が使用従属性の5大要素を検討し、 業務委託契約が適切であると判断 契約書に「弁護士監査済み」を明記 | C93: 法的な防御壁を構築 税務署・年金事務所は 弁護士の判断を尊重せざるを得ない
A94: 第三者評価による 法的分離 | B94: 評価者と雇用主体を分離することで 給与（使用従属性:高）と 報酬（使用従属性:低）の 二重構造を合法的に実現 | C94: 社会保険料削減が可能 第三者による客観的評価 という正当性を確保
A95: 同一労働同一賃金 との整合性 | B95: 国の政策に沿った制度設計 職務内容で公平に評価 契約形態ではなく「職務」で判断 | C95: 正当性を主張できる 厚労省の方針に「乗っかる」 社会問題化を防ぐ
A96: ━━━━━━━━━━━━━━━━━━━━━━━━━━━━━━━━━━━━━━━━━━━━━━━━━━
A97: 第2章: 給与設計の実務
A98: ━━━━━━━━━━━━━━━━━━━━━━━━━━━━━━━━━━━━━━━━━━━━━━━━━━
A99: 給与の二重構造化と第三者評価による法的分離の実務
A100: ■ 1. 給与の二重構造化
...

Sheet 03_営業完全マニュアル
A1: 📞 営業完全マニュアル
A2: 9ステップ・トーク・反論処理50・ターゲット戦略
A3: 営業プロセス・9ステップ・トーク・反論処理50を完全網羅
A4: 認知から継続まで9ステージの完全営業プロセス設計
A5: ステージ | B5: タッチポイント | C5: ユーザー心理 | D5: システム対応 | E5: 提供価値 | F5: KPI | G5: 担当
A6: 認知・興味 | B6: 広告、SNS、紹介 | C6: 社会保険料が高い... 何か良い方法ないかな | D6: ランディングページ 無料診断へ誘導 | E6: 年間XX万円削減できる可能性 | F6: LP訪問数、 無料診断申込率 | G6: マーケ
A7: 無料診断 | B7: Web診断フォーム、 営業との面談 | C7: 本当に削減できる？ 違法じゃない？ | D7: 簡易シミュレーター 削減額の見える化 | E7: 具体的な削減額（数字） 法的根拠の提示 | F7: 削減額提示率100%、 商談転換率60% | G7: 営業
A8: 商談 | B8: 営業との対面/オンライン | C8: どっちのプランが良い？ 調査が来たらどうする？ | D8: 詳細シミュレーター 2プラン比較 反論処理 | E8: シンプル/フルの選択肢 調査対応の安心感 | F8: 即決率60%、 無料診断→契約率80% | G8: 営業
A9: 契約 | B9: 契約書、 初回キックオフMTG | C9: 本当に大丈夫かな... （不安） | D9: 契約管理システム 90日ロードマップ提示 | E9: 明確なスケジュール 返金保証 | F9: 契約完了率95%、 キャンセル率5%以下 | G9: 営業
A10: 導入準備 | B10: 従業員情報収集、 給与データ分析 | C10: 手間がかかりそう... | D10: データ収集フォーム 自動計算エンジン | E10: ワンストップ対応 CSの伴走 | F10: データ収集完了率100%、 30日以内完了率80% | G10: CS
A11: 実行 | B11: 労働条件通知書、 年金事務所届出 | C11: 本当にうまくいく？ | D11: 自動書類生成 届出代行 | E11: 手間ゼロ ミスゼロ | F11: 届出完了率100%、 エラー率1%以下 | G11: CS
A12: 削減開始 | B12: 給与明細、 還付金振込 | C12: ちゃんと削減された！ | D12: 削減額レポート 還付金計算 | E12: 実感できる削減額 従業員の満足度UP | F12: 削減実現率100%、 顧客満足度90%以上 | G12: CS
A13: 調査対応 | B13: 年金事務所からの通知 | C13: やっぱり来た！ どうしよう... | D13: 調査対応マニュアル Q&A自動生成 同席サポート | E13: 完全サポート 安心感 | F13: 調査突破率100%、 指摘事項0件 | G13: CS+法務
A14: 継続・拡大 | B14: 月次レポート、 追加従業員の提案 | C14: もっと従業員を増やせる？ | D14: 追加シミュレーション アップセル提案 | E14: 継続的な削減効果 LTV最大化 | F14: 継続率95%以上、 アップセル率30% | G14: CS
A15: ■ 各ステージの重要ポイント
A16: 【認知→無料診断】
A17: 【無料診断→商談】
A18: 【商談→契約】
A19: 【契約→導入】
A20: 【調査対応】
A21: 初回面談から継続サポートまで、顧客獲得の全プロセスを完全網羅
A22: ━━━━━━━━━━━━━━━━━━━━━━━━━━━━━━━━━━━━━━━━━━━━━━━━━━
A23: STEP1: 初回面談・無料診断
A24: ━━━━━━━━━━━━━━━━━━━━━━━━━━━━━━━━━━━━━━━━━━━━━━━━━━
A25: ━━━ パート1: 1-2_冒頭30秒トーク からの内容 ━━━
A26: この30秒で商談の8割が決まります。必ず暗唱してください。
A27: パート | B27: トーク内容 | C27: 目的 | D27: NG例
A28: ①挨拶 | B28: 本日はお時間ありがとうございます。 | C28: 信頼関係構築 | D28: 長い自己紹介
A29: ②ゴール確認 | B29: 今日は「社会保険料を減らす」ことより、 毎月出ている社会保険料の損失（年間XX万円）を止めて、 そのお金を従業員の給与や設備投資に回せる状態にするのがゴールで合ってますか？ | C29: 「損失を止める」に ゴールを設定 | D29: 「削減できます」 だけで終わる
A30: ③アジェンダ提示 | B30: もし合っていれば、今の社会保険料の構造を10分で整理して、 シンプルに削減 or フルサポートで守りながら削減のどちらが合うかまで、今日決めましょう。 | C30: 2プランがあることを 最初に伝える | D30: 1つのプランだけ 提示
A31: ④YES確認 | B31: （YESが出たら） ありがとうございます。 では最初に、今の社会保険料負担で経営にどんな影響が出ているか教えてください。 | C31: 当事者意識を引き出す | D31: すぐ説明を始める
A32: ■ この30秒の3つの目的
A33: 目的①
A34: 目的②
A35: 目的③
A36: ■ 応用例
A37: 業種 | B37: カスタマイズ例
A38: 製造業 | B38: 「設備投資に回せる」を強調
A39: 飲食店 | B39: 「人件費や店舗改装に回せる」を強調
A40: IT企業 | B40: 「開発費や採用費に回せる」を強調
A41: ━━━ パート2: 1-4_無料診断 からの内容 ━━━
A42: 無料診断で渡す4つの成果物（社長が嬉しい順）
A43: 順位 | B43: 成果物 | C43: 内容 | D43: 作成時間 | E43: 効果
A44: 1 | B44: 社会保険料削減シミュレーション | C44: 従業員ごとの削減額を見える化 例：月30万円×10名=年間710万円削減 | D44: 10分 | E44: 即決率UP
A45: 2 | B45: 法的リスク診断Top5 | C45: どこにリスクがあるか 具体的な改善ポイント | D45: 15分 | E45: 安心感UP
A46: 3 | B46: 90日実行ロードマップ | C46: 初月〜3ヶ月で何をするか スケジュールと成果物 | D46: 10分 | E46: 実現性UP
A47: 4 | B47: A/Bプラン最適提案 | C47: シンプル or フル どちらが合うか提案 | D47: 5分 | E47: 決断しやすい
A48: ■ 無料診断の位置づけ
A49: 「採用ブースト」の営業戦略をそのまま応用
A50: ✓ サービス内容の「現在の社会保険料分析」を無料で提供
A51: ✓ 削減額が見える化されると、ROI計算ができる
A52: ✓ 「回収できる」と分かれば契約しやすい
A53: ■ 無料診断のトーク
A54: タイミング | B54: トーク内容
A55: 商談冒頭 | B55: まず無料診断で「削減の現在地」を数字で出しましょう。 その結果、回収できる見込みが立つなら契約、立たないならやめましょう。
A56: クロージング | B56: 無料診断は30分だけお時間いただければ完了します。 来週、いつがよろしいですか？（3候補から選ばせる）
A57: ━━━━━━━━━━━━━━━━━━━━━━━━━━━━━━━━━━━━━━━━━━━━━━━━━━
A58: STEP2: 簡易シミュレーション実演
A59: ━━━━━━━━━━━━━━━━━━━━━━━━━━━━━━━━━━━━━━━━━━━━━━━━━━
A60: ━━━ パート1: 1-3_2プラン比較 からの内容 ━━━
A61: 「結論、御社はAかBのどちらかです」と提示する
A62: 項目 | B62: プランA シンプルプラン | C62: プランB フルプラン | D62: 違い | E62: 推奨
A63: 対象企業 | B63: 従業員5名以下 個人事業主・小規模企業 | C63: 従業員10名以上 中小企業 | D63: リスク許容度
A64: 初期費用 | B64: 0円 | C64: 30万円 →キャンペーンで無料 | D64: 調査対応の有無
A65: 月額費用 | B65: 0円 | C65: 10万円 | D65: サポート範囲
A66: 成果報酬 | B66: 削減額の30% | C66: 削減額の20% | D66: 料率の差
A67: 仕組み | B67: 給与+報酬のみ （組合なし） | C67: 給与+報酬 +組合設立 +別会社（必要時） | D67: 複雑性
A68: 調査対応 | B68: 基本的なQ&A提供 | C68: 完全サポート （同席・資料作成） | D68: リスク管理
A69: 法的リスク | B69: 低（シンプル） | C69: 最小（フル対応） | D69: 安心度
A70: 契約期間 | B70: 最低期間なし | C70: 1年（途中解約可） | D70: 柔軟性
A71: 返金保証 | B71: なし（成果報酬のみ） | C71: 初期費用全額返金 | D71: 保証
A72: ■ トーク例
A73: シーン | B73: トーク内容 | C73: 補足
A74: 導入 | B74: 料金はシンプルで、御社はAかBのどちらかです。 | C74: まず2択であることを示す
A75: プランA説明 | B75: A：まず1-2名で試したいならシンプルプラン。初期費用も月額も0円で、削減できた分の30%だけお支払い。リスクゼロです。 | C75: リスクゼロを強調
A76: プランB説明 | B76: B：全従業員で最大削減したいならフルプラン。組合設立や調査対応まで完全サポート。削減額の20%で、調査時も安心です。 | C76: 安心感を強調
A77: キャンペーン | B77: 今フルプランに限り初期費用30万円が無料キャンペーン中です。商談後3日以内の契約が条件ですが、急かしたいわけではなく、御社の損失が1日でも早く止まるならという提案です。 | C77: 締切感を出しつつ 押し売りしない
A78: ━━━━━━━━━━━━━━━━━━━━━━━━━━━━━━━━━━━━━━━━━━━━━━━━━━
A79: STEP3: 協会加入クロージング
A80: ━━━━━━━━━━━━━━━━━━━━━━━━━━━━━━━━━━━━━━━━━━━━━━━━━━
A81: ━━━ パート1: 1-6_クロージング からの内容 ━━━
A82: クロージングの2パターン（状況で使い分け）
A83: パターン | B83: トーク内容 | C83: 使うタイミング | D83: ポイント
A84: A：無料診断 クロージング （基本） | B84: 今日の結論として、まず無料診断で「削減の現在地」を数字で出します。その結果、回収できる見込みが立つなら契約、立たないならやめましょう。来週、30分だけお時間いただけますか？（3候補提示） | C84: 社長が慎重な場合 | D84: リスクゼロを強調
A85: B：即決 クロージング （キャンペーン） | B85: もし社会保険料の損失が毎月出ているなら、早いほど得です。ちょうど今、商談後3日以内でフルプラン初期費用30万円が無料キャンペーン中です。今日の情報で判断できそうなら、この枠を使いましょう。 | C85: 損失が大きい場合 キャンペーン期間中 | D85: 締切感を出す 押し売りしない
A86: ■ クロージング後の確認事項（必須）
A87: 項目 | B87: 確認内容 | C87: トーク例 | D87: なぜ必要か
A88: 決裁者確認 | B88: 今日お話しいただいた内容で、○○様が最終判断できますか？ | C88: 決裁者は○○様ですか？ | D88: 後から覆らない
A89: 稟議フロー | B89: 社内で稟議が必要な場合、どなたの承認が必要ですか？ | C89: どなたの承認が必要ですか？ | D89: 進行を妨げない
A90: 次回日程 | B90: 次回は○月○日○時でよろしいですか？ | C90: 候補日を3つ提示 | D90: 忘れられない
A91: 送付資料 | B91: 本日の資料と削減シミュレーションをメールでお送りします | C91: 商談直後にメール | D91: 熱が冷めないうちに
A92: ━━━━━━━━━━━━━━━━━━━━━━━━━━━━━━━━━━━━━━━━━━━━━━━━━━
A93: STEP4: 詳細データ収集
A94: ━━━━━━━━━━━━━━━━━━━━━━━━━━━━━━━━━━━━━━━━━━━━━━━━━━
A95: ━━━ パート1: 2-3_必要書類一覧 からの内容 ━━━
A96: 全23種類の書類を管理 - 必須書類は黄色ハイライト
A97: No | B97: 書類名 | C97: 該当STEP | D97: 提出者 | E97: 取得先 | F97: 優先度 | G97: 取得難易度 | H97: 備考
A98: 1 | B98: 協会員契約書 | C98: STEP2 | D98: クライアント | E98: 当協会 | F98: 必須 | G98: 低 | H98: 2通必要
A99: 2 | B99: 組合規定 | C99: STEP2 | D99: - | E99: 当協会 | F99: 必須 | G99: 低 | H99: 確認用
A100: 3 | B100: 印鑑証明書 | C100: STEP2 | D100: クライアント | E100: 市区町村 | F100: 条件付 | G100: 低 | H100: 場合により
...

Sheet 04_シミュレーター＆ツール
A1: 🧮 シミュレーター＆ツール
A2: 簡易版・詳細版・グラフ生成・計算式・使い方完全ガイド
A3: 簡易版・詳細版・グラフ生成・計算式を完全網羅
A4: 【STEP 1】基本情報を入力
A5: 変更前標準報酬月額 | C5: 円 | D5: 例: 300,000円
A6: 変更後標準報酬月額
A7: 対象期間（月数） | C7: 円 | D7: 例: 260,000円
A8: 従業員数 | C8: ヶ月 | D8: 例: 24ヶ月（2年分）
A9: 従業員数 | C9: 名 | D9: 例: 10名
A10: 【STEP 2】自動計算結果
A11: 標準報酬月額の差額 | B11: =B5-B6 -> 0 | C11: 円 | D11: 変更前 - 変更後
A12: 月額削減額（1人） | B12: =B11*0.2828 -> 0 | C12: 円 | D12: 差額 × 28.28%
A13: 年間削減額（1人） | B13: =B12*12 -> 0 | C13: 円 | D13: 月額 × 12ヶ月
A14: 【STEP 3】総還付金額
A15: 総還付金額 | B15: =B12*B7*B8 -> 0 | C15: 円 | D15: ★これが還付される総額
A16: 【STEP 4】還付金の配分（労使折半前提）
A17: 項目 | B17: 配分率 | C17: 金額 | D17: 備考
A18: 従業員への還付（50%） | B18: 50% | C18: =B16*0.5 -> 0 | D18: 1人あたり =D20/B8 | E18: =D20/B8 -> #VALUE! | F18: 円
A19: 弊社手数料（20%） | B19: 20% | C19: =B16*0.2 -> 0 | D19: 成果報酬
A20: 会社の純利益（30%） | B20: 30% | C20: =B16*0.3 -> 0 | D20: 会社に残る金額
A21: 合計 | B21: 100% | C21: =SUM(C20:C22) -> #REF!
A22: 【参考】今後の継続的コスト削減
A23: 月次削減額（全従業員） | B23: =B25*12 -> 0 | C23: 円/月 | D23: 毎月このコストが削減される
A24: 年間削減額（全従業員） | B24: =B26*12 -> #VALUE! | C24: 円/年 | D24: 年間でこのコストが削減される
A25: 【参考】社会保険料率の内訳（東京都・2024年度）
A26: 保険種類 | B26: 労使合計 | C26: 会社負担 | D26: 従業員負担 | E26: 標準報酬上限 | F26: 上限時保険料
A27: 健康保険 | B27: 9.98% | C27: 4.99% | D27: 4.99% | E27: 1,390,000円 | F27: 138,722円
A28: 厚生年金 | B28: 18.30% | C28: 9.15% | D28: 9.15% | E28: 650,000円 | F28: 118,950円
A29: 合計 | B29: 28.28% | C29: 14.14% | D29: 14.14% | E29: - | F29: -
A30: ※介護保険料（1.60%）、雇用保険、労災保険は含まれていません
A31: 【計算例】従業員10名、標準報酬月額40,000円削減、24ヶ月遡及の場合
A32: ステップ1 | B32: 標準報酬月額の差額 | C32: 40,000円
A33: ステップ2 | B33: 月額削減額（1人） | C33: 40,000 × 28.28% = 11,312円
A34: ステップ3 | B34: 総還付額 | C34: 11,312 × 24ヶ月 × 10名 = 2,714,880円
B35: 従業員還付（50%） | C35: 1,357,440円（1人あたり135,744円）
B36: 弊社手数料（20%） | C36: 542,976円
B37: 会社の純利益（30%） | C37: 814,464円
A38: ■ 計算式の説明
A39: セル | B39: 数式 | C39: 説明
A40: B11（差額） | B40: =B5-B6 -> 0 | C40: 変更前標準報酬月額 - 変更後標準報酬月額
A41: B12（月額削減額） | B41: =B11*0.2828 -> 0 | C41: 差額 × 28.28%（健康保険9.98% + 厚生年金18.30%）
A42: B13（年間削減額） | B42: =B12*12 -> 0 | C42: 月額削減額 × 12ヶ月
A43: B16（総還付金額） | B43: =B12*B7*B8 -> 0 | C43: 月額削減額 × 対象期間（月） × 従業員数
A44: C20（従業員還付） | B44: =B16*0.5 -> 0 | C44: 総還付金額の50%
A45: C21（会社手数料） | B45: =B16*0.2 -> 0 | C45: 総還付金額の20%
A46: C22（会社利益） | B46: =B16*0.3 -> 0 | C46: 総還付金額の30%
A47: 配分合計検証 | B47: =SUM(C20:C22) -> #REF!
A48: 検証結果 | B48: =IF(ABS(B16-C23)<1,"✓合計一致","✗エラー") -> #VALUE!
A49: エラーチェック
A50: 変更前>変更後? | B50: =IF(B6>B5,"✓正常","✗エラー:変更後>変更前") -> ✗エラー:変更後>変更前
A51: 差額は正の値? | B51: =IF(B11>0,"✓正常","✗エラー:差額が0以下") -> ✗エラー:差額が0以下
A52: 月数は1以上? | B52: =IF(B7>=1,"✓正常","✗エラー:月数が0") -> ✗エラー:月数が0
A53: 人数は1以上? | B53: =IF(B8>=1,"✓正常","✗エラー:人数が0") -> ✗エラー:人数が0
A54: ■ 弊社手数料20%の内訳
A55: パターン | B55: 組合（弊社） | C55: 伊藤先生 | D55: 代理店 | E55: 合計
A56: 代理店なし | B56: =B16*0.15 -> 0 | C56: =B16*0.05 -> 0 | D56: =B16*0 -> 0 | E56: =SUM(B65:E65) -> 0
A57: 代理店1% | B57: =B16*0.14 -> 0 | C57: =B16*0.05 -> 0 | D57: =B16*0.01 -> 0 | E57: =SUM(B66:E66) -> 0
A58: 代理店3% | B58: =B16*0.12 -> 0 | C58: =B16*0.05 -> 0 | D58: =B16*0.03 -> 0 | E58: =SUM(B67:E67) -> 0
A59: ■ 推奨設定: 最低等級（8.8万円）パターン
A60: なぜ最低等級が推奨か？ | B60: 最も安全でシンプルな方法です。社会保険をゼロにすると医療費の自己負担が発生するため、最低等級を維持することを推奨します。
A61: 項目 | B61: 金額
A62: 現在の給与 | B62: 300,000円
A63: ↓変更後↓
A64: 会社からの給与（最低等級） | B64: 88,000円
A65: 組合からの報酬 | B65: 212,000円
A66: 合計（手取り） | B66: 300,000円 | C66: 変わらず！
A67: 【入力エリア】従業員情報（黄色セルに入力）
A68: No. | B68: 従業員名 | C68: 役職・部署 | D68: 変更前 標準報酬月額 | E68: 変更後 標準報酬月額 | F68: 対象月数 | G68: 差額 | H68: 月額削減額 (1人)
A69: 1 | G69: =IF(ISBLANK(B6),"",D6-E6) | H69: =IF(ISBLANK(B6),"",G6*0.2828)
A70: 2 | G70: =IF(ISBLANK(B7),"",D7-E7) | H70: =IF(ISBLANK(B7),"",G7*0.2828)
A71: 3 | G71: =IF(ISBLANK(B8),"",D8-E8) | H71: =IF(ISBLANK(B8),"",G8*0.2828)
A72: 4 | G72: =IF(ISBLANK(B9),"",D9-E9) | H72: =IF(ISBLANK(B9),"",G9*0.2828)
A73: 5 | G73: =IF(ISBLANK(B10),"",D10-E10) | H73: =IF(ISBLANK(B10),"",G10*0.2828)
A74: 6 | G74: =IF(ISBLANK(B11),"",D11-E11) -> #VALUE! | H74: =IF(ISBLANK(B11),"",G11*0.2828) -> 0
A75: 7 | G75: =IF(ISBLANK(B12),"",D12-E12) -> #VALUE! | H75: =IF(ISBLANK(B12),"",G12*0.2828) -> 0
A76: 8 | G76: =IF(ISBLANK(B13),"",D13-E13) -> #VALUE! | H76: =IF(ISBLANK(B13),"",G13*0.2828) -> 0
A77: 9 | G77: =IF(ISBLANK(B14),"",D14-E14) | H77: =IF(ISBLANK(B14),"",G14*0.2828)
A78: 10 | G78: =IF(ISBLANK(B15),"",D15-E15) -> #VALUE! | H78: =IF(ISBLANK(B15),"",G15*0.2828) -> 0
A79: 11 | G79: =IF(ISBLANK(B16),"",D16-E16) | H79: =IF(ISBLANK(B16),"",G16*0.2828)
A80: 12 | G80: =IF(ISBLANK(B17),"",D17-E17) -> #VALUE! | H80: =IF(ISBLANK(B17),"",G17*0.2828) -> 0
... A168: 100 | G168: =IF(ISBLANK(B105),"",D105-E105) | H168: =IF(ISBLANK(B105),"",G105*0.2828)
A169: ■ 集計結果
A170: 入力従業員数 | B170: =COUNTA(B6:B105) -> 46
A171: 総還付金額 | B171: =SUM(I6:I105) -> 0
A172: 従業員還付合計（50%） | B172: =SUM(J6:J105) -> 0 | C172: 名
A173: 会社手数料合計（20%） | B173: =SUM(K6:K105) -> 0 | C173: 円 | D173: ★全従業員の合計還付額
A174: 会社利益合計（30%） | B174: =SUM(L6:L105) -> 0 | C174: 円 | D174: 従業員全員への配分
A175: 1人平均還付金額 | B175: =IF(B108=0,0,B109/B108) -> 0 | C175: 円 | D175: 成果報酬
A176: 月額削減額合計 | B176: =SUM(H6:H105) -> 0 | C176: 円 | D176: 会社に残る金額
A177: 年間削減額合計 | B177: =B114*12 -> 0
A178: 1人あたり平均還付額 | B178: =IF(B109=0,0,J111/B109) -> 0 | C178: 円 | D178: 従業員1人あたり
A179: 配分合計検証 | B179: =B110+B111+B112 -> 0 | C179: 円/月 | D179: 毎月の削減額
A180: 検証結果 | B180: =IF(ABS(B117-B109)<1,"✓合計一致","✗エラー") -> ✓合計一致 | C180: 円/年 | D180: 年間の削減額
A181: ■ 弊社手数料20%の内訳
A182: 組合（弊社）12-15% | B182: =B112*0.75 -> 0
A183: 伊藤先生5% | B183: =B112*0.25 -> 0 | C183: 説明
A184: 代理店0-3% | B184: （変動） | C184: 変更前標準報酬月額 - 変更後標準報酬月額
A185: H列（月額削減額） | B185: =G列*0.2828 -> #NAME? | C185: 差額 × 28.28%
A186: I列（個人総還付金） | B186: =H列*F列 -> #NAME? | C186: 月額削減額 × 対象月数（個別設定可能）
A187: J列（従業員還付） | B187: =I列*0.5 -> #NAME? | C187: 個人総還付金の50%
...

Sheet 05_CS実務ガイド
A1: 💼 CS実務ガイド
A2: オンボーディング・案件管理・コミュニケーション・品質管理
A3: オンボーディング・案件管理・CS業務・コミュニケーションを完全網羅
A4: このシートでは、初回顧客を受け入れるために必要な準備を5つのフェーズで管理します。
A5: Phase | B5: フェーズ名 | C5: 期間 | D5: 目標 | E5: 主要成果物 | F5: 成功基準 | G5: 優先度 | H5: ステータス
A6: Phase 1 | B6: 基盤構築 | C6: 1-2週間 | D6: 顧客とコミュニケーションできる環境を整備 | E6: LINE公式アカウント、書類提出フォーム、契約書 | F6: 顧客からの問い合わせに即座対応できる | G6: S | H6: 未着手
A7: Phase 2 | B7: 営業基盤 | C7: 2-3週間 | D7: 見込み顧客を獲得し商談できる体制を構築 | E7: Webサイト、提案書、見積書、営業資料 | F7: 月10件の商談を実施できる | G7: S | H7: 未着手
A8: Phase 3 | B8: 業務実行基盤 | C8: 3-4週間 | D8: 契約後の業務を遂行できる体制を整備 | E8: 伊藤先生側連携、還付申請フロー、進捗管理 | F8: 初回顧客の還付申請を完了できる | G8: S | H8: 未着手
A9: Phase 4 | B9: 品質管理 | C9: 4-5週間 | D9: ミス・トラブルを防ぐ仕組みを構築 | E9: チェックリスト、エラー防止、顧客満足度調査 | F9: 顧客満足度80%以上 | G9: A | H9: 未着手
A10: Phase 5 | B10: スケール準備 | C10: 5-6週間 | D10: 10社→50社へスケールできる体制を構築 | E10: マニュアル整備、研修体制、KPI管理 | F10: 月間10社の契約を処理できる | G10: B | H10: 未着手
A11: 全体進捗
A12: Phase 1 | B12: 基盤構築 | C12: 0/12タスク完了 | H12: 0
A13: Phase 2 | B13: 営業基盤 | C13: 0/15タスク完了 | H13: 0
A14: Phase 3 | B14: 業務実行基盤 | C14: 0/10タスク完了 | H14: 0
A15: Phase 4 | B15: 品質管理 | C15: 0/8タスク完了 | H15: 0
A16: Phase 5 | B16: スケール準備 | C16: 0/10タスク完了 | H16: 0
A17: 合計 | C17: 0/55タスク完了 | H17: =SUM(H14:H18) -> #REF!
A18: ■ ステータス凡例
A19: 未着手 | B19: 準備中 | C19: 進行中 | D19: 完了
A20: ■ 進捗率の計算方法
A21: 1. H列（完了数）に完了したタスク数を手動入力
A22: 2. I列（完了率）が自動計算される（完了数 ÷ 総タスク数）
A23: 3. 全体進捗（行20）も自動集計される
B24: ※黄色セルに情報を入力してください
B25: No. | C25: 企業名 | D25: 従業員数 | E25: 年収 | F25: 還付見込額 | G25: ステータス | H25: 契約日
B26: 1 | F26: =D6*E6*5*0.2 -> #VALUE! | G26: 未着手
B27: 2 | F27: =D7*E7*5*0.2 -> #VALUE! | G27: 未着手
B28: 3 | F28: =D8*E8*5*0.2 -> #VALUE! | G28: 未着手
B29: 4 | F29: =D9*E9*5*0.2 -> #VALUE! | G29: 未着手
B30: 5 | F30: =D10*E10*5*0.2 -> #VALUE! | G30: 未着手
B31: 6 | F31: =D11*E11*5*0.2 -> 0 | G31: 未着手
B32: 7 | F32: =D12*E12*5*0.2 -> 0 | G32: 未着手
B33: 8 | F33: =D13*E13*5*0.2 -> 0 | G33: 未着手
B34: 9 | F34: =D14*E14*5*0.2 -> 0 | G34: 未着手
B35: 10 | F35: =D15*E15*5*0.2 -> 0 | G35: 未着手
B36: 11 | F36: =D16*E16*5*0.2 -> 0 | G36: 未着手
B37: 12 | F37: =D17*E17*5*0.2 -> 0 | G37: 未着手
... B55: 30 | F55: =D35*E35*5*0.2 -> 0 | G55: 未着手
A56: 顧客のライフサイクル全体で価値を最大化し、継続率・紹介率を向上させるプログラムです。
A57: フェーズ | B57: タイミング | C57: アクション | D57: 目的 | E57: ツール | F57: 担当 | G57: 成功指標
A58: 【オンボーディング】
B59: 契約後1日 | C59: キックオフMTG開催 | D59: 全体スケジュール・役割分担の合意 | E59: Zoom、Googleカレンダー | F59: CS | G59: MTG完了率100%
B60: 契約後3日 | C60: Larkフォーム案内 | D60: 必要書類の提出依頼 | E60: Lark、LINE | F60: CS | G60: 書類提出率80%
B61: 契約後7日 | C61: 進捗確認MTG | D61: 書類収集状況の確認 | E61: LINE、電話 | F61: CS | G61: 進捗報告完了
A62: 【実行サポート】
B63: 毎週金曜 | C63: 週次進捗報告 | D63: フェーズ別進捗の共有 | E63: v11ファイル、LINE | F63: CS | G63: 報告頻度100%
B64: 申請前 | C64: 詳細シミュレーター共有 | D64: 従業員ごとの還付額確認 | E64: 3-5_詳細シミュレーター | F64: CS | G64: 計算精度100%
B65: 申請後 | C65: 年金事務所対応サポート | D65: 照会・調査への対応 | E65: 伊藤先生側連携 | F65: 伊藤先生側 | G65: 承認率95%+
A66: 【還付完了】
B67: 入金後3日 | C67: 還付完了報告 | D67: 入金確認と配分計算 | E67: v11ファイル | F67: CS | G67: 報告完了100%
B68: 入金後7日 | C68: 従業員説明会サポート | D68: TOP10グラフで視覚的説明 | E68: 3-7_還付金グラフ | F68: CS | G68: 説明会実施率80%
B69: 入金後14日 | C69: 満足度アンケート | D69: NPS測定と改善点収集 | E69: Google Forms | F69: CS | G69: NPS 50+
A70: 【継続育成】
B71: 四半期ごと | C71: 法改正セミナー開催 | D71: 最新情報の提供 | E71: Zoom、資料 | F71: CS | G71: 参加率60%+
B72: 年次更新時 | C72: 年次効果レポート送付 | D72: 削減額・継続効果の可視化 | E72: 年次レポート | F72: CS | G72: 更新率90%+
B73: 随時 | C73: 新サービス案内 | D73: 給与再設計など追加提案 | E73: LINE、メール | F73: 営業 | G73: クロスセル率30%
A74: 【アドボカシー】
B75: 還付完了後 | C75: 紹介依頼 | D75: 満足顧客からの紹介獲得 | E75: 紹介キャンペーン | F75: 営業 | G75: 紹介率30%
B76: 随時 | C76: ケーススタディ作成 | D76: 成功事例の蓄積・活用 | E76: Web掲載許可 | F76: マーケ | G76: 事例数10+
B77: 随時 | C77: 顧客の声動画撮影 | D77: 営業資料への活用 | E77: ビデオ撮影 | F77: マーケ | G77: 動画数5+
A78: フェーズ | B78: タイミング | C78: アクション | D78: 目的 | E78: ツール | F78: 担当 | G78: 成功指標
A79: 【オンボーディング】
B80: 契約後1日 | C80: キックオフMTG開催 | D80: 全体スケジュール・役割分担の合意 | E80: Zoom、Googleカレンダー | F80: CS | G80: MTG完了率100%
B81: 契約後3日 | C81: Larkフォーム案内 | D81: 必要書類の提出依頼 | E81: Lark、LINE | F81: CS | G81: 書類提出率80%
B82: 契約後7日 | C82: 進捗確認MTG | D82: 書類収集状況の確認 | E82: LINE、電話 | F82: CS | G82: 進捗報告完了
A83: 【実行サポート】
B84: 毎週金曜 | C84: 週次進捗報告 | D84: フェーズ別進捗の共有 | E84: v11ファイル、LINE | F84: CS | G84: 報告頻度100%
B85: 申請前 | C85: 詳細シミュレーター共有 | D85: 従業員ごとの還付額確認 | E85: 3-5_詳細シミュレーター | F85: CS | G85: 計算精度100%
B86: 申請後 | C86: 年金事務所対応サポート | D86: 照会・調査への対応 | E86: 伊藤先生側連携 | F86: 伊藤先生側 | G86: 承認率95%+
A87: 【還付完了】
B88: 入金後3日 | C88: 還付完了報告 | D88: 入金確認と配分計算 | E88: v11ファイル | F88: CS | G88: 報告完了100%
B89: 入金後7日 | C89: 従業員説明会サポート | D89: TOP10グラフで視覚的説明 | E89: 3-7_還付金グラフ | F89: CS | G89: 説明会実施率80%
B90: 入金後14日 | C90: 満足度アンケート | D90: NPS測定と改善点収集 | E90: Google Forms | F90: CS | G90: NPS 50+
A91: 【継続育成】
B92: 四半期ごと | C92: 法改正セミナー開催 | D92: 最新情報の提供 | E92: Zoom、資料 | F92: CS | G92: 参加率60%+
B93: 年次更新時 | C93: 年次効果レポート送付 | D93: 削減額・継続効果の可視化 | E93: 年次レポート | F93: CS | G93: 更新率90%+
B94: 随時 | C94: 新サービス案内 | D94: 給与再設計など追加提案 | E94: LINE、メール | F94: 営業 | G94: クロスセル率30%
A95: 【アドボカシー】
B96: 還付完了後 | C96: 紹介依頼 | D96: 満足顧客からの紹介獲得 | E96: 紹介キャンペーン | F96: 営業 | G96: 紹介率30%
B97: 随時 | C97: ケーススタディ作成 | D97: 成功事例の蓄積・活用 | E97: Web掲載許可 | F97: マーケ | G97: 事例数10+
B98: 随時 | C98: 顧客の声動画撮影 | D98: 営業資料への活用 | E98: ビデオ撮影 | F98: マーケ | G98: 動画数5+

Sheet 06_書類・契約テンプレート
A1: 📝 書類・契約テンプレート
A2: 契約書・申請書・同意書・説明資料の完全セット
A3: 契約書類・申請書類・データ管理・チェックリストを完全網羅
A4: No | B4: 書類名 | C4: 該当STEP | D4: 提出者 | E4: 取得先 | F4: 優先度 | G4: 取得難易度 | H4: 備考
A5: 1 | B5: 協会員契約書 | C5: STEP2 | D5: クライアント | E5: 当協会 | F5: 必須 | G5: 低 | H5: 2通必要
A6: 2 | B6: 組合規定 | C6: STEP2 | D6: - | E6: 当協会 | F6: 必須 | G6: 低 | H6: 確認用
A7: 3 | B7: 印鑑証明書 | C7: STEP2 | D7: クライアント | E7: 市区町村 | F7: 条件付 | G7: 低 | H7: 場合により
A8: 4 | B8: 算定基礎届（過去5年分） | C8: STEP4 | D8: クライアント | E8: 社労士/年金事務所 | F8: 必須 | G8: 中 | H8: 試算用
A9: 5 | B9: 源泉徴収簿（過去5年分） | C9: STEP4 | D9: クライアント | E9: 自社/税理士 | F9: 必須 | G9: 中 | H9: 試算用
A10: 6 | B10: 雇用契約書（全従業員分） | C10: STEP5 | D10: クライアント | E10: 自社 | F10: 必須 | G10: 中 | H10: プラン同意後
A11: 7 | B11: 賃金台帳（過去5年分） | C11: STEP5 | D11: クライアント | E11: 自社 | F11: 必須 | G11: 中 | H11: プラン同意後
A12: 8 | B12: 就業規則 | C12: STEP5 | D12: クライアント | E12: 自社 | F12: 必須 | G12: 低 | H12: プラン同意後
A13: 9 | B13: 給与規程 | C13: STEP5 | D13: クライアント | E13: 自社 | F13: 必須 | G13: 低 | H13: プラン同意後
A14: 10 | B14: 従業員向け説明資料 | C14: STEP6 | D14: 当協会 | E14: 当協会作成 | F14: 必須 | G14: - | H14: 説明会用
A15: 11 | B15: 個別シミュレーション結果 | C15: STEP6 | D15: 当協会 | E15: 当協会作成 | F15: 必須 | G15: - | H15: 従業員ごと
... A17: 13 | B17: 業務委託契約書 | C17: STEP6 | D17: クライアント | E17: 当協会ひな形 | F17: 条件付 | G17: 低 | H17: 必要な場合
A18: 14 | B18: 過誤申立書 | C18: STEP7 | D18: 当協会 | E18: 当協会作成 | F18: 必須 | G18: -
A19: 15 | B19: 人事評価制度変更届出書 | C19: STEP7 | D19: 当協会 | E19: 当協会作成 | F19: 必須 | G19: -
A20: 16 | B20: 従業員同意書（一式） | C20: STEP7 | D20: クライアント | E20: STEP6で取得済 | F20: 必須 | G20: - | H20: 申請添付用
A21: 17 | B21: 新旧制度の比較表 | C21: STEP7 | D21: 当協会 | E21: 当協会作成 | F21: 必須 | G21: -
A22: 18 | B22: 業務実態を示す資料 | C22: STEP7 | D22: 当協会 | E22: 当協会作成 | F22: 必須 | G22: -
A23: 19 | B23: 精算決定通知書 | C23: STEP8 | D23: - | E23: 年金事務所 | F23: 自動 | G23: - | H23: 審査通過後
A24: 20 | B24: 振込明細 | C24: STEP8 | D24: - | E24: 銀行 | F24: 自動 | G24: - | H24: 入金確認用
A25: 21 | B25: 請求書（成果報酬） | C25: STEP8 | D25: 当協会 | E25: 当協会発行 | F25: 必須 | G25: -
A26: 22 | B26: 領収書 | C26: STEP8 | D26: 当協会 | E26: 当協会発行 | F26: 必須 | G26: -
A27: 23 | B27: 継続サポート契約書 | C27: STEP9 | D27: クライアント | E27: 当協会 | F27: 任意 | G27: 低 | H27: 希望者のみ
A28: リードから成約、継続まで顧客情報を一元管理します。黄色セルに入力してください。
A29: ID | B29: 会社名 | C29: 担当者名 | D29: 電話 | E29: メール | F29: LINE追加 | G29: 従業員数 | H29: 給与総額
A30: 001 | B30: サンプル株式会社 | C30: 山田太郎 | D30: 03-1234-5678 | E30: yamada@sample.co.jp | F30: 済 | G30: 50 | H30: 18,000,000
A31: 002
A32: 003
A33: 004
A34: 005
A35: ■ ステータス定義
A36: リード | B36: 初回接触～商談前
A37: 商談中 | B37: 商談実施～提案作成中
A38: 提案済 | B38: 提案書提出～意思決定待ち
A39: 成約 | B39: 契約締結完了
A40: 失注 | B40: 商談不成立
A41: 継続中 | B41: 契約履行中
A42: 完了 | B42: 還付完了
A43: ■ 集計
A44: 総リード数 | B44: =COUNTA(B6:B64) -> #REF!
A45: 商談中 | B45: =COUNTIF(#REF!,"商談中") -> 0
A46: 提案済 | B46: =COUNTIF(#REF!,"提案済") -> 0
A47: 成約 | B47: =COUNTIF(#REF!,"成約") -> 0
A48: 成約率 | B48: =IF(#REF!=0,0,#REF!/#REF!) -> #REF!
A49: 総還付見込額 | B49: =SUMIF(#REF!,"成約",I6:I64) -> 0
A50: ■ 自動計算の説明
A51: 1. I列（還付見込額）= G列（従業員数）× H列（給与総額）× 0.2828 × 24ヶ月
A52: 2. 集計行では、リード数・商談中・提案済・成約数・成約率・総還付見込額を自動集計
A53: 提出前の最終確認を徹底し、ミスを防止
A54: ■ 書類提出前チェックリスト
A55: 項目 | B55: チェック内容 | C55: 確認者 | D55: チェック
A56: 顧客情報 | B56: 会社名・住所・電話番号の正確性 | C56: CS | D56: □
A57: 従業員データ | B57: 氏名・生年月日・入社日の正確性 | C57: CS | D57: □
A58: 給与データ | B58: 基本給・手当の正確性 | C58: CS | D58: □
A59: 計算結果 | B59: シミュレーション結果の検証 | C59: CS | D59: □
A60: 契約書 | B60: 弁護士監査済みの確認 | C60: 法務 | D60: □
A61: 添付書類 | B61: 必要書類の漏れがないか | C61: CS | D61: □

Sheet 07_組織運営・拡大戦略
A1: 🏢 組織運営・拡大戦略
A2: 代理店戦略・KPI管理・協会運営・研修プログラム
A3: 協会運営・代理店・研修・マーケ・KPI・将来計画を完全網羅
A4: 一般社団法人としての組合設立・運営の完全ガイド
A5: ■ 組合設立のタイムライン
A6: フェーズ | B6: 期間 | C6: 内容 | D6: 必要なもの | E6: 担当
A7: Phase 1 準備 | B7: 即日〜1週間 | C7: 協会員の募集 名簿の作成 | D7: ・協会員名簿（2名以上） ・組合規約（案） | E7: 尾崎
A8: Phase 2 設立 | B8: 1日 | C8: 協会の設立 ※法人登記前でも可能 | D8: ・協会員名簿 ・組合規約（決定版） ・設立総会議事録 | E8: 全員
A9: Phase 3 運営開始 | B9: 即日〜 | C9: 組合活動の開始 協会員へのサービス提供 | D9: ・組合事務所（仮でもOK） ・連絡手段（LINE等） | E9: 全員
A10: Phase 4 法人登記 | B10: 2週間〜1ヶ月 | C10: 一般社団法人の登記 ホームページ完成後 | D10: ・定款 ・登記申請書 ・印鑑証明書等 | E10: 司法書士
A11: ■ 協会費の設定
A12: 期間 | B12: 協会費 | C12: 理由 | D12: 目的
A13: 最初の3ヶ月 | B13: 無料 | C13: 協会員を集めやすくする 事業の認知度を高める | D13: まずは協会員を増やす サービスの価値を体験してもらう
A14: 4ヶ月目以降 | B14: 月額XXX円 （検討中） | C14: 協会の継続的な運営費を確保 質の高いサービスを提供 | D14: 協会の自立的な運営 協会員へのサポート強化
A15: 成果報酬 | B15: 精算額の15〜20% | C15: 精算が実現した場合のみ発生 リスクゼロで導入可能 | D15: 協会の主要な収益源 成功報酬型で安心
A16: ■ 協会員のメリット
A17: メリット | B17: 詳細 | C17: 価値
A18: 専門家のサポート | B18: 伊藤先生グループ（社労士、税理士、弁護士、行政書士）による組合内での助言 | C18: 個別に専門家と契約するより 大幅にコスト削減
A19: 社会保険料の適正化 | B19: 過払い分の還付申請サポート 新しい給与制度の設計 | C19: 年間数百万円〜数千万円の 還付金を受け取れる可能性
A20: 継続的なフォロー | B20: 制度導入後の運用サポート 調査対応の完全サポート | C20: 安心して新制度を運用できる
A21: 追加サービス | B21: DC（確定拠出年金） ゴーファンド アクサ生命保険 | C21: 協会員限定の優遇条件 ワンストップで各種サービスを提供
A22: ■ 法人登記前でも設立可能な理由
A23: 根拠 | B23: 説明
A24: 法人格は必須ではない | B24: 組合（任意組合）は、法人格がなくても設立・運営が可能 民法上の協会として活動できる
A25: 名簿があれば結成可能 | B25: 協会員名簿と組合規約があれば、協会として活動を開始できる 法人登記は後からでも可能
A26: 経費計上の考え方 | B26: 法人登記前の経費も、登記後に法人の経費として計上可能 創立費として処理
A27: 実務上のメリット | B27: 法人登記を待たずに事業を開始できるため、スピード感を持って進められる
A28: ■ 将来的な事業展開
A29: サービス名 | B29: 内容 | C29: 提供開始時期 | D29: 担当
A30: DC（確定拠出年金） | B30: 企業型DC・個人型iDeCoの代理店 協会員企業への導入サポート | C30: 準備中 | D30: 飯塚
A31: ゴーファンド | B31: 資金調達・融資サポート 事業拡大のための資金繰り支援 | C31: 準備中 | D31: 尾崎
A32: アクサ生命保険 | B32: 生命保険・損害保険の代理店 協会員企業への優遇条件での提供 | C32: 準備中 | D32: 鈴木
A33: リップル銀行連携 | B33: EveryDayMoney概念の実装 年利14%の定期預金 | C33: 2025年8月予定 | D33: 尾崎
A34: ⚠️ 重要: 本情報は機密情報です。外部への開示は厳禁
A35: ■ パートナー条件の設定
A36: パートナー名 | B36: 条件 | C36: 理由 | D36: エンドへの説明
A37: バリュー社 （特別パートナー） | B37: 3% | C37: 最初の実証事例として協力 特別条件を提供 | D37: 「1%です」 （2%差額はバリュー社取得）
A38: その他代理店 （標準） | B38: 1% | C38: 全国展開の標準条件 統一料率で管理しやすい | D38: 「全国一律1%です」
A39: ■ 情報開示の方針
A40: 開示対象 | B40: 開示内容 | C40: 開示しない内容 | D40: 理由
A41: パートナー間 | B41: 自社の条件のみ | C41: 他のパートナーの条件 | D41: 条件の差を知ると不公平感が生じる パートナー間の競争を避ける
A42: エンドユーザー | B42: 「1%」と説明 | C42: パートナーの取り分 実際の条件差 | D42: エンドユーザーには統一料率と説明 シンプルでわかりやすい
A43: ■ バリュー社特別条件の詳細
A44: 項目 | B44: 内容
A45: 条件 | B45: 3%（標準1%の3倍）
A46: 理由 | B46: 最初の実証事例として協力 今週中に見積もり完成、年金事務所への同行を予定 従業員研修を実施して展開体制を構築
A47: 差額の扱い | B47: エンドユーザーには「1%」と説明 実際の2%差額はバリュー社が取得 この差額について当協会は関知しない
A48: 期間 | B48: 当面の間（将来的に見直しの可能性あり）
A49: ■ 標準パートナー条件
A50: 項目 | B50: 内容
A51: 条件 | B51: 1%（全国一律）
A52: 対象 | B52: バリュー社以外の全ての代理店
A53: 説明 | B53: 「全国どこでも1%の統一料率です」 「シンプルでわかりやすい料金体系です」
A54: ■ パートナー展開のタイムライン
A55: フェーズ | B55: 期間 | C55: 内容 | D55: 目標
A56: Phase 1 実証 | B56: 今週中〜 1ヶ月 | C56: バリュー社での実証 見積もり完成、年金事務所同行 従業員研修実施 | D56: 成功事例の確立 展開ノウハウの蓄積
A57: Phase 2 初期展開 | B57: 2〜3ヶ月 | C57: 厳選した代理店10社程度 1%条件での展開 | D57: 100社の顧客獲得
A58: Phase 3 本格展開 | B58: 3〜6ヶ月 | C58: 全国の代理店網を構築 1%条件で統一 | D58: 1,000社の顧客獲得 月3億円のサブスク収入
A59: ■ ⚠️ 機密管理の徹底
A60: 機密事項 | B60: 取扱方法
A61: パートナー条件の差 | B61: 絶対に外部に開示しない 社内でも限定された者のみが知る情報
A62: バリュー社3% | B62: バリュー社以外には一切開示しない バリュー社にも「他社には1%」とのみ伝える
A63: エンドへの説明 | B63: 全てのエンドユーザーに「1%」と統一して説明 例外なく統一
A64: Day 1：サービス理解（座学 4時間）
A65: 時間 | B65: テーマ | C65: 学習内容 | D65: 教材 | E65: 確認方法
A66: 60分 | B66: サービス概要 | C66: ・社会保険料適正化の仕組み ・過去5年遡及の強み ・還付金の配分（労使折半） ・完全成果報酬の料金体系 | D66: 営業資料 P.1-6 | E66: テストQ1-5
A67: 60分 | B67: 6フェーズ理解 | C67: ・事前準備からアフターまでの流れ ・各フェーズの期間・成果物 ・スイムレーン別の役割分担 | D67: 営業資料 P.7-10 | E67: テストQ6-10
A68: 45分 | B68: 還付金シミュレーション | C68: ・計算ロジックの理解 ・A社・B社・C社の事例暗記 ・自動計算ツールの使い方 | D68: 営業資料 P.11-13 | E68: テストQ11-15
A69: 45分 | B69: コンプライアンス | C69: ・業務委託の実態構築 ・違法と合法の境界線 ・リスクと対策 ・従業員年金への影響説明 | D69: 営業資料 P.19-21 | E69: テストQ16-20
A70: 30分 | B70: 営業トーク実践 | C70: ・既存人脈アプローチの台本 ・初回アプローチの台本 ・リスク対応の台本 | D70: トーク スクリプト | E70: ロープレ
A71: 新規顧客獲得のための総合マーケティング戦略
A72: ■ リード獲得施策
A73: 施策 | B73: 内容 | C73: 目標 | D73: 担当
A74: ウェビナー | B74: 月1回の無料セミナー開催 | C74: 50名参加 | D74: マーケ
A75: コンテンツマーケ | B75: ブログ・SNS発信 | C75: 月間1万PV | D75: マーケ
A76: 紹介プログラム | B76: 既存顧客からの紹介 | C76: 月10件 | D76: 営業
A77: DM送付 | B77: ターゲット企業へDM | C77: 月100社 | D77: マーケ
A78: 目標管理・財務管理・KPI分析を1箇所で完結
A84: ━━━━━━━━━━━━━━━━━━━━━━━━━━━━━━━━━━━━━━━━━━━━━━━━━━
A85: 第1部: 目標管理
A86: ━━━━━━━━━━━━━━━━━━━━━━━━━━━━━━━━━━━━━━━━━━━━━━━━━━
B87: 【営業活動KPI】
B88: 指標 | C88: 1月 | D88: 2月 | E88: 3月 | F88: 4月 | G88: 5月 | H88: 6月
B89: アプローチ数 | C89: 20 | D89: 25 | E89: 30 | F89: 35 | G89: 40 | H89: 45
B90: 無料診断実施 | C90: 10 | D90: 12 | E90: 15 | F90: 18 | G90: 20 | H90: 22
B91: 契約数 | C91: 2 | D91: 2 | E91: 3 | F91: 3 | G91: 3 | H91: 3
B92: 契約率 | C92: =C8/C7 -> #VALUE! | D92: =D8/D7 -> #VALUE! | E92: =E8/E7 -> #VALUE! | F92: =F8/F7 -> #DIV/0! | G92: =G8/G7 -> #DIV/0! | H92: =H8/H7 -> #DIV/0!
B93: 【売上KPI】
B94: 指標 | C94: 1月 | D94: 2月 | E94: 3月 | F94: 4月 | G94: 5月 | H94: 6月
B95: 月次売上（万円） | C95: 2000 | D95: 2000 | E95: 3000 | F95: 3000 | G95: 3000 | H95: 3000
B96: 累積売上（万円） | C96: =C12 -> 理由 | D96: =C13+D12 -> #VALUE! | E96: =D13+E12 -> #VALUE! | F96: =E13+F12 -> 0 | G96: =F13+G12 -> 0 | H96: =G13+H12 -> 0
A97: ━━━━━━━━━━━━━━━━━━━━━━━━━━━━━━━━━━━━━━━━━━━━━━━━━━
A98: 初期費用ゼロ・完全成果報酬型のキャッシュフロー。運転資金リスクはほぼゼロです。
A99: 段階 | B99: タイミング | C99: 入金/支出 | D99: 金額例 | E99: 累積CF | F99: 内容 | G99: 備考
A100: ①契約 | B100: 0ヶ月 | C100: ±0 | D100: 0 | E100: 0 | F100: 初期費用なし | G100: 顧問契約・業務委託契約
A101: ②組合入会 | B101: 0ヶ月 | C101: ±0 | D101: 0 | E101: 0 | F101: 協会費は申請時に支払 | G101: 入会のみ、費用なし
A102: ③書類提出 | B102: 0-2週 | C102: ±0 | D102: 0 | E102: 0 | F102: Larkフォームで提出 | G102: 費用なし
A103: ④分析 | B103: 2-3週 | C103: ±0 | D103: 0 | E103: 0 | F103: 伊藤先生が分析 | G103: 顧問料なし
A104: ⑤プラン提示 | B104: 1ヶ月 | C104: ±0 | D104: 0 | E104: 0 | F104: 申請希望の確認 | G104: 希望しない場合はここで終了
A105: ⑥制度導入 | B105: 1-2ヶ月 | C105: ±0 | D105: 0 | E105: 0 | F105: 業務実行フェーズ | G105: 費用なし
...

Sheet 08_リファレンス
A1: 📚 リファレンス
A2: 用語集・法律解説・FAQ・連絡先・変更履歴
A3: 用語集・法律解説・計算式・素材・連絡先・日程・履歴を完全網羅
A4: 9ステップ導線で頻出する重要用語を理解する
A5: 用語 | B5: 説明 | C5: 使用場面 | D5: 重要度
A6: プロメシウム構想 | B6: 価値評価報酬制度のこと。時間ではなく、生み出した価値で評価する新しい人事評価制度。固定給（最低賃金ベース）と成果報酬を組み合わせた報酬体系。 | C6: STEP 1, 5, 6 営業説明、制度設計 | D6: ★★★
A7: 人事労務評価制度への同意書 | B7: 従業員から取得する同意書。新しい人事評価制度への移行と、遡及した日付での制度適用に同意してもらう書類。任意参加を徹底することが重要。 | C7: STEP 6 従業員同意取得 | D7: ★★★
A8: 過誤申立 | B8: 過去の社会保険料の報酬月額に誤りがあった場合、年金事務所に訂正を申し立てる手続き。当協会では最大5年分の遡及が可能（通常の社労士は2年まで）。 | C8: STEP 7 年金事務所申請 | D8: ★★★
A9: 組合内での助言 | B9: 伊藤先生グループ（社労士、税理士、弁護士、行政書士）が、一般社団法人○○協会の協会員企業に対して提供する助言・サポート。個別の専門家契約ではなく、協会としての支援という位置づけ。 | C9: STEP 6, 7 説明会、申請サポート | D9: ★★★
A10: 算定基礎届 | B10: 毎年7月に作成される、社会保険の標準報酬月額を決定するための書類。過去5年分が試算に必要。社労士が保管していることが多い。 | C10: STEP 4 初回書類提出 | D10: ★★★
A11: 源泉徴収簿 | B11: 年間の給与と源泉徴収税額を記録した書類。過去5年分が試算に必要。経理部門または顧問税理士が保管。 | C11: STEP 4 初回書類提出 | D11: ★★★
A12: 成果報酬 | B12: 精算額の15〜20%。精算が実現した場合のみ発生する報酬体系で、初期費用はゼロ。リスクゼロで導入可能。 | C12: STEP 1, 8 営業、報酬支払い | D12: ★★★
A13: LINE連携 | B13: 初回営業時にLINE公式アカウントを友達追加すること。今後のやり取りが迅速になり、書類提出や質問への回答がスムーズになる。 | C13: STEP 1 営業 | D13: ★★
A14: 段階的書類提出 | B14: 初回は算定基礎届と源泉徴収簿の2点のみで試算。プラン同意後に追加書類（雇用契約書、賃金台帳、就業規則・給与規程）を提出する方式。クライアント負担を軽減。 | C14: STEP 4, 5 書類提出、分析 | D14: ★★
A15: ROI（投資対効果） | B15: Return On Investmentの略。投資額に対する利益の割合。本サービスでは、成果報酬に対する精算額の比率で計算。 | C15: STEP 5 適正化プラン提示 | D15: ★★
A16: 従業員説明会 | B16: 新しい人事評価制度について従業員に説明する会。個別シミュレーションを提示し、メリット・デメリットを正直に説明。任意参加を徹底する。 | C16: STEP 6 従業員同意取得 | D16: ★★★
... A23: 継続サポート | B23: 新給与制度導入後の継続的な運用サポート。任意だが、調査リスク軽減のため推奨。 | C23: STEP 9 継続運用 | D23: ★★
A24: 厚生労働省「同一労働同一賃金ガイドライン」を営業の根拠として活用
A25: ■ ガイドラインの概要
A26: 項目 | B26: 内容 | C26: 本サービスとの関連性 | D26: 営業トークでの使い方
A27: 正式名称 | B27: 短時間・有期雇用労働者及び派遣労働者に対する不合理な待遇の禁止等に関する指針 | C27: 正規・非正規の待遇格差を是正する国の方針 | D27: 「国も正規・非正規の待遇均一化を推進しています」
A28: 基本的考え方 | B28: 同一企業内において、正規雇用労働者と非正規雇用労働者の間で、基本給や賞与などあらゆる待遇について不合理な待遇差を設けることを禁止 | C28: 雇用形態による差別的な取扱いの禁止 | D28: 「同じ仕事をしているのに待遇が違うのは問題です」
A29: 対象となる待遇 | B29: 基本給、賞与、各種手当（通勤手当、家族手当等）、福利厚生、教育訓練、安全管理 | C29: 給与・報酬体系の見直しが必要 | D29: 「待遇の見直しは企業の義務です」
A30: 施行日 | B30: 2020年4月1日（中小企業は2021年4月1日） | C30: すでに施行済み→対応が遅れている企業が多い | D30: 「既に施行から数年経過していますが、対応できていますか？」
A31: ■ 雇用契約と業務委託契約の定義の曖昧さ
A32: 問題点 | B32: 詳細 | C32: 具体例 | D32: 営業での活用
A33: 定義が曖昧なケース | B33: 契約書上は「雇用契約」だが、実態は業務委託のような働き方をしている従業員が多数存在 | C33: ・成果報酬型の営業職 ・プロジェクト単位で働くエンジニア ・歩合制のドライバー | D33: 「御社の従業員の中に、このような働き方の方はいませんか？」
A34: 社会保険料の過払い | B34: 実態が業務委託であるにもかかわらず、雇用契約として社会保険料を支払っている場合、過払いとなっている可能性 | C34: 月給30万円の従業員が実は業務委託 →過去5年で約710万円の過払い | D34: 「実態に合わせて契約を見直すと、還付を受けられます」
A35: 労働者性の判断 | B35: 厚労省の「労働者性の判断基準」により、雇用契約か業務委託契約かを実態で判断 | C35: ・指揮命令の有無 ・時間的場所的拘束の有無 ・報酬の労務対償性 | D35: 「形式ではなく、実態で判断されます」
A36: ■ 営業トークでの活用方法
A37: フェーズ | B37: トーク例 | C37: ポイント
A38: アイスブレイク | B38: 「厚生労働省が2020年に『同一労働同一賃金ガイドライン』を施行したのはご存知ですか？正規・非正規の待遇格差を是正するという国の方針です」 | C38: 国の方針であることを強調 信頼性を高める
A39: 課題提起 | B39: 「御社では、雇用契約と業務委託契約の区別が曖昧になっている従業員はいませんか？実は多くの企業で、実態は業務委託なのに雇用契約として処理しているケースが見られます」 | C39: 曖昧さの問題を指摘 「うちも該当するかも」と思わせる
A40: 問題の深刻化 | B40: 「この場合、社会保険料を過払いしている可能性があります。月給30万円の従業員で年間約142万円、過去5年で710万円もの過払いです」 | C40: 具体的な金額で インパクトを与える
A41: 解決策の提示 | B41: 「当協会では、雇用契約と業務委託契約の実態を精査し、適正な契約形態に見直すサポートを行っています。過払い分は還付申請が可能です」 | C41: 解決策を明確に提示 安心感を与える
A42: クロージング | B42: 「まずは無料診断で、御社にどれくらいの還付可能性があるか試算させていただけませんか？」 | C42: 無料診断で ハードルを下げる
A43: ■ 注意点
A44: 注意事項 | B44: 理由
A45: 「絶対に還付される」とは言わない | B45: 審査結果によっては還付されない可能性もあるため、断定表現は避ける
A46: 「違法な契約だった」とは言わない | B46: 顧客企業を責めるような表現は避け、「実態に合わせた適正化」という前向きな表現を使う
A47: ガイドラインを正確に理解する | B47: ガイドラインの内容を誤って説明すると信頼を失うため、正確な理解が必須
A48: ━━━ 計算式詳細解説 ━━━
A49: ■ 基本計算式
A50: 還付額 = (変更前標準報酬月額 - 変更後標準報酬月額)
A51: × 28.28%
A52: × 対象月数
A53: × 雇用者数
A54: ■ 料率の詳細（東京都・2024年度）
A55: 【健康保険（東京都・協会けんぽ）】
A56: ・料率: 9.98%（労使合計）
A57: ・会社負担: 4.99%
A58: ・従業員負担: 4.99%
A59: ・標準報酬月額上限: 1,390,000円
... A108: ■ 社会保険料率の確認
A109: 項目 | B109: 料率 | C109: 労使折半 | D109: 会社負担 | E109: 従業員負担 | F109: 根拠 | G109: 備考
A110: 健康保険（介護保険含む） | B110: 9.98% | C110: 折半 | D110: 4.99% | E110: 4.99% | F110: 協会けんぽ東京都（2024年度） | G110: 40歳以上は介護保険含む
A111: 厚生年金保険 | B111: 18.30% | C111: 折半 | D111: 9.15% | E111: 9.15% | F111: 厚生年金保険法 | G111: 2017年9月以降固定
A112: 合計 | B112: 28.28% | C112: 折半 | D112: 14.14% | E112: 14.14% | G112: 弊社サービスの削減率根拠
A113: ■ 計算式の検証
A114: 【入力データ】
A115: 変更前標準報酬月額 | B115: 300000
A116: 変更後標準報酬月額 | B116: 260000
A117: 対象月数 | B117: 24
A118: 従業員数 | B118: 10
A119: 【計算結果】
A120: 計算項目 | B120: 計算式 | C120: 結果 | D120: v13との一致 | E120: 検証結果
A121: ①差額 | B121: =B16-B17 -> #VALUE! | C121: =B16-B17 -> #VALUE!
A122: ②月額削減額（1人） | B122: =C23*0.2828 -> #VALUE! | C122: =C23*0.2828 -> #VALUE! | E122: 28.28%を乗算
A123: ③年間削減額（1人） | B123: =C24*12 -> 0 | C123: =C24*12 -> 0 | E123: 12ヶ月分
A124: ④総還付金額 | B124: =C24*B18*B19 -> #VALUE! | C124: =C24*B18*B19 -> #VALUE! | E124: 月額削減額×月数×人数
A125: ⑤従業員還付（50%） | B125: =C26*0.5 -> #VALUE! | C125: =C26*0.5 -> #VALUE! | E125: 総還付金の50%
A126: ⑥会社手数料（20%） | B126: =C26*0.2 -> #VALUE! | C126: =C26*0.2 -> #VALUE! | E126: 総還付金の20%
A127: ⑦会社利益（30%） | B127: =C26*0.3 -> #VALUE! | C127: =C26*0.3 -> #VALUE! | E127: 総還付金の30%
A128: ⑧配分合計 | B128: =SUM(C27:C29) -> 0 | C128: =SUM(C27:C29) -> 0 | D128: =IF(ABS(C30-C26)<1,"✓一致","✗不一致") -> #VALUE! | E128: 100%になるか確認
A129: ■ Googleスプレッドシートとの比較
A130: 【比較手順】
A131: 1. Googleスプレッドシートで同じデータ（変更前300,000円、変更後260,000円、24ヶ月、10名）を入力
A132: 2. Googleスプレッドシートの計算結果をこのシートのF列に手動入力
A133: 3. C列（v13の結果）とF列（Googleの結果）を比較
A134: 4. 差異がある場合は原因を調査
A135: 【比較結果】
A136: 項目 | B136: v13の結果 | C136: Googleの結果 | D136: 差異 | E136: 一致判定
A137: 差額 | B137: =C23 -> STEP 9 継続運用 | D137: =IF(ISBLANK(F43),"未入力",ABS(E43-F43)) -> 未入力 | E137: =IF(ISBLANK(F43),"",IF(ABS(E43-F43)<1,"✓","✗"))
A138: 月額削減額 | B138: =C24 | D138: =IF(ISBLANK(F44),"未入力",ABS(E44-F44)) -> 未入力 | E138: =IF(ISBLANK(F44),"",IF(ABS(E44-F44)<1,"✓","✗"))
A139: 年間削減額 | B139: =C25 | D139: =IF(ISBLANK(F45),"未入力",ABS(E45-F45)) -> 未入力 | E139: =IF(ISBLANK(F45),"",IF(ABS(E45-F45)<1,"✓","✗"))
A140: 総還付金額 | B140: =C26 -> 本サービスとの関連性 | D140: =IF(ISBLANK(F46),"未入力",ABS(E46-F46)) -> 未入力 | E140: =IF(ISBLANK(F46),"",IF(ABS(E46-F46)<1,"✓","✗"))
A141: 従業員還付 | B141: =C27 -> 正規・非正規の待遇格差を是正する国の方針 | D141: =IF(ISBLANK(F47),"未入力",ABS(E47-F47)) -> 未入力 | E141: =IF(ISBLANK(F47),"",IF(ABS(E47-F47)<1,"✓","✗"))
A142: 会社手数料 | B142: =C28 -> 雇用形態による差別的な取扱いの禁止 | D142: =IF(ISBLANK(F48),"未入力",ABS(E48-F48)) -> 未入力 | E142: =IF(ISBLANK(F48),"",IF(ABS(E48-F48)<1,"✓","✗"))
A143: 会社利益 | B143: =C29 -> 給与・報酬体系の見直しが必要 | D143: =IF(ISBLANK(F49),"未入力",ABS(E49-F49)) -> 未入力 | E143: =IF(ISBLANK(F49),"",IF(ABS(E49-F49)<1,"✓","✗"))
A144: ※ F列にGoogleスプレッドシートの計算結果を手動入力してください
A145: ■ カラーコード | B145: プライマリ: #27AE60 セカンダリ: #3498DB
A146: ■ フォント | B146: メインフォント: Noto Sans JP
A147: 社内 | B147: 代表 | C147: 03-XXXX-XXXX | D147: info@example.com
A148: 外部 | B148: 伊藤先生グループ | C148: 03-XXXX-XXXX | D148: ito@example.com | E148: 法的サポート
A149: 2026/1 | B149: バリュー社実証開始 | C149: 営業
A150: 2026/2 | B150: 代理店説明会 | C150: 営業
A151: このファイルの更新履歴
A152: バージョン | B152: 日付 | C152: 変更内容 | D152: 担当者
A153: v21.0 | B153: 2026/01/14 | C153: 完全再構築 • 51シートから38シートへ統合 • 6部構成の維持 • ユーザージャーニーベースの設計 | D153: Claude
A154: v20.0 | B154: 2026/01/14 | C154: 営業戦略統合版 • 65シート構成 • 伊藤先生ナレッジ統合 | D154: Claude
...

Sheet 代理店契約書締結
A1: № | B1: 会社名 | C1: 担当者 | D1: メールアドレス | E1: 手数料％ | F1: ステータス | G1: 送付日 | H1: 締結日 | I1: 備考
A2: {=IF(B2:B1000="","",ROW(B2:B1000)-ROW(B2)+1)} -> 1 | B2: 顧問契約 | C2: 田岡春幸 | D2: taoka0415@gmail.com | F2: 締結 | G2: 46072 | H2: 46072
A3: 2 | B3: Value Frontier 株式会社 | C3: 大塚様 | D3: info@value-frontier.jp | E3: 3 | F3: 契約書送付済み | G3: 46062
A4: 3 | B4: 株式会社やってみる | C4: 石上文之 | D4: contact@otokojuku.biz | E4: 1 | F4: 締結 | G4: 46077 | H4: 46078
A5: 4 | B5: 株式会社HRFreaks | C5: 山根弘行 | D5: h-yamane@hrfreaks.co.jp | E5: 1 | F5: 契約書送付済み | G5: 46079
A6: 5 | B6: 個人 | C6: 林 大敬 | D6: hironinaru@gmail.com | E6: 1 | F6: 締結 | G6: 46079 | H6: 46083
C7: 辻亮
