Workbook

Sheet 契約状況
A1: 項目 | B1: 内容
A2: 番号
A3: LINE名
A4: 紹介URL
A5: 担当AS
A6: コンサル担当者
A7: 会社名 | B7: サンプル株式会社
A8: 代表者名
A9: 主担当者名
A10: 顧客メール | B10: taro@example.com
A11: 顧客電話 | B11: 090-0000-0000
A12: 契約日 | B12: 46093
A13: 契約プラン
A14: 契約金額 | B14: 5500000
A15: サービス種別 | B15: 卸+コンサル+BPO
A16: 案件ステータス | B16: 進行中
A17: セキュリティクラウド販売有無 | B17: あり
A18: 助成金採択コンサル有無 | B18: あり
A19: BPO申請支援有無 | B19: あり
A20: コンサルプラン | B20: プロフェッショナル
A21: 成功報酬金額 | B21: 150000
A22: 開始日 | B22: 46082
A23: 終了予定日 | B23: 46265
A24: 請求状況
A25: 入金状況 | B25: 未請求
A26: 売上計上日 | B26: 未入金
A27: 粗利
A28: 備考

Sheet コンサル状況
A1: ベンダー名 | B1: 対応日 | C1: 対応手段 | D1: ベンダー様 課題/ご相談内容 | E1: ヒアリング内容 | F1: 回答内容 | G1: 提案内容 | H1: ベンダー様 次回アクション | I1: 次回期限 | J1: ベンダー様 タスク内容 | K1: タスク期限 | L1: 優先度 | M1: タスク完了 | N1: 申請サポート タスク内容 | O1: タスク期限 | P1: 優先度 | Q1: タスク完了 | R1: 添付資料URL | S1: 録画URL | T1: スクショURL | U1: 備考
B2: 46093 | C2: LINE | D2: 初期運用の不安 | E2: 現状の販売体制/件数 | F2: 5分動画リンク送付 | G2: 運用フロー整備の提案 メモ 提案ノーションURLを添付 毎回ノーションで専用ページ作成 子ページを増やして詳細の内容を増やしていく | H2: 次回は申請書類の提出物チェック | I2: 46096 | K2: 46095 | L2: 高 | M2: 未完了 | N2: 提出書類一覧の作成 | O2: 46095 | P2: 高 | Q2: 未完了 | R2: https://drive.example.com/docs | S2: https://drive.example.com/record | T2: https://drive.example.com/ss
A3: ここはベンダー側は非表示 | U3: ベンダー側のみが記載可能

Sheet 顧客情報_参考用（〜概要案内）
A1: 申請者名 | B1: 紹介者 | C1: 営業担当者 | D1: 区分 | E1: ステータス | F1: 見込み度合い | G1: 詳細メモ | H1: 次のアクション | I1: 次の連絡日 | J1: 概要案内日 | K1: MTG録画 | L1: 案内担当者 | M1: 電話番号 | N1: 事業体 | O1: 業種 | P1: システム | Q1: 貸付 | R1: 売上帯 | S1: 重要タグ | T1: 貸付なし インボイスあり | U1: 貸付なし インボイスなし/現金 | V1: 貸付あり インボイスあり | W1: 貸付あり インボイスなし/現金 | X1: 紹介者報酬% | Y1: 代理店①番号 | Z1: 代理店①報酬% | AA1: 報酬合計 | AB1: ダブルチェック者 | AC1: おかわり判定 | AD1: 賃上げ可否 | AE1: 過去導入 商品名 | AF1: 検討後失注日 離脱日 | AG1: 代理店契約書URL | AH1: 書類取得開始日 | AI1: 書類提出日 | AJ1: 事業者名 | AK1: 書類① | AL1: 書類② | AM1: 書類③ | AN1: 書類④ | AO1: 書類⑤ （賃金台帳） | AP1: IT戦略ナビwith PDF | AQ1: 従業員有無 | AR1: gBizID TOPスクショ | AS1: gBizID アドレス | AT1: 自己宣言ID(11桁) | AU1: 反社チェック | AV1: 開業/ 設立年月日 | AW1: 資本金 | AX1: 決算月 | AY1: 売上高 | AZ1: 粗利益 | BA1: 営業利益 | BB1: 経常利益 | BC1: 減価償却費 | BD1: 人件費 | BE1: 資本金または準備金 | BF1: 役員報酬総額 | BG1: 給与支払い総額 （前年度実績値） | BH1: ※参考程度 計画数値 (1年度目) | BI1: ※参考程度 計画数値 (2年度目) | BJ1: ※参考程度 計画数値 (3年度目) | BK1: 加点①対象 | BL1: 加点①資料 | BM1: 加点②対象 | BN1: 加点②資料 | BO1: 事業場内最低賃金 | BP1: 申請システム | BQ1: 事業内容文章 （申請文章） | BR1: 3.ビジネスプロセスの改善に向けて ∟その他（フリー記載） | BS1: HP | BT1: 事業内容 | BU1: 挑戦課題のタイトル | BV1: 挑戦課題の解決の目標 | BW1: 成長マッチング 事業内容 | BX1: 情報入力者 | BY1: 情報入力 確認 | BZ1: 事業内容文章 （最終） | CA1: 業種コード | CB1: 事業所数 | CC1: 正規雇用 | CD1: 契約社員 | CE1: パートアルバイト | CF1: 派遣社員 | CG1: その他 | CH1: 1段目 | CI1: 2段目 | CJ1: 3段目 | CK1: 4段目 | CL1: 5段目 | CM1: 6段目 | CN1: 7段目 | CO1: 8段目 | CP1: 9段目 | CQ1: 10段目
D2: クライアント | E2: 申請完了 | G2: 申請者名： [記録] 法人or個人： 事業内容： 売上： システム：セキュリティクラウド 枠：インボイス枠 貸付：あり/なし gBizID：あり/なし 次のアクション： 申請可否：あり/なし 次の日程： メモ： | H2: 交付申請シート | J2: 45794 | L2: 佐藤 | N2: 法人 | O2: 建築業 | Q2: あり | R2: 2000万〜2499万 | S2: 再度システム案内必要, 紹介制度案内済み | T2: 0.2 | U2: 0.175 | V2: 0.15 | W2: 0.125 | AA2: =IFERROR(T2+X2+Z2+#REF!+#REF!,"") | AB2: 佐藤 | AC2: 新規 | AH2: 45794 | AI2: 45820 | AJ2: 株式会社Ｃｈａ１ｒｍｅ | AK2: 保管用GoogleドライブURL | AU2: 問題なし | AW2: 50万円 | AY2: 24572843 | AZ2: 22246354 | BA2: 1520736 | BB2: 1509025 | BC2: 64010 | BE2: 500000 | BF2: 1, 000, 000 | BG2: 1, 000, 000 | BP2: システムクラウド | BQ2: 弊社は建築業を営んでおります。現在、受発注・請求・会計業務をExcelや紙で管理しており、事務処理に時間がかかるうえ、情報の一元管理ができておりません。今回のIT導入補助金を活用し、クラウドシステムを導入することで業務の効率化とミスの削減を図り、空いた時間を営業や現場対応に充て、売上向上と事業拡大を目指します。 | BU2: 顧客管理システムの選定と導入 | BV2: 当社では業務に最適な顧客管理システム（CRM）の選定と導入を通じて、営業・マーケティング・カスタマーサポートの業務効率向上と顧客満足度の最大化を目指します。現行の管理方法は属人化・分散化しており、情報共有や分析に課題があるため、全社で統一されたシステムの導入が急務です。自社の業務プロセスと整合性のあるCRMを選定し、段階的に運用を定着させることで、顧客データの一元管理、対応履歴の可視化、施策の最適化を図ります。最終的には、顧客ロイヤルティの向上と、継続的な売上拡大につながる仕組みの構築を目標とします。 | BW2: 株式会社Cha1rmeは、千葉市中央区を拠点に屋根工事を中核としたリフォーム・建築サービスを提供する企業です。主な施工内容は、屋根の葺き替えや雨漏り補修をはじめ、外壁塗装、雨樋の交換・修理など外装部分の総合工事に加え、内装や設備に関するリフォームにも対応しています。足場の設置から工事完了まで一括で請け負い、屋根・外壁から内部空間に至るまでの一貫した施工が可能です。 代表のスキルと経験にも強みがあり、海上自衛隊や福島第一原発での復興作業を含む多彩な実務経験を経た高度な技術者が率いることで、施工品質には定評があります。工事においては単に価格や工程を示すだけでなく、必要な工事の内容、メリット・注意点をしっかりと共有し、顧客が納得した上で進める誠実な対応を重んじています。関東圏を主な対応地域とし、屋根・外装・内装を包括した信頼できるリフォーム会社として活動しています。 | BX2: 佐藤 | BY2: 確認完了 | CA2: 0661 | CB2: 1 | CC2: 0 | CD2: 0 | CE2: 0 | CF2: 0 | CG2: 0 | CH2: 佐藤 | CI2: 田中
BZ4: ここ | CA4: ここ | CB4: ここ | CC4: ここ | CD4: ここ | CE4: ここ | CF4: ここ | CG4: ここ

Sheet 顧客情報_記入用（〜概要案内）
A1: BPOIかどうか | B1: 申請者名 | C1: 紹介者 | D1: 営業担当者 | E1: 区分 | F1: ステータス | G1: 見込み度合い | H1: 詳細メモ | I1: 次のアクション | J1: 次の連絡日 | K1: 概要案内日 | L1: MTG録画 | M1: 案内担当者 | N1: 電話番号 | O1: 事業体 | P1: 業種 | Q1: システム | R1: 貸付 | S1: 売上帯 | T1: 重要タグ | U1: 貸付なし インボイスあり | V1: 貸付なし インボイスなし/現金 | W1: 貸付あり インボイスあり | X1: 貸付あり インボイスなし/現金 | Y1: 紹介者報酬% | Z1: 代理店①番号 | AA1: 代理店①報酬% | AB1: 報酬合計 | AC1: ダブルチェック者 | AD1: おかわり判定 | AE1: 賃上げ可否 | AF1: 過去導入 商品名 | AG1: 検討後失注日 離脱日 | AH1: 代理店契約書URL | AI1: 書類取得開始日 | AJ1: 書類提出日 | AK1: 事業者名 | AL1: 書類① | AM1: 書類② | AN1: 書類③ | AO1: 書類④ | AP1: 書類⑤ （賃金台帳） | AQ1: IT戦略ナビwith PDF | AR1: 従業員有無 | AS1: gBizID TOPスクショ | AT1: gBizID アドレス | AU1: 自己宣言ID(11桁) | AV1: 反社チェック | AW1: 開業/ 設立年月日 | AX1: 資本金 | AY1: 決算月 | AZ1: 売上高 | BA1: 粗利益 | BB1: 営業利益 | BC1: 経常利益 | BD1: 減価償却費 | BE1: 人件費 | BF1: 資本金または準備金 | BG1: 役員報酬総額 | BH1: 給与支払い総額 （前年度実績値） | BI1: ※参考程度 計画数値 (1年度目) | BJ1: ※参考程度 計画数値 (2年度目) | BK1: ※参考程度 計画数値 (3年度目) | BL1: 加点①対象 | BM1: 加点①資料 | BN1: 加点②対象 | BO1: 加点②資料 | BP1: 事業場内最低賃金 | BQ1: 申請システム | BR1: 事業内容文章 （申請文章） | BS1: 3.ビジネスプロセスの改善に向けて ∟その他（フリー記載） | BT1: HP | BU1: 事業内容 | BV1: 挑戦課題のタイトル | BW1: 挑戦課題の解決の目標 | BX1: 成長マッチング 事業内容 | BY1: 情報入力者 | BZ1: 情報入力 確認 | CA1: 事業内容文章 （最終） | CB1: 業種コード | CC1: 事業所数 | CD1: 正規雇用 | CE1: 契約社員 | CF1: パートアルバイト | CG1: 派遣社員 | CH1: その他 | CI1: 1段目 | CJ1: 2段目 | CK1: 3段目

Sheet 顧客情報_参考用（交付申請〜）
A1: BPOIかどうか | B1: 申請者名 | C1: メモ | D1: {=IFERROR(IF(ROW(D1:D1000)=1,"紹介者", IF(#REF!<>"", IF(ISNUMBER(SEARCH("AG-25",#REF!)), IFERROR(VLOOKUP(#REF!, 'AG_案内'!$A$2:$BF1000, MATCH("紹介者", 'AG_案内'!$1:$1, 0), FALSE), ""), IFERROR(VLOOKUP(#REF!, '概要案内'!$A$2:$BG1000, MATCH("紹介者", '概要案内'!$1:$1, 0), FALSE), "") ), "")),"")} -> 紹介者 | E1: 営業担当者 | F1: 申請完了日 | G1: 申請担当者 | H1: 交付申請番号 | I1: 次のアクション | J1: 次に連絡する日 | K1: 資料保管 | L1: 存在資料 | M1: 担当者アドレス | N1: 成長加速マッチング URL | O1: 成長加速マッチング ステータス | P1: 賃上げ | Q1: 省力化ナビ | R1: インボイス登録 | S1: おかわり判定 | T1: 申請者名 | U1: 都道府県 | V1: 募集回 | W1: 申請類型 | X1: ステータス | Y1: ステータス最終更新日 | Z1: ベンダー名 | AA1: ITツール名 | AB1: 補助金対象額（円） | AC1: 申請額（円） | AD1: 交付決定日 | AE1: 交付決定額（円） | AF1: 確定内容承認日時 | AG1: 補助金の確定額(円) | AH1: 貸付調査回答 | AI1: 貸付 | AJ1: 貸付MTG日 | AK1: 貸付MTG日 コミット/完了 | AL1: 貸付MTG担当者 | AM1: 事務所/現地出張 | AN1: 貸付金額 | AO1: 現金 | AP1: ダブルチェック者 | AQ1: 支払日 | AR1: 貸付時刻 | AS1: 支払日 コミット/完了 | AT1: 納品日 | AU1: 納品日 コミット/完了 | AV1: 従業員一覧 | AW1: 従業員一覧フォームURL | AX1: 従業員一覧 作成 | AY1: 実績報告日 | AZ1: 実績報告日 コミット/完了 | BA1: 確定承認日 | BB1: 確定承認日 コミット/完了 | BC1: 交付日 | BD1: 交付日 コミット/完了 | BE1: 返金日 | BF1: 返金日 コミット/完了 | BG1: 助成金支払日 | BH1: 助成金支払日 コミット/完了 | BI1: 完了日 | BJ1: {=IF(ROW(BJ$1:BJ1000)=1,"紹介者番号",IF(#REF!="","",IF(LEFT(#REF!,3)="AG-",VLOOKUP(#REF!,'AG_案内'!$A:$AAC,MATCH("紹介者番号",'AG_案内'!$1:$1,0),0),VLOOKUP(#REF!,'概要案内'!$A:$AAB,MATCH("紹介者番号",'概要案内'!$1:$1,0),0))))} -> 紹介者番号 | BK1: {=IFERROR(IF(ROW(BK1:BK1000)=1,"紹介報酬 LINE名",IF(BJ1:BJ1000<>"", IFERROR(VLOOKUP(BJ1:BJ1000, 'CSV貼り付け'!$A$2:$AJ1000, MATCH("LINE名", 'CSV貼り付け'!$1:$1, 0), FALSE), ""), "")),"")} -> 紹介報酬 LINE名 | BL1: {=IF(ROW(BJ$1:BJ1000)=1,"紹介者報酬%",IF(#REF!="","",IF(LEFT(#REF!,3)="AG-",VLOOKUP(#REF!,'AG_案内'!$A:$AAD,MATCH("紹介者報酬%",'AG_案内'!$1:$1,0),0),VLOOKUP(#REF!,'概要案内'!$A:$AAB,MATCH("紹介者報酬%",'概要案内'!$1:$1,0),0))))} -> 紹介者報酬% | BM1: {=IF(ROW(BM1:BM1000)=1,"紹介報酬 金額", IF(BL1:BL1000<>"", IFERROR($AB1:$AB1000*1.1*BL1:BL1000, ""), ""))} -> 紹介報酬 金額 | BN1: 紹介報酬支払日 | BO1: 紹介報酬支払日 コミット/完了 | BP1: {=IF(ROW(BP$1:BP1000)=1,"代理店①番号",IF(#REF!="","",IF(LEFT(#REF!,3)="AG-",VLOOKUP(#REF!,'AG_案内'!$A:$AAD,MATCH("代理店①番号",'AG_案内'!$1:$1,0),0),VLOOKUP(#REF!,'概要案内'!$A:$AAB,MATCH("代理店①番号",'概要案内'!$1:$1,0),0))))} -> 代理店①番号 | BQ1: {=IFERROR(IF(ROW(BQ1:BQ1000)=1,"代理店報酬① LINE名",IF(BP1:BP1000<>"", IFERROR(VLOOKUP(BP1:BP1000, 'CSV貼り付け'!$A$2:$AJ1000, MATCH("LINE名", 'CSV貼り付け'!$1:$1, 0), FALSE), ""), "")),"")} -> 代理店報酬① LINE名 | BR1: {=IF(ROW(BP$1:BP1000)=1,"代理店①報酬%",IF(#REF!="","",IF(LEFT(#REF!,3)="AG-",VLOOKUP(#REF!,'AG_案内'!$A:$AAD,MATCH("代理店①報酬%",'AG_案内'!$1:$1,0),0),VLOOKUP(#REF!,'概要案内'!$A:$AAB,MATCH("代理店①報酬%",'概要案内'!$1:$1,0),0))))} -> 代理店①報酬% | BS1: {=IF(ROW(BS1:BS1000)=1,"代理店報酬① 金額", IF(BR1:BR1000<>"", IFERROR($AB1:$AB1000*1.1*BR1:BR1000, ""), ""))} -> 代理店報酬① 金額 | BT1: 代理店①報酬支払日 | BU1: 代理店①報酬支払日 コミット/完了 | BV1: {=IF(ROW(BP$1:BP1000)=1,"代理店②番号",IF(#REF!="","",IF(LEFT(#REF!,3)="AG-",VLOOKUP(#REF!,'AG_案内'!$A:$AAD,MATCH("代理店②番号",'AG_案内'!$1:$1,0),0),VLOOKUP(#REF!,'概要案内'!$A:$AAB,MATCH("代理店②番号",'概要案内'!$1:$1,0),0))))} -> 代理店②番号 | BW1: {=IFERROR(IF(ROW(BW1:BW1000)=1,"代理店報酬② LINE名",IF(BV1:BV1000<>"", IFERROR(VLOOKUP(BV1:BV1000, 'CSV貼り付け'!$A$2:$AJ1000, MATCH("LINE名", 'CSV貼り付け'!$1:$1, 0), FALSE), ""), "")),"")} -> 代理店報酬② LINE名 | BX1: {=IF(ROW(BP$1:BP1000)=1,"代理店②報酬%",IF(#REF!="","",IF(LEFT(#REF!,3)="AG-",VLOOKUP(#REF!,'AG_案内'!$A:$AAD,MATCH("代理店②報酬%",'AG_案内'!$1:$1,0),0),VLOOKUP(#REF!,'概要案内'!$A:$AAB,MATCH("代理店②報酬%",'概要案内'!$1:$1,0),0))))} -> 代理店②報酬% | BY1: {=IF(ROW(BY1:BY1000)=1,"代理店報酬② 金額", IF(BX1:BX1000<>"", IFERROR($AB1:$AB1000*1.1*BX1:BX1000, ""), ""))} -> 代理店報酬② 金額 | BZ1: 代理店②報酬支払日 | CA1: 代理店②報酬支払日 コミット/完了 | CB1: {=IF(ROW(BP$1:BP1000)=1,"代理店③番号",IF(#REF!="","",IF(LEFT(#REF!,3)="AG-",VLOOKUP(#REF!,'AG_案内'!$A:$AAD,MATCH("代理店③番号",'AG_案内'!$1:$1,0),0),VLOOKUP(#REF!,'概要案内'!$A:$AAB,MATCH("代理店③番号",'概要案内'!$1:$1,0),0))))} -> 代理店③番号 | CC1: {=IFERROR(IF(ROW(CC1:CC1000)=1,"代理店報酬③ LINE名",IF(CB1:CB1000<>"", IFERROR(VLOOKUP(CB1:CB1000, 'CSV貼り付け'!$A$2:$AJ1000, MATCH("LINE名", 'CSV貼り付け'!$1:$1, 0), FALSE), ""), "")),"")} -> 代理店報酬③ LINE名 | CD1: {=IF(ROW(BP$1:BP1000)=1,"代理店③報酬%",IF(#REF!="","",IF(LEFT(#REF!,3)="AG-",VLOOKUP(#REF!,'AG_案内'!$A:$AAD,MATCH("代理店③報酬%",'AG_案内'!$1:$1,0),0),VLOOKUP(#REF!,'概要案内'!$A:$AAB,MATCH("代理店③報酬%",'概要案内'!$1:$1,0),0))))} -> 代理店③報酬% | CE1: {=IF(ROW(CE1:CE1000)=1,"代理店報酬③ 金額", IF(CD1:CD1000<>"", IFERROR($AB1:$AB1000*1.1*CD1:CD1000, ""), ""))} -> 代理店報酬③ 金額 | CF1: 代理店③報酬支払日 | CG1: 代理店③報酬支払日 コミット/完了 | CH1: ベンダー パターン | CI1: ツール パターン | CJ1: {=IFERROR(IF(ROW(CJ1:CJ1000)=1,"おかわり判定", IF(#REF!<>"", IF(ISNUMBER(SEARCH("AG-25",#REF!)), IFERROR(VLOOKUP(#REF!, 'AG_案内'!$A$2:$CY1000, MATCH("おかわり判定", 'AG_案内'!$1:$1, 0), FALSE), ""), IFERROR(VLOOKUP(#REF!, '概要案内'!$A$2:$DF1000, MATCH("おかわり判定", '概要案内'!$1:$1, 0), FALSE), "") ), "")),"")} -> おかわり判定 | CK1: {=IF( ROW(CK1:CK1000) = 1, "1段目", IF(#REF!<>"", IFERROR( VLOOKUP( #REF!, { INDIRECT("'CSV貼り付け'!"& SUBSTITUTE(ADDRESS(2, MATCH("LINE番号", 'CSV貼り付け'!$1:$1, 0)), "$", "") & ":" & SUBSTITUTE(ADDRESS(ROWS('CSV貼り付け'!$A:$A), MATCH("LINE番号", 'CSV貼り付け'!$1:$1, 0)), "$", "") ), INDIRECT("'CSV貼り付け'!"& SUBSTITUTE(ADDRESS(2, MATCH("1段目", 'CSV貼り付け'!$1:$1, 0)), "$", "") & ":" & SUBSTITUTE(ADDRESS(ROWS('CSV貼り付け'!$A:$A), MATCH("1段目", 'CSV貼り付け'!$1:$1, 0)), "$", "") ) }, 2, FALSE ), "" ),"") )} -> 1段目 | CL1: {=IF( ROW(CL1:CL1000) = 1, "2段目", IF(#REF!<>"", IFERROR( VLOOKUP( #REF!, { INDIRECT("'CSV貼り付け'!"& SUBSTITUTE(ADDRESS(2, MATCH("LINE番号", 'CSV貼り付け'!$1:$1, 0)), "$", "") & ":" & SUBSTITUTE(ADDRESS(ROWS('CSV貼り付け'!$A:$A), MATCH("LINE番号", 'CSV貼り付け'!$1:$1, 0)), "$", "") ), INDIRECT("'CSV貼り付け'!"& SUBSTITUTE(ADDRESS(2, MATCH("2段目", 'CSV貼り付け'!$1:$1, 0)), "$", "") & ":" & SUBSTITUTE(ADDRESS(ROWS('CSV貼り付け'!$A:$A), MATCH("2段目", 'CSV貼り付け'!$1:$1, 0)), "$", "") ) }, 2, FALSE ), "" ),"") )} -> 2段目 | CM1: {=IF( ROW(CM1:CM1000) = 1, "3段目", IF(#REF!<>"", IFERROR( VLOOKUP( #REF!, { INDIRECT("'CSV貼り付け'!"& SUBSTITUTE(ADDRESS(2, MATCH("LINE番号", 'CSV貼り付け'!$1:$1, 0)), "$", "") & ":" & SUBSTITUTE(ADDRESS(ROWS('CSV貼り付け'!$A:$A), MATCH("LINE番号", 'CSV貼り付け'!$1:$1, 0)), "$", "") ), INDIRECT("'CSV貼り付け'!"& SUBSTITUTE(ADDRESS(2, MATCH("3段目", 'CSV貼り付け'!$1:$1, 0)), "$", "") & ":" & SUBSTITUTE(ADDRESS(ROWS('CSV貼り付け'!$A:$A), MATCH("3段目", 'CSV貼り付け'!$1:$1, 0)), "$", "") ) }, 2, FALSE ), "" ),"") )} -> 3段目 | CN1: {=IF( ROW(CN1:CN1000) = 1, "4段目", IF(#REF!<>"", IFERROR( VLOOKUP( #REF!, { INDIRECT("'CSV貼り付け'!"& SUBSTITUTE(ADDRESS(2, MATCH("LINE番号", 'CSV貼り付け'!$1:$1, 0)), "$", "") & ":" & SUBSTITUTE(ADDRESS(ROWS('CSV貼り付け'!$A:$A), MATCH("LINE番号", 'CSV貼り付け'!$1:$1, 0)), "$", "") ), INDIRECT("'CSV貼り付け'!"& SUBSTITUTE(ADDRESS(2, MATCH("4段目", 'CSV貼り付け'!$1:$1, 0)), "$", "") & ":" & SUBSTITUTE(ADDRESS(ROWS('CSV貼り付け'!$A:$A), MATCH("4段目", 'CSV貼り付け'!$1:$1, 0)), "$", "") ) }, 2, FALSE ), "" ),"") )} -> 4段目 | CO1: {=IF( ROW(CO1:CO1000) = 1, "5段目", IF(#REF!<>"", IFERROR( VLOOKUP( #REF!, { INDIRECT("'CSV貼り付け'!"& SUBSTITUTE(ADDRESS(2, MATCH("LINE番号", 'CSV貼り付け'!$1:$1, 0)), "$", "") & ":" & SUBSTITUTE(ADDRESS(ROWS('CSV貼り付け'!$A:$A), MATCH("LINE番号", 'CSV貼り付け'!$1:$1, 0)), "$", "") ), INDIRECT("'CSV貼り付け'!"& SUBSTITUTE(ADDRESS(2, MATCH("5段目", 'CSV貼り付け'!$1:$1, 0)), "$", "") & ":" & SUBSTITUTE(ADDRESS(ROWS('CSV貼り付け'!$A:$A), MATCH("5段目", 'CSV貼り付け'!$1:$1, 0)), "$", "") ) }, 2, FALSE ), "" ),"") )} -> 5段目 | CP1: {=IF( ROW(CP1:CP1000) = 1, "6段目", IF(#REF!<>"", IFERROR( VLOOKUP( #REF!, { INDIRECT("'CSV貼り付け'!"& SUBSTITUTE(ADDRESS(2, MATCH("LINE番号", 'CSV貼り付け'!$1:$1, 0)), "$", "") & ":" & SUBSTITUTE(ADDRESS(ROWS('CSV貼り付け'!$A:$A), MATCH("LINE番号", 'CSV貼り付け'!$1:$1, 0)), "$", "") ), INDIRECT("'CSV貼り付け'!"& SUBSTITUTE(ADDRESS(2, MATCH("6段目", 'CSV貼り付け'!$1:$1, 0)), "$", "") & ":" & SUBSTITUTE(ADDRESS(ROWS('CSV貼り付け'!$A:$A), MATCH("6段目", 'CSV貼り付け'!$1:$1, 0)), "$", "") ) }, 2, FALSE ), "" ),"") )} -> 6段目 | CQ1: {=IF( ROW(CQ1:CQ1000) = 1, "7段目", IF(#REF!<>"", IFERROR( VLOOKUP( #REF!, { INDIRECT("'CSV貼り付け'!"& SUBSTITUTE(ADDRESS(2, MATCH("LINE番号", 'CSV貼り付け'!$1:$1, 0)), "$", "") & ":" & SUBSTITUTE(ADDRESS(ROWS('CSV貼り付け'!$A:$A), MATCH("LINE番号", 'CSV貼り付け'!$1:$1, 0)), "$", "") ), INDIRECT("'CSV貼り付け'!"& SUBSTITUTE(ADDRESS(2, MATCH("7段目", 'CSV貼り付け'!$1:$1, 0)), "$", "") & ":" & SUBSTITUTE(ADDRESS(ROWS('CSV貼り付け'!$A:$A), MATCH("7段目", 'CSV貼り付け'!$1:$1, 0)), "$", "") ) }, 2, FALSE ), "" ),"") )} -> 7段目 | CR1: {=IF( ROW(CR1:CR1000) = 1, "8段目", IF(#REF!<>"", IFERROR( VLOOKUP( #REF!, { INDIRECT("'CSV貼り付け'!"& SUBSTITUTE(ADDRESS(2, MATCH("LINE番号", 'CSV貼り付け'!$1:$1, 0)), "$", "") & ":" & SUBSTITUTE(ADDRESS(ROWS('CSV貼り付け'!$A:$A), MATCH("LINE番号", 'CSV貼り付け'!$1:$1, 0)), "$", "") ), INDIRECT("'CSV貼り付け'!"& SUBSTITUTE(ADDRESS(2, MATCH("8段目", 'CSV貼り付け'!$1:$1, 0)), "$", "") & ":" & SUBSTITUTE(ADDRESS(ROWS('CSV貼り付け'!$A:$A), MATCH("8段目", 'CSV貼り付け'!$1:$1, 0)), "$", "") ) }, 2, FALSE ), "" ),"") )} -> 8段目 | CS1: {=IF( ROW(CS1:CS1000) = 1, "9段目", IF(#REF!<>"", IFERROR( VLOOKUP( #REF!, { INDIRECT("'CSV貼り付け'!"& SUBSTITUTE(ADDRESS(2, MATCH("LINE番号", 'CSV貼り付け'!$1:$1, 0)), "$", "") & ":" & SUBSTITUTE(ADDRESS(ROWS('CSV貼り付け'!$A:$A), MATCH("LINE番号", 'CSV貼り付け'!$1:$1, 0)), "$", "") ), INDIRECT("'CSV貼り付け'!"& SUBSTITUTE(ADDRESS(2, MATCH("9段目", 'CSV貼り付け'!$1:$1, 0)), "$", "") & ":" & SUBSTITUTE(ADDRESS(ROWS('CSV貼り付け'!$A:$A), MATCH("9段目", 'CSV貼り付け'!$1:$1, 0)), "$", "") ) }, 2, FALSE ), "" ),"") )} -> 9段目 | CT1: {=IF( ROW(CT1:CT1000) = 1, "10段目", IF(#REF!<>"", IFERROR( VLOOKUP( #REF!, { INDIRECT("'CSV貼り付け'!"& SUBSTITUTE(ADDRESS(2, MATCH("LINE番号", 'CSV貼り付け'!$1:$1, 0)), "$", "") & ":" & SUBSTITUTE(ADDRESS(ROWS('CSV貼り付け'!$A:$A), MATCH("LINE番号", 'CSV貼り付け'!$1:$1, 0)), "$", "") ), INDIRECT("'CSV貼り付け'!"& SUBSTITUTE(ADDRESS(2, MATCH("10段目", 'CSV貼り付け'!$1:$1, 0)), "$", "") & ":" & SUBSTITUTE(ADDRESS(ROWS('CSV貼り付け'!$A:$A), MATCH("10段目", 'CSV貼り付け'!$1:$1, 0)), "$", "") ) }, 2, FALSE ), "" ),"") )} -> 10段目 | CU1: {=IF( ROW(CU1:CU1000) = 1, "uid", IF(#REF!<>"", IFERROR( VLOOKUP( #REF!, { INDIRECT("'CSV貼り付け'!"& SUBSTITUTE(ADDRESS(2, MATCH("LINE番号", 'CSV貼り付け'!$1:$1, 0)), "$", "") & ":" & SUBSTITUTE(ADDRESS(ROWS('CSV貼り付け'!$A:$A), MATCH("LINE番号", 'CSV貼り付け'!$1:$1, 0)), "$", "") ), INDIRECT("'CSV貼り付け'!"& SUBSTITUTE(ADDRESS(2, MATCH("uid", 'CSV貼り付け'!$1:$1, 0)), "$", "") & ":" & SUBSTITUTE(ADDRESS(ROWS('CSV貼り付け'!$A:$A), MATCH("uid", 'CSV貼り付け'!$1:$1, 0)), "$", "") ) }, 2, FALSE ), "" ),"") )} -> uid
F2: 45804 | G2: 佐藤 | H2: KSN01-0000001 | I2: 完了 | K2: 各種資料保管用 GoogleドライブURL | L2: 申請支援契約書（通称：違約金契約書）, 1_請求明細書, 従業員一覧, 支払証憑, 口座情報, ソフトウェアキャプチャ, 利用規約 | M2: 0000@gmail.com | S2: 概要案内シートより転記 | AI2: あり | AJ2: 45865 | AK2: 完了 | AL2: 佐藤 | AM2: 事務所 | AN2: 2660000 | AO2: - | AQ2: 45911 | AS2: 完了 | AT2: 45912 | AU2: 完了 | AV2: {=IFERROR( INDEX(#REF!,MATCH(H2,'従業員一覧フォーム'!$D:$D,0),MATCH("従業員一覧を提出してください。",'従業員一覧フォーム'!$1:$1,0)) ,"未提出")} -> 未提出 | AX2: 書類作成済み | AY2: 45918 | AZ2: 完了 | BA2: 45930 | BB2: 完了 | BC2: 45945 | BD2: 完了 | BE2: 45945 | BF2: 完了 | BG2: 45952 | BH2: 完了 | BI2: 45952 | BJ2: #REF! | BL2: #REF! | BM2: #REF! | BN2: 45976 | BO2: 完了 | BP2: #REF! | BR2: #REF! | BS2: #REF! | BT2: 45976 | BU2: コミット | BV2: #REF! | BX2: #REF! | BY2: #REF! | CB2: #REF! | CD2: #REF! | CE2: #REF! | CH2: 株式会社エイトフューチャー② | CI2: システムクラウド① | CK2: #REF! | CL2: #REF! | CM2: #REF! | CN2: #REF! | CO2: #REF! | CP2: #REF! | CQ2: #REF! | CR2: #REF! | CS2: #REF! | CT2: #REF! | CU2: #REF!
BJ3: #REF! | BL3: #REF! | BM3: #REF! | BP3: #REF! | BR3: #REF! | BS3: #REF! | BV3: #REF! | BX3: #REF! | BY3: #REF! | CB3: #REF! | CD3: #REF! | CE3: #REF! | CK3: #REF! | CL3: #REF! | CM3: #REF! | CN3: #REF! | CO3: #REF! | CP3: #REF! | CQ3: #REF! | CR3: #REF! | CS3: #REF! | CT3: #REF! | CU3: #REF!
A4: BPO側が入力する項目 | C4: ここ | F4: ここ | G4: ここ | H4: ここ | I4: ここ | J4: ここ | M4: ここ | N4: ここ | O4: ここ | P4: ここ | Q4: ここ | R4: ここ | BJ4: #REF! | BL4: #REF! | BM4: #REF! | BP4: #REF! | BR4: #REF! | BS4: #REF! | BV4: #REF! | BX4: #REF! | BY4: #REF! | CB4: #REF! | CD4: #REF! | CE4: #REF! | CK4: #REF! | CL4: #REF! | CM4: #REF! | CN4: #REF! | CO4: #REF! | CP4: #REF! | CQ4: #REF! | CR4: #REF! | CS4: #REF! | CT4: #REF! | CU4: #REF!
BJ5: #REF! | BL5: #REF! | BM5: #REF! | BP5: #REF! | BR5: #REF! | BS5: #REF! | BV5: #REF! | BX5: #REF! | BY5: #REF! | CB5: #REF! | CD5: #REF! | CE5: #REF! | CK5: #REF! | CL5: #REF! | CM5: #REF! | CN5: #REF! | CO5: #REF! | CP5: #REF! | CQ5: #REF! | CR5: #REF! | CS5: #REF! | CT5: #REF! | CU5: #REF!
BJ6: #REF! | BL6: #REF! | BM6: #REF! | BP6: #REF! | BR6: #REF! | BS6: #REF! | BV6: #REF! | BX6: #REF! | BY6: #REF! | CB6: #REF! | CD6: #REF! | CE6: #REF! | CK6: #REF! | CL6: #REF! | CM6: #REF! | CN6: #REF! | CO6: #REF! | CP6: #REF! | CQ6: #REF! | CR6: #REF! | CS6: #REF! | CT6: #REF! | CU6: #REF!
BJ7: #REF! | BL7: #REF! | BM7: #REF! | BP7: #REF! | BR7: #REF! | BS7: #REF! | BV7: #REF! | BX7: #REF! | BY7: #REF! | CB7: #REF! | CD7: #REF! | CE7: #REF! | CK7: #REF! | CL7: #REF! | CM7: #REF! | CN7: #REF! | CO7: #REF! | CP7: #REF! | CQ7: #REF! | CR7: #REF! | CS7: #REF! | CT7: #REF! | CU7: #REF!
BJ8: #REF! | BL8: #REF! | BM8: #REF! | BP8: #REF! | BR8: #REF! | BS8: #REF! | BV8: #REF! | BX8: #REF! | BY8: #REF! | CB8: #REF! | CD8: #REF! | CE8: #REF! | CK8: #REF! | CL8: #REF! | CM8: #REF! | CN8: #REF! | CO8: #REF! | CP8: #REF! | CQ8: #REF! | CR8: #REF! | CS8: #REF! | CT8: #REF! | CU8: #REF!
BJ9: #REF! | BL9: #REF! | BM9: #REF! | BP9: #REF! | BR9: #REF! | BS9: #REF! | BV9: #REF! | BX9: #REF! | BY9: #REF! | CB9: #REF! | CD9: #REF! | CE9: #REF! | CK9: #REF! | CL9: #REF! | CM9: #REF! | CN9: #REF! | CO9: #REF! | CP9: #REF! | CQ9: #REF! | CR9: #REF! | CS9: #REF! | CT9: #REF! | CU9: #REF!
BJ10: #REF! | BL10: #REF! | BM10: #REF! | BP10: #REF! | BR10: #REF! | BS10: #REF! | BV10: #REF! | BX10: #REF! | BY10: #REF! | CB10: #REF! | CD10: #REF! | CE10: #REF! | CK10: #REF! | CL10: #REF! | CM10: #REF! | CN10: #REF! | CO10: #REF! | CP10: #REF! | CQ10: #REF! | CR10: #REF! | CS10: #REF! | CT10: #REF! | CU10: #REF!
BJ11: #REF! | BL11: #REF! | BM11: #REF! | BP11: #REF! | BR11: #REF! | BS11: #REF! | BV11: #REF! | BX11: #REF! | BY11: #REF! | CB11: #REF! | CD11: #REF! | CE11: #REF! | CK11: #REF! | CL11: #REF! | CM11: #REF! | CN11: #REF! | CO11: #REF! | CP11: #REF! | CQ11: #REF! | CR11: #REF! | CS11: #REF! | CT11: #REF! | CU11: #REF!
BJ12: #REF! | BL12: #REF! | BM12: #REF! | BP12: #REF! | BR12: #REF! | BS12: #REF! | BV12: #REF! | BX12: #REF! | BY12: #REF! | CB12: #REF! | CD12: #REF! | CE12: #REF! | CK12: #REF! | CL12: #REF! | CM12: #REF! | CN12: #REF! | CO12: #REF! | CP12: #REF! | CQ12: #REF! | CR12: #REF! | CS12: #REF! | CT12: #REF! | CU12: #REF!
BJ13: #REF! | BL13: #REF! | BM13: #REF! | BP13: #REF! | BR13: #REF! | BS13: #REF! | BV13: #REF! | BX13: #REF! | BY13: #REF! | CB13: #REF! | CD13: #REF! | CE13: #REF! | CK13: #REF! | CL13: #REF! | CM13: #REF! | CN13: #REF! | CO13: #REF! | CP13: #REF! | CQ13: #REF! | CR13: #REF! | CS13: #REF! | CT13: #REF! | CU13: #REF!
BJ14: #REF! | BL14: #REF! | BM14: #REF! | BP14: #REF! | BR14: #REF! | BS14: #REF! | BV14: #REF! | BX14: #REF! | BY14: #REF! | CB14: #REF! | CD14: #REF! | CE14: #REF! | CK14: #REF! | CL14: #REF! | CM14: #REF! | CN14: #REF! | CO14: #REF! | CP14: #REF! | CQ14: #REF! | CR14: #REF! | CS14: #REF! | CT14: #REF! | CU14: #REF!
BJ15: #REF! | BL15: #REF! | BM15: #REF! | BP15: #REF! | BR15: #REF! | BS15: #REF! | BV15: #REF! | BX15: #REF! | BY15: #REF! | CB15: #REF! | CD15: #REF! | CE15: #REF! | CK15: #REF! | CL15: #REF! | CM15: #REF! | CN15: #REF! | CO15: #REF! | CP15: #REF! | CQ15: #REF! | CR15: #REF! | CS15: #REF! | CT15: #REF! | CU15: #REF!
BJ16: #REF! | BL16: #REF! | BM16: #REF! | BP16: #REF! | BR16: #REF! | BS16: #REF! | BV16: #REF! | BX16: #REF! | BY16: #REF! | CB16: #REF! | CD16: #REF! | CE16: #REF! | CK16: #REF! | CL16: #REF! | CM16: #REF! | CN16: #REF! | CO16: #REF! | CP16: #REF! | CQ16: #REF! | CR16: #REF! | CS16: #REF! | CT16: #REF! | CU16: #REF!
... BJ1000: #REF! | BL1000: #REF! | BM1000: #REF! | BP1000: #REF! | BR1000: #REF! | BS1000: #REF! | BV1000: #REF! | BX1000: #REF! | BY1000: #REF! | CB1000: #REF! | CD1000: #REF! | CE1000: #REF! | CK1000: #REF! | CL1000: #REF! | CM1000: #REF! | CN1000: #REF! | CO1000: #REF! | CP1000: #REF! | CQ1000: #REF! | CR1000: #REF! | CS1000: #REF! | CT1000: #REF! | CU1000: #REF!

Sheet 顧客情報_記入用（交付申請〜）
A1: BPOIかどうか | B1: 申請者名 | C1: メモ | D1: {=IFERROR(IF(ROW(D1:D1000)=1,"紹介者", IF(#REF!<>"", IF(ISNUMBER(SEARCH("AG-25",#REF!)), IFERROR(VLOOKUP(#REF!, 'AG_案内'!$A$2:$BF1000, MATCH("紹介者", 'AG_案内'!$1:$1, 0), FALSE), ""), IFERROR(VLOOKUP(#REF!, '概要案内'!$A$2:$BG1000, MATCH("紹介者", '概要案内'!$1:$1, 0), FALSE), "") ), "")),"")} -> 紹介者 | E1: 営業担当者 | F1: 申請完了日 | G1: 申請担当者 | H1: 交付申請番号 | I1: 次のアクション | J1: 次に連絡する日 | K1: 資料保管 | L1: 存在資料 | M1: 担当者アドレス | N1: 成長加速マッチング URL | O1: 成長加速マッチング ステータス | P1: 賃上げ | Q1: 省力化ナビ | R1: インボイス登録 | S1: おかわり判定 | T1: 申請者名 | U1: 都道府県 | V1: 募集回 | W1: 申請類型 | X1: ステータス | Y1: ステータス最終更新日 | Z1: ベンダー名 | AA1: ITツール名 | AB1: 補助金対象額（円） | AC1: 申請額（円） | AD1: 交付決定日 | AE1: 交付決定額（円） | AF1: 確定内容承認日時 | AG1: 補助金の確定額(円) | AH1: 貸付調査回答 | AI1: 貸付 | AJ1: 貸付MTG日 | AK1: 貸付MTG日 コミット/完了 | AL1: 貸付MTG担当者 | AM1: 事務所/現地出張 | AN1: 貸付金額 | AO1: 現金 | AP1: ダブルチェック者 | AQ1: 支払日 | AR1: 貸付時刻 | AS1: 支払日 コミット/完了 | AT1: 納品日 | AU1: 納品日 コミット/完了 | AV1: 従業員一覧 | AW1: 従業員一覧フォームURL | AX1: 従業員一覧 作成 | AY1: 実績報告日 | AZ1: 実績報告日 コミット/完了 | BA1: 確定承認日 | BB1: 確定承認日 コミット/完了 | BC1: 交付日 | BD1: 交付日 コミット/完了 | BE1: 返金日 | BF1: 返金日 コミット/完了 | BG1: 助成金支払日 | BH1: 助成金支払日 コミット/完了 | BI1: 完了日 | BJ1: {=IF(ROW(BJ$1:BJ1000)=1,"紹介者番号",IF(#REF!="","",IF(LEFT(#REF!,3)="AG-",VLOOKUP(#REF!,'AG_案内'!$A:$AAC,MATCH("紹介者番号",'AG_案内'!$1:$1,0),0),VLOOKUP(#REF!,'概要案内'!$A:$AAB,MATCH("紹介者番号",'概要案内'!$1:$1,0),0))))} -> 紹介者番号 | BK1: {=IFERROR(IF(ROW(BK1:BK1000)=1,"紹介報酬 LINE名",IF(BJ1:BJ1000<>"", IFERROR(VLOOKUP(BJ1:BJ1000, 'CSV貼り付け'!$A$2:$AJ1000, MATCH("LINE名", 'CSV貼り付け'!$1:$1, 0), FALSE), ""), "")),"")} -> 紹介報酬 LINE名 | BL1: {=IF(ROW(BJ$1:BJ1000)=1,"紹介者報酬%",IF(#REF!="","",IF(LEFT(#REF!,3)="AG-",VLOOKUP(#REF!,'AG_案内'!$A:$AAD,MATCH("紹介者報酬%",'AG_案内'!$1:$1,0),0),VLOOKUP(#REF!,'概要案内'!$A:$AAB,MATCH("紹介者報酬%",'概要案内'!$1:$1,0),0))))} -> 紹介者報酬% | BM1: {=IF(ROW(BM1:BM1000)=1,"紹介報酬 金額", IF(BL1:BL1000<>"", IFERROR($AB1:$AB1000*1.1*BL1:BL1000, ""), ""))} -> 紹介報酬 金額 | BN1: 紹介報酬支払日 | BO1: 紹介報酬支払日 コミット/完了 | BP1: {=IF(ROW(BP$1:BP1000)=1,"代理店①番号",IF(#REF!="","",IF(LEFT(#REF!,3)="AG-",VLOOKUP(#REF!,'AG_案内'!$A:$AAD,MATCH("代理店①番号",'AG_案内'!$1:$1,0),0),VLOOKUP(#REF!,'概要案内'!$A:$AAB,MATCH("代理店①番号",'概要案内'!$1:$1,0),0))))} -> 代理店①番号 | BQ1: {=IFERROR(IF(ROW(BQ1:BQ1000)=1,"代理店報酬① LINE名",IF(BP1:BP1000<>"", IFERROR(VLOOKUP(BP1:BP1000, 'CSV貼り付け'!$A$2:$AJ1000, MATCH("LINE名", 'CSV貼り付け'!$1:$1, 0), FALSE), ""), "")),"")} -> 代理店報酬① LINE名 | BR1: {=IF(ROW(BP$1:BP1000)=1,"代理店①報酬%",IF(#REF!="","",IF(LEFT(#REF!,3)="AG-",VLOOKUP(#REF!,'AG_案内'!$A:$AAD,MATCH("代理店①報酬%",'AG_案内'!$1:$1,0),0),VLOOKUP(#REF!,'概要案内'!$A:$AAB,MATCH("代理店①報酬%",'概要案内'!$1:$1,0),0))))} -> 代理店①報酬% | BS1: {=IF(ROW(BS1:BS1000)=1,"代理店報酬① 金額", IF(BR1:BR1000<>"", IFERROR($AB1:$AB1000*1.1*BR1:BR1000, ""), ""))} -> 代理店報酬① 金額 | BT1: 代理店①報酬支払日 | BU1: 代理店①報酬支払日 コミット/完了 | BV1: {=IF(ROW(BP$1:BP1000)=1,"代理店②番号",IF(#REF!="","",IF(LEFT(#REF!,3)="AG-",VLOOKUP(#REF!,'AG_案内'!$A:$AAD,MATCH("代理店②番号",'AG_案内'!$1:$1,0),0),VLOOKUP(#REF!,'概要案内'!$A:$AAB,MATCH("代理店②番号",'概要案内'!$1:$1,0),0))))} -> 代理店②番号 | BW1: {=IFERROR(IF(ROW(BW1:BW1000)=1,"代理店報酬② LINE名",IF(BV1:BV1000<>"", IFERROR(VLOOKUP(BV1:BV1000, 'CSV貼り付け'!$A$2:$AJ1000, MATCH("LINE名", 'CSV貼り付け'!$1:$1, 0), FALSE), ""), "")),"")} -> 代理店報酬② LINE名 | BX1: {=IF(ROW(BP$1:BP1000)=1,"代理店②報酬%",IF(#REF!="","",IF(LEFT(#REF!,3)="AG-",VLOOKUP(#REF!,'AG_案内'!$A:$AAD,MATCH("代理店②報酬%",'AG_案内'!$1:$1,0),0),VLOOKUP(#REF!,'概要案内'!$A:$AAB,MATCH("代理店②報酬%",'概要案内'!$1:$1,0),0))))} -> 代理店②報酬% | BY1: {=IF(ROW(BY1:BY1000)=1,"代理店報酬② 金額", IF(BX1:BX1000<>"", IFERROR($AB1:$AB1000*1.1*BX1:BX1000, ""), ""))} -> 代理店報酬② 金額 | BZ1: 代理店②報酬支払日 | CA1: 代理店②報酬支払日 コミット/完了 | CB1: {=IF(ROW(BP$1:BP1000)=1,"代理店③番号",IF(#REF!="","",IF(LEFT(#REF!,3)="AG-",VLOOKUP(#REF!,'AG_案内'!$A:$AAD,MATCH("代理店③番号",'AG_案内'!$1:$1,0),0),VLOOKUP(#REF!,'概要案内'!$A:$AAB,MATCH("代理店③番号",'概要案内'!$1:$1,0),0))))} -> 代理店③番号 | CC1: {=IFERROR(IF(ROW(CC1:CC1000)=1,"代理店報酬③ LINE名",IF(CB1:CB1000<>"", IFERROR(VLOOKUP(CB1:CB1000, 'CSV貼り付け'!$A$2:$AJ1000, MATCH("LINE名", 'CSV貼り付け'!$1:$1, 0), FALSE), ""), "")),"")} -> 代理店報酬③ LINE名 | CD1: {=IF(ROW(BP$1:BP1000)=1,"代理店③報酬%",IF(#REF!="","",IF(LEFT(#REF!,3)="AG-",VLOOKUP(#REF!,'AG_案内'!$A:$AAD,MATCH("代理店③報酬%",'AG_案内'!$1:$1,0),0),VLOOKUP(#REF!,'概要案内'!$A:$AAB,MATCH("代理店③報酬%",'概要案内'!$1:$1,0),0))))} -> 代理店③報酬% | CE1: {=IF(ROW(CE1:CE1000)=1,"代理店報酬③ 金額", IF(CD1:CD1000<>"", IFERROR($AB1:$AB1000*1.1*CD1:CD1000, ""), ""))} -> 代理店報酬③ 金額 | CF1: 代理店③報酬支払日 | CG1: 代理店③報酬支払日 コミット/完了 | CH1: ベンダー パターン | CI1: ツール パターン | CJ1: {=IFERROR(IF(ROW(CJ1:CJ1000)=1,"おかわり判定", IF(#REF!<>"", IF(ISNUMBER(SEARCH("AG-25",#REF!)), IFERROR(VLOOKUP(#REF!, 'AG_案内'!$A$2:$CY1000, MATCH("おかわり判定", 'AG_案内'!$1:$1, 0), FALSE), ""), IFERROR(VLOOKUP(#REF!, '概要案内'!$A$2:$DF1000, MATCH("おかわり判定", '概要案内'!$1:$1, 0), FALSE), "") ), "")),"")} -> おかわり判定 | CK1: {=IF( ROW(CK1:CK1000) = 1, "1段目", IF(#REF!<>"", IFERROR( VLOOKUP( #REF!, { INDIRECT("'CSV貼り付け'!"& SUBSTITUTE(ADDRESS(2, MATCH("LINE番号", 'CSV貼り付け'!$1:$1, 0)), "$", "") & ":" & SUBSTITUTE(ADDRESS(ROWS('CSV貼り付け'!$A:$A), MATCH("LINE番号", 'CSV貼り付け'!$1:$1, 0)), "$", "") ), INDIRECT("'CSV貼り付け'!"& SUBSTITUTE(ADDRESS(2, MATCH("1段目", 'CSV貼り付け'!$1:$1, 0)), "$", "") & ":" & SUBSTITUTE(ADDRESS(ROWS('CSV貼り付け'!$A:$A), MATCH("1段目", 'CSV貼り付け'!$1:$1, 0)), "$", "") ) }, 2, FALSE ), "" ),"") )} -> 1段目 | CL1: {=IF( ROW(CL1:CL1000) = 1, "2段目", IF(#REF!<>"", IFERROR( VLOOKUP( #REF!, { INDIRECT("'CSV貼り付け'!"& SUBSTITUTE(ADDRESS(2, MATCH("LINE番号", 'CSV貼り付け'!$1:$1, 0)), "$", "") & ":" & SUBSTITUTE(ADDRESS(ROWS('CSV貼り付け'!$A:$A), MATCH("LINE番号", 'CSV貼り付け'!$1:$1, 0)), "$", "") ), INDIRECT("'CSV貼り付け'!"& SUBSTITUTE(ADDRESS(2, MATCH("2段目", 'CSV貼り付け'!$1:$1, 0)), "$", "") & ":" & SUBSTITUTE(ADDRESS(ROWS('CSV貼り付け'!$A:$A), MATCH("2段目", 'CSV貼り付け'!$1:$1, 0)), "$", "") ) }, 2, FALSE ), "" ),"") )} -> 2段目 | CM1: {=IF( ROW(CM1:CM1000) = 1, "3段目", IF(#REF!<>"", IFERROR( VLOOKUP( #REF!, { INDIRECT("'CSV貼り付け'!"& SUBSTITUTE(ADDRESS(2, MATCH("LINE番号", 'CSV貼り付け'!$1:$1, 0)), "$", "") & ":" & SUBSTITUTE(ADDRESS(ROWS('CSV貼り付け'!$A:$A), MATCH("LINE番号", 'CSV貼り付け'!$1:$1, 0)), "$", "") ), INDIRECT("'CSV貼り付け'!"& SUBSTITUTE(ADDRESS(2, MATCH("3段目", 'CSV貼り付け'!$1:$1, 0)), "$", "") & ":" & SUBSTITUTE(ADDRESS(ROWS('CSV貼り付け'!$A:$A), MATCH("3段目", 'CSV貼り付け'!$1:$1, 0)), "$", "") ) }, 2, FALSE ), "" ),"") )} -> 3段目 | CN1: {=IF( ROW(CN1:CN1000) = 1, "4段目", IF(#REF!<>"", IFERROR( VLOOKUP( #REF!, { INDIRECT("'CSV貼り付け'!"& SUBSTITUTE(ADDRESS(2, MATCH("LINE番号", 'CSV貼り付け'!$1:$1, 0)), "$", "") & ":" & SUBSTITUTE(ADDRESS(ROWS('CSV貼り付け'!$A:$A), MATCH("LINE番号", 'CSV貼り付け'!$1:$1, 0)), "$", "") ), INDIRECT("'CSV貼り付け'!"& SUBSTITUTE(ADDRESS(2, MATCH("4段目", 'CSV貼り付け'!$1:$1, 0)), "$", "") & ":" & SUBSTITUTE(ADDRESS(ROWS('CSV貼り付け'!$A:$A), MATCH("4段目", 'CSV貼り付け'!$1:$1, 0)), "$", "") ) }, 2, FALSE ), "" ),"") )} -> 4段目 | CO1: {=IF( ROW(CO1:CO1000) = 1, "5段目", IF(#REF!<>"", IFERROR( VLOOKUP( #REF!, { INDIRECT("'CSV貼り付け'!"& SUBSTITUTE(ADDRESS(2, MATCH("LINE番号", 'CSV貼り付け'!$1:$1, 0)), "$", "") & ":" & SUBSTITUTE(ADDRESS(ROWS('CSV貼り付け'!$A:$A), MATCH("LINE番号", 'CSV貼り付け'!$1:$1, 0)), "$", "") ), INDIRECT("'CSV貼り付け'!"& SUBSTITUTE(ADDRESS(2, MATCH("5段目", 'CSV貼り付け'!$1:$1, 0)), "$", "") & ":" & SUBSTITUTE(ADDRESS(ROWS('CSV貼り付け'!$A:$A), MATCH("5段目", 'CSV貼り付け'!$1:$1, 0)), "$", "") ) }, 2, FALSE ), "" ),"") )} -> 5段目 | CP1: {=IF( ROW(CP1:CP1000) = 1, "6段目", IF(#REF!<>"", IFERROR( VLOOKUP( #REF!, { INDIRECT("'CSV貼り付け'!"& SUBSTITUTE(ADDRESS(2, MATCH("LINE番号", 'CSV貼り付け'!$1:$1, 0)), "$", "") & ":" & SUBSTITUTE(ADDRESS(ROWS('CSV貼り付け'!$A:$A), MATCH("LINE番号", 'CSV貼り付け'!$1:$1, 0)), "$", "") ), INDIRECT("'CSV貼り付け'!"& SUBSTITUTE(ADDRESS(2, MATCH("6段目", 'CSV貼り付け'!$1:$1, 0)), "$", "") & ":" & SUBSTITUTE(ADDRESS(ROWS('CSV貼り付け'!$A:$A), MATCH("6段目", 'CSV貼り付け'!$1:$1, 0)), "$", "") ) }, 2, FALSE ), "" ),"") )} -> 6段目 | CQ1: {=IF( ROW(CQ1:CQ1000) = 1, "7段目", IF(#REF!<>"", IFERROR( VLOOKUP( #REF!, { INDIRECT("'CSV貼り付け'!"& SUBSTITUTE(ADDRESS(2, MATCH("LINE番号", 'CSV貼り付け'!$1:$1, 0)), "$", "") & ":" & SUBSTITUTE(ADDRESS(ROWS('CSV貼り付け'!$A:$A), MATCH("LINE番号", 'CSV貼り付け'!$1:$1, 0)), "$", "") ), INDIRECT("'CSV貼り付け'!"& SUBSTITUTE(ADDRESS(2, MATCH("7段目", 'CSV貼り付け'!$1:$1, 0)), "$", "") & ":" & SUBSTITUTE(ADDRESS(ROWS('CSV貼り付け'!$A:$A), MATCH("7段目", 'CSV貼り付け'!$1:$1, 0)), "$", "") ) }, 2, FALSE ), "" ),"") )} -> 7段目 | CR1: {=IF( ROW(CR1:CR1000) = 1, "8段目", IF(#REF!<>"", IFERROR( VLOOKUP( #REF!, { INDIRECT("'CSV貼り付け'!"& SUBSTITUTE(ADDRESS(2, MATCH("LINE番号", 'CSV貼り付け'!$1:$1, 0)), "$", "") & ":" & SUBSTITUTE(ADDRESS(ROWS('CSV貼り付け'!$A:$A), MATCH("LINE番号", 'CSV貼り付け'!$1:$1, 0)), "$", "") ), INDIRECT("'CSV貼り付け'!"& SUBSTITUTE(ADDRESS(2, MATCH("8段目", 'CSV貼り付け'!$1:$1, 0)), "$", "") & ":" & SUBSTITUTE(ADDRESS(ROWS('CSV貼り付け'!$A:$A), MATCH("8段目", 'CSV貼り付け'!$1:$1, 0)), "$", "") ) }, 2, FALSE ), "" ),"") )} -> 8段目 | CS1: {=IF( ROW(CS1:CS1000) = 1, "9段目", IF(#REF!<>"", IFERROR( VLOOKUP( #REF!, { INDIRECT("'CSV貼り付け'!"& SUBSTITUTE(ADDRESS(2, MATCH("LINE番号", 'CSV貼り付け'!$1:$1, 0)), "$", "") & ":" & SUBSTITUTE(ADDRESS(ROWS('CSV貼り付け'!$A:$A), MATCH("LINE番号", 'CSV貼り付け'!$1:$1, 0)), "$", "") ), INDIRECT("'CSV貼り付け'!"& SUBSTITUTE(ADDRESS(2, MATCH("9段目", 'CSV貼り付け'!$1:$1, 0)), "$", "") & ":" & SUBSTITUTE(ADDRESS(ROWS('CSV貼り付け'!$A:$A), MATCH("9段目", 'CSV貼り付け'!$1:$1, 0)), "$", "") ) }, 2, FALSE ), "" ),"") )} -> 9段目 | CT1: {=IF( ROW(CT1:CT1000) = 1, "10段目", IF(#REF!<>"", IFERROR( VLOOKUP( #REF!, { INDIRECT("'CSV貼り付け'!"& SUBSTITUTE(ADDRESS(2, MATCH("LINE番号", 'CSV貼り付け'!$1:$1, 0)), "$", "") & ":" & SUBSTITUTE(ADDRESS(ROWS('CSV貼り付け'!$A:$A), MATCH("LINE番号", 'CSV貼り付け'!$1:$1, 0)), "$", "") ), INDIRECT("'CSV貼り付け'!"& SUBSTITUTE(ADDRESS(2, MATCH("10段目", 'CSV貼り付け'!$1:$1, 0)), "$", "") & ":" & SUBSTITUTE(ADDRESS(ROWS('CSV貼り付け'!$A:$A), MATCH("10段目", 'CSV貼り付け'!$1:$1, 0)), "$", "") ) }, 2, FALSE ), "" ),"") )} -> 10段目 | CU1: 貸付調査回答 | CV1: {=IF( ROW(CV1:CV1000) = 1, "uid", IF(#REF!<>"", IFERROR( VLOOKUP( #REF!, { INDIRECT("'CSV貼り付け'!"& SUBSTITUTE(ADDRESS(2, MATCH("LINE番号", 'CSV貼り付け'!$1:$1, 0)), "$", "") & ":" & SUBSTITUTE(ADDRESS(ROWS('CSV貼り付け'!$A:$A), MATCH("LINE番号", 'CSV貼り付け'!$1:$1, 0)), "$", "") ), INDIRECT("'CSV貼り付け'!"& SUBSTITUTE(ADDRESS(2, MATCH("uid", 'CSV貼り付け'!$1:$1, 0)), "$", "") & ":" & SUBSTITUTE(ADDRESS(ROWS('CSV貼り付け'!$A:$A), MATCH("uid", 'CSV貼り付け'!$1:$1, 0)), "$", "") ) }, 2, FALSE ), "" ),"") )} -> uid
F2: 45804 | G2: 佐藤 | H2: KSN01-0000001 | I2: 完了 | K2: 各種資料保管用 GoogleドライブURL | L2: 申請支援契約書（通称：違約金契約書）, 1_請求明細書, 従業員一覧, 支払証憑, 口座情報, ソフトウェアキャプチャ, 利用規約 | M2: 0000@gmail.com | S2: 概要案内シートより転記 | AI2: あり | AJ2: 45865 | AK2: 完了 | AL2: 佐藤 | AM2: 事務所 | AN2: 2660000 | AO2: - | AQ2: 45911 | AS2: 完了 | AT2: 45912 | AU2: 完了 | AV2: {=IFERROR( INDEX(#REF!,MATCH(H2,'従業員一覧フォーム'!$D:$D,0),MATCH("従業員一覧を提出してください。",'従業員一覧フォーム'!$1:$1,0)) ,"未提出")} -> 未提出 | AX2: 書類作成済み | AY2: 45918 | AZ2: 完了 | BA2: 45930 | BB2: 完了 | BC2: 45945 | BD2: 完了 | BE2: 45945 | BF2: 完了 | BG2: 45952 | BH2: 完了 | BI2: 45952 | BJ2: #REF! | BL2: #REF! | BM2: #REF! | BN2: 45976 | BO2: 完了 | BP2: #REF! | BR2: #REF! | BS2: #REF! | BT2: 45976 | BU2: コミット | BV2: #REF! | BX2: #REF! | BY2: #REF! | CB2: #REF! | CD2: #REF! | CE2: #REF! | CH2: 株式会社エイトフューチャー② | CI2: システムクラウド① | CK2: #REF! | CL2: #REF! | CM2: #REF! | CN2: #REF! | CO2: #REF! | CP2: #REF! | CQ2: #REF! | CR2: #REF! | CS2: #REF! | CT2: #REF! | CU2: =IF(AD2<>"", IF(COUNTIF(#REF!,H2)>0,"回答済み","未回答"), "") | CV2: #REF!
BJ3: #REF! | BL3: #REF! | BM3: #REF! | BP3: #REF! | BR3: #REF! | BS3: #REF! | BV3: #REF! | BX3: #REF! | BY3: #REF! | CB3: #REF! | CD3: #REF! | CE3: #REF! | CK3: #REF! | CL3: #REF! | CM3: #REF! | CN3: #REF! | CO3: #REF! | CP3: #REF! | CQ3: #REF! | CR3: #REF! | CS3: #REF! | CT3: #REF! | CV3: #REF!
A4: BPO側が入力する項目 | BJ4: #REF! | BL4: #REF! | BM4: #REF! | BP4: #REF! | BR4: #REF! | BS4: #REF! | BV4: #REF! | BX4: #REF! | BY4: #REF! | CB4: #REF! | CD4: #REF! | CE4: #REF! | CK4: #REF! | CL4: #REF! | CM4: #REF! | CN4: #REF! | CO4: #REF! | CP4: #REF! | CQ4: #REF! | CR4: #REF! | CS4: #REF! | CT4: #REF! | CV4: #REF!
BJ5: #REF! | BL5: #REF! | BM5: #REF! | BP5: #REF! | BR5: #REF! | BS5: #REF! | BV5: #REF! | BX5: #REF! | BY5: #REF! | CB5: #REF! | CD5: #REF! | CE5: #REF! | CK5: #REF! | CL5: #REF! | CM5: #REF! | CN5: #REF! | CO5: #REF! | CP5: #REF! | CQ5: #REF! | CR5: #REF! | CS5: #REF! | CT5: #REF! | CV5: #REF!
BJ6: #REF! | BL6: #REF! | BM6: #REF! | BP6: #REF! | BR6: #REF! | BS6: #REF! | BV6: #REF! | BX6: #REF! | BY6: #REF! | CB6: #REF! | CD6: #REF! | CE6: #REF! | CK6: #REF! | CL6: #REF! | CM6: #REF! | CN6: #REF! | CO6: #REF! | CP6: #REF! | CQ6: #REF! | CR6: #REF! | CS6: #REF! | CT6: #REF! | CV6: #REF!
BJ7: #REF! | BL7: #REF! | BM7: #REF! | BP7: #REF! | BR7: #REF! | BS7: #REF! | BV7: #REF! | BX7: #REF! | BY7: #REF! | CB7: #REF! | CD7: #REF! | CE7: #REF! | CK7: #REF! | CL7: #REF! | CM7: #REF! | CN7: #REF! | CO7: #REF! | CP7: #REF! | CQ7: #REF! | CR7: #REF! | CS7: #REF! | CT7: #REF! | CV7: #REF!
BJ8: #REF! | BL8: #REF! | BM8: #REF! | BP8: #REF! | BR8: #REF! | BS8: #REF! | BV8: #REF! | BX8: #REF! | BY8: #REF! | CB8: #REF! | CD8: #REF! | CE8: #REF! | CK8: #REF! | CL8: #REF! | CM8: #REF! | CN8: #REF! | CO8: #REF! | CP8: #REF! | CQ8: #REF! | CR8: #REF! | CS8: #REF! | CT8: #REF! | CV8: #REF!
BJ9: #REF! | BL9: #REF! | BM9: #REF! | BP9: #REF! | BR9: #REF! | BS9: #REF! | BV9: #REF! | BX9: #REF! | BY9: #REF! | CB9: #REF! | CD9: #REF! | CE9: #REF! | CK9: #REF! | CL9: #REF! | CM9: #REF! | CN9: #REF! | CO9: #REF! | CP9: #REF! | CQ9: #REF! | CR9: #REF! | CS9: #REF! | CT9: #REF! | CV9: #REF!
BJ10: #REF! | BL10: #REF! | BM10: #REF! | BP10: #REF! | BR10: #REF! | BS10: #REF! | BV10: #REF! | BX10: #REF! | BY10: #REF! | CB10: #REF! | CD10: #REF! | CE10: #REF! | CK10: #REF! | CL10: #REF! | CM10: #REF! | CN10: #REF! | CO10: #REF! | CP10: #REF! | CQ10: #REF! | CR10: #REF! | CS10: #REF! | CT10: #REF! | CV10: #REF!
BJ11: #REF! | BL11: #REF! | BM11: #REF! | BP11: #REF! | BR11: #REF! | BS11: #REF! | BV11: #REF! | BX11: #REF! | BY11: #REF! | CB11: #REF! | CD11: #REF! | CE11: #REF! | CK11: #REF! | CL11: #REF! | CM11: #REF! | CN11: #REF! | CO11: #REF! | CP11: #REF! | CQ11: #REF! | CR11: #REF! | CS11: #REF! | CT11: #REF! | CV11: #REF!
BJ12: #REF! | BL12: #REF! | BM12: #REF! | BP12: #REF! | BR12: #REF! | BS12: #REF! | BV12: #REF! | BX12: #REF! | BY12: #REF! | CB12: #REF! | CD12: #REF! | CE12: #REF! | CK12: #REF! | CL12: #REF! | CM12: #REF! | CN12: #REF! | CO12: #REF! | CP12: #REF! | CQ12: #REF! | CR12: #REF! | CS12: #REF! | CT12: #REF! | CV12: #REF!
BJ13: #REF! | BL13: #REF! | BM13: #REF! | BP13: #REF! | BR13: #REF! | BS13: #REF! | BV13: #REF! | BX13: #REF! | BY13: #REF! | CB13: #REF! | CD13: #REF! | CE13: #REF! | CK13: #REF! | CL13: #REF! | CM13: #REF! | CN13: #REF! | CO13: #REF! | CP13: #REF! | CQ13: #REF! | CR13: #REF! | CS13: #REF! | CT13: #REF! | CV13: #REF!
BJ14: #REF! | BL14: #REF! | BM14: #REF! | BP14: #REF! | BR14: #REF! | BS14: #REF! | BV14: #REF! | BX14: #REF! | BY14: #REF! | CB14: #REF! | CD14: #REF! | CE14: #REF! | CK14: #REF! | CL14: #REF! | CM14: #REF! | CN14: #REF! | CO14: #REF! | CP14: #REF! | CQ14: #REF! | CR14: #REF! | CS14: #REF! | CT14: #REF! | CV14: #REF!
BJ15: #REF! | BL15: #REF! | BM15: #REF! | BP15: #REF! | BR15: #REF! | BS15: #REF! | BV15: #REF! | BX15: #REF! | BY15: #REF! | CB15: #REF! | CD15: #REF! | CE15: #REF! | CK15: #REF! | CL15: #REF! | CM15: #REF! | CN15: #REF! | CO15: #REF! | CP15: #REF! | CQ15: #REF! | CR15: #REF! | CS15: #REF! | CT15: #REF! | CV15: #REF!
BJ16: #REF! | BL16: #REF! | BM16: #REF! | BP16: #REF! | BR16: #REF! | BS16: #REF! | BV16: #REF! | BX16: #REF! | BY16: #REF! | CB16: #REF! | CD16: #REF! | CE16: #REF! | CK16: #REF! | CL16: #REF! | CM16: #REF! | CN16: #REF! | CO16: #REF! | CP16: #REF! | CQ16: #REF! | CR16: #REF! | CS16: #REF! | CT16: #REF! | CV16: #REF!
... BJ1000: #REF! | BL1000: #REF! | BM1000: #REF! | BP1000: #REF! | BR1000: #REF! | BS1000: #REF! | BV1000: #REF! | BX1000: #REF! | BY1000: #REF! | CB1000: #REF! | CD1000: #REF! | CE1000: #REF! | CK1000: #REF! | CL1000: #REF! | CM1000: #REF! | CN1000: #REF! | CO1000: #REF! | CP1000: #REF! | CQ1000: #REF! | CR1000: #REF! | CS1000: #REF! | CT1000: #REF! | CV1000: #REF!
